Workbook

Sheet Capa
A1: Análise de Pontos de Função — entrega coletiva
A3: Projeto | B3: Estoque Inteligente
A5: Integrantes | B5: Artur Ribeiro de Souza Cristhian Ruan de Rezende Lucas Andriani Theiss
A7: Versão | B7: Branch entrega-trabalho — conclusão da revisão de 25/10/2026
A9: Escopo | B9: Aplicação completa, contagem sem sobreposição dos três recortes individuais.
A11: Leitura | B11: Resumo → Catálogo → fichas por ID → Matrizes → NI e estimativas → Conferência.
A13: Resultado | B13: Fórmulas nativas editáveis; resultados e premissas nas abas seguintes.
A15: Ressalvas | B15: Notas NI são avaliação técnica com premissas acadêmicas explícitas. Capturas reais incluem dados de demonstração e simulador IoT identificado. Os três recortes individuais são documentos históricos preservados.

Sheet Resumo
A1: Resultado coletivo e reconciliação
A3: Tipo | B3: Quantidade | C3: PF | D3: Regra
A4: ALI | B4: =COUNTIF(Catálogo!$B$4:$B$58,A4) -> 9 | C4: =SUMIF(Catálogo!$B$4:$B$58,A4,Catálogo!$G$4:$G$58) -> 63 | D4: Uma função por ID, sem somar recortes.
A5: AIE | B5: =COUNTIF(Catálogo!$B$4:$B$58,A5) -> 2 | C5: =SUMIF(Catálogo!$B$4:$B$58,A5,Catálogo!$G$4:$G$58) -> 10 | D5: Uma função por ID, sem somar recortes.
A6: EE | B6: =COUNTIF(Catálogo!$B$4:$B$58,A6) -> 28 | C6: =SUMIF(Catálogo!$B$4:$B$58,A6,Catálogo!$G$4:$G$58) -> 135 | D6: Uma função por ID, sem somar recortes.
A7: SE | B7: =COUNTIF(Catálogo!$B$4:$B$58,A7) -> 8 | C7: =SUMIF(Catálogo!$B$4:$B$58,A7,Catálogo!$G$4:$G$58) -> 48 | D7: Uma função por ID, sem somar recortes.
A8: CE | B8: =COUNTIF(Catálogo!$B$4:$B$58,A8) -> 8 | C8: =SUMIF(Catálogo!$B$4:$B$58,A8,Catálogo!$G$4:$G$58) -> 27 | D8: Uma função por ID, sem somar recortes.
A10: PFB | B10: =SUM(C4:C8) -> 283
A11: NI | B11: ='NI e estimativas'!B19 -> 38
A12: FA | B12: ='NI e estimativas'!B22 -> 1.03
A13: PFA | B13: =B10*B12 -> 291.49
A15: Mudança funcional | B15: CE10 passa a SE10: indicador de estorno é derivado por EXISTS e exibido. Não é função nova; diferença de peso: 6 para 7 PF.
A17: Mudança no NI | B17: Desempenho 1→0; implantação 2→1; operação 2→1. Notas altas exigiam evidências não demonstradas. Premissas de volume e múltiplos locais continuam explícitas.
A19: Cobertura do enunciado | B19: Destaque de quatro CEs: CE04, CE05, CE08, CE12. SEs numéricas: SE02, SE04, SE06, SE07, SE08 e SE13. Todas as funções restantes permanecem no coletivo.
A21: Estimativa | B21: Desenvolvimento do sistema inteiro. Não é prazo restante da atividade. Ver premissas e fórmulas em NI e estimativas.

Sheet Catálogo
A1: Catálogo coletivo — uma linha por função
A3: ID | B3: Tipo | C3: Função | D3: TD | E3: AR / RL | F3: Complexidade | G3: PF | H3: Ficha
A4: A01 | B4: ALI | C4: Modelos de produto | D4: =A01!B60 -> 5 | E4: =A01!D60 -> 1 | F4: =A01!D64 -> Simples | G4: =A01!D65 -> 7 | H4: =HYPERLINK("#'A01'!A1","Abrir A01") -> Abrir A01
A5: A02 | B5: ALI | C5: Produtos | D5: =A02!B60 -> 11 | E5: =A02!D60 -> 1 | F5: =A02!D64 -> Simples | G5: =A02!D65 -> 7 | H5: =HYPERLINK("#'A02'!A1","Abrir A02") -> Abrir A02
A6: A03 | B6: ALI | C6: Posições | D6: =A03!B60 -> 11 | E6: =A03!D60 -> 1 | F6: =A03!D64 -> Simples | G6: =A03!D65 -> 7 | H6: =HYPERLINK("#'A03'!A1","Abrir A03") -> Abrir A03
A7: A04 | B7: ALI | C7: Estoque por posição / vínculos | D7: =A04!B60 -> 4 | E7: =A04!D60 -> 1 | F7: =A04!D64 -> Simples | G7: =A04!D65 -> 7 | H7: =HYPERLINK("#'A04'!A1","Abrir A04") -> Abrir A04
A8: A05 | B8: ALI | C8: Movimentações | D8: =A05!B60 -> 12 | E8: =A05!D60 -> 1 | F8: =A05!D64 -> Simples | G8: =A05!D65 -> 7 | H8: =HYPERLINK("#'A05'!A1","Abrir A05") -> Abrir A05
A9: A06 | B9: ALI | C9: Usuários | D9: =A06!B60 -> 6 | E9: =A06!D60 -> 1 | F9: =A06!D64 -> Simples | G9: =A06!D65 -> 7 | H9: =HYPERLINK("#'A06'!A1","Abrir A06") -> Abrir A06
A10: A07 | B10: ALI | C10: Permissões por perfil | D10: =A07!B60 -> 3 | E10: =A07!D60 -> 1 | F10: =A07!D64 -> Simples | G10: =A07!D65 -> 7 | H10: =HYPERLINK("#'A07'!A1","Abrir A07") -> Abrir A07
A11: A08 | B11: ALI | C11: Lojas e configuração | D11: =A08!B60 -> 12 | E11: =A08!D60 -> 1 | F11: =A08!D64 -> Simples | G11: =A08!D65 -> 7 | H11: =HYPERLINK("#'A08'!A1","Abrir A08") -> Abrir A08
A12: A09 | B12: ALI | C12: Auditoria consultável | D12: =A09!B60 -> 6 | E12: =A09!D60 -> 1 | F12: =A09!D64 -> Simples | G12: =A09!D65 -> 7 | H12: =HYPERLINK("#'A09'!A1","Abrir A09") -> Abrir A09
A13: X01 | B13: AIE | C13: Fornecedores externos | D13: =X01!B60 -> 5 | E13: =X01!D60 -> 1 | F13: =X01!D64 -> Simples | G13: =X01!D65 -> 5 | H13: =HYPERLINK("#'X01'!A1","Abrir X01") -> Abrir X01
A14: X02 | B14: AIE | C14: Ofertas externas | D14: =X02!B60 -> 9 | E14: =X02!D60 -> 1 | F14: =X02!D64 -> Simples | G14: =X02!D65 -> 5 | H14: =HYPERLINK("#'X02'!A1","Abrir X02") -> Abrir X02
A15: CE04 | B15: CE | C15: Consultar fornecedores externos | D15: =CE04!B60 -> 8 | E15: =CE04!D60 -> 1 | F15: =CE04!D64 -> Simples | G15: =CE04!D65 -> 3 | H15: =HYPERLINK("#'CE04'!A1","Abrir CE04") -> Abrir CE04
A16: CE05 | B16: CE | C16: Consultar modelos | D16: =CE05!B60 -> 6 | E16: =CE05!D60 -> 1 | F16: =CE05!D64 -> Simples | G16: =CE05!D65 -> 3 | H16: =HYPERLINK("#'CE05'!A1","Abrir CE05") -> Abrir CE05
A17: CE06 | B17: CE | C17: Consultar vínculos | D17: =CE06!B60 -> 10 | E17: =CE06!D60 -> 4 | F17: =CE06!D64 -> Complexa | G17: =CE06!D65 -> 6 | H17: =HYPERLINK("#'CE06'!A1","Abrir CE06") -> Abrir CE06
A18: CE07 | B18: CE | C18: Consultar equipe e permissões | D18: =CE07!B60 -> 6 | E18: =CE07!D60 -> 2 | F18: =CE07!D64 -> Simples | G18: =CE07!D65 -> 3 | H18: =HYPERLINK("#'CE07'!A1","Abrir CE07") -> Abrir CE07
A19: CE08 | B19: CE | C19: Consultar lojas | D19: =CE08!B60 -> 9 | E19: =CE08!D60 -> 1 | F19: =CE08!D64 -> Simples | G19: =CE08!D65 -> 3 | H19: =HYPERLINK("#'CE08'!A1","Abrir CE08") -> Abrir CE08
A20: CE09 | B20: CE | C20: Consultar configuração IoT | D20: =CE09!B60 -> 6 | E20: =CE09!D60 -> 1 | F20: =CE09!D64 -> Simples | G20: =CE09!D65 -> 3 | H20: =HYPERLINK("#'CE09'!A1","Abrir CE09") -> Abrir CE09
A21: CE11 | B21: CE | C21: Consultar auditoria | D21: =CE11!B60 -> 6 | E21: =CE11!D60 -> 2 | F21: =CE11!D64 -> Simples | G21: =CE11!D65 -> 3 | H21: =HYPERLINK("#'CE11'!A1","Abrir CE11") -> Abrir CE11
A22: CE12 | B22: CE | C22: Consultar ofertas externas | D22: =CE12!B60 -> 11 | E22: =CE12!D60 -> 1 | F22: =CE12!D64 -> Simples | G22: =CE12!D65 -> 3 | H22: =HYPERLINK("#'CE12'!A1","Abrir CE12") -> Abrir CE12
A23: EE01 | B23: EE | C23: Incluir produto, inclusive grade e saldo inicial | D23: =EE01!B60 -> 16 | E23: =EE01!D60 -> 6 | F23: =EE01!D64 -> Complexa | G23: =EE01!D65 -> 6 | H23: =HYPERLINK("#'EE01'!A1","Abrir EE01") -> Abrir EE01
A24: EE02 | B24: EE | C24: Alterar produto | D24: =EE02!B60 -> 13 | E24: =EE02!D60 -> 4 | F24: =EE02!D64 -> Complexa | G24: =EE02!D65 -> 6 | H24: =HYPERLINK("#'EE02'!A1","Abrir EE02") -> Abrir EE02
A25: EE03 | B25: EE | C25: Excluir produto logicamente | D25: =EE03!B60 -> 3 | E25: =EE03!D60 -> 3 | F25: =EE03!D64 -> Moderada | G25: =EE03!D65 -> 4 | H25: =HYPERLINK("#'EE03'!A1","Abrir EE03") -> Abrir EE03
A26: EE04 | B26: EE | C26: Incluir modelo | D26: =EE04!B60 -> 5 | E26: =EE04!D60 -> 2 | F26: =EE04!D64 -> Moderada | G26: =EE04!D65 -> 4 | H26: =HYPERLINK("#'EE04'!A1","Abrir EE04") -> Abrir EE04
A27: EE05 | B27: EE | C27: Alterar modelo | D27: =EE05!B60 -> 6 | E27: =EE05!D60 -> 2 | F27: =EE05!D64 -> Moderada | G27: =EE05!D65 -> 4 | H27: =HYPERLINK("#'EE05'!A1","Abrir EE05") -> Abrir EE05
A28: EE06 | B28: EE | C28: Excluir modelo | D28: =EE06!B60 -> 3 | E28: =EE06!D60 -> 3 | F28: =EE06!D64 -> Moderada | G28: =EE06!D65 -> 4 | H28: =HYPERLINK("#'EE06'!A1","Abrir EE06") -> Abrir EE06
A29: EE07 | B29: EE | C29: Incluir posição | D29: =EE07!B60 -> 10 | E29: =EE07!D60 -> 2 | F29: =EE07!D64 -> Moderada | G29: =EE07!D65 -> 4 | H29: =HYPERLINK("#'EE07'!A1","Abrir EE07") -> Abrir EE07
A30: EE08 | B30: EE | C30: Alterar posição | D30: =EE08!B60 -> 11 | E30: =EE08!D60 -> 3 | F30: =EE08!D64 -> Complexa | G30: =EE08!D65 -> 6 | H30: =HYPERLINK("#'EE08'!A1","Abrir EE08") -> Abrir EE08
A31: EE09 | B31: EE | C31: Excluir posição logicamente | D31: =EE09!B60 -> 3 | E31: =EE09!D60 -> 3 | F31: =EE09!D64 -> Moderada | G31: =EE09!D65 -> 4 | H31: =HYPERLINK("#'EE09'!A1","Abrir EE09") -> Abrir EE09
A32: EE10 | B32: EE | C32: Incluir vínculo | D32: =EE10!B60 -> 4 | E32: =EE10!D60 -> 4 | F32: =EE10!D64 -> Moderada | G32: =EE10!D65 -> 4 | H32: =HYPERLINK("#'EE10'!A1","Abrir EE10") -> Abrir EE10
A33: EE11 | B33: EE | C33: Alterar vínculo vazio | D33: =EE11!B60 -> 6 | E33: =EE11!D60 -> 4 | F33: =EE11!D64 -> Complexa | G33: =EE11!D65 -> 6 | H33: =HYPERLINK("#'EE11'!A1","Abrir EE11") -> Abrir EE11
A34: EE12 | B34: EE | C34: Excluir vínculo vazio | D34: =EE12!B60 -> 4 | E34: =EE12!D60 -> 4 | F34: =EE12!D64 -> Moderada | G34: =EE12!D65 -> 4 | H34: =HYPERLINK("#'EE12'!A1","Abrir EE12") -> Abrir EE12
A35: EE13 | B35: EE | C35: Incluir usuário | D35: =EE13!B60 -> 5 | E35: =EE13!D60 -> 3 | F35: =EE13!D64 -> Complexa | G35: =EE13!D65 -> 6 | H35: =HYPERLINK("#'EE13'!A1","Abrir EE13") -> Abrir EE13
A36: EE14 | B36: EE | C36: Alterar usuário | D36: =EE14!B60 -> 6 | E36: =EE14!D60 -> 3 | F36: =EE14!D64 -> Complexa | G36: =EE14!D65 -> 6 | H36: =HYPERLINK("#'EE14'!A1","Abrir EE14") -> Abrir EE14
A37: EE15 | B37: EE | C37: Excluir usuário logicamente | D37: =EE15!B60 -> 5 | E37: =EE15!D60 -> 3 | F37: =EE15!D64 -> Complexa | G37: =EE15!D65 -> 6 | H37: =HYPERLINK("#'EE15'!A1","Abrir EE15") -> Abrir EE15
A38: EE16 | B38: EE | C38: Incluir loja e administrador | D38: =EE16!B60 -> 10 | E38: =EE16!D60 -> 4 | F38: =EE16!D64 -> Complexa | G38: =EE16!D65 -> 6 | H38: =HYPERLINK("#'EE16'!A1","Abrir EE16") -> Abrir EE16
A39: EE17 | B39: EE | C39: Alterar loja e recursos | D39: =EE17!B60 -> 9 | E39: =EE17!D60 -> 3 | F39: =EE17!D64 -> Complexa | G39: =EE17!D65 -> 6 | H39: =HYPERLINK("#'EE17'!A1","Abrir EE17") -> Abrir EE17
A40: EE18 | B40: EE | C40: Excluir loja logicamente | D40: =EE18!B60 -> 3 | E40: =EE18!D60 -> 2 | F40: =EE18!D64 -> Simples | G40: =EE18!D65 -> 3 | H40: =HYPERLINK("#'EE18'!A1","Abrir EE18") -> Abrir EE18
A41: EE19 | B41: EE | C41: Alterar matriz de permissões | D41: =EE19!B60 -> 5 | E41: =EE19!D60 -> 2 | F41: =EE19!D64 -> Moderada | G41: =EE19!D65 -> 4 | H41: =HYPERLINK("#'EE19'!A1","Abrir EE19") -> Abrir EE19
A42: EE20 | B42: EE | C42: Alterar configuração IoT | D42: =EE20!B60 -> 6 | E42: =EE20!D60 -> 2 | F42: =EE20!D64 -> Moderada | G42: =EE20!D65 -> 4 | H42: =HYPERLINK("#'EE20'!A1","Abrir EE20") -> Abrir EE20
A43: EE21 | B43: EE | C43: Registrar entrada | D43: =EE21!B60 -> 7 | E43: =EE21!D60 -> 5 | F43: =EE21!D64 -> Complexa | G43: =EE21!D65 -> 6 | H43: =HYPERLINK("#'EE21'!A1","Abrir EE21") -> Abrir EE21
A44: EE22 | B44: EE | C44: Registrar saída | D44: =EE22!B60 -> 7 | E44: =EE22!D60 -> 5 | F44: =EE22!D64 -> Complexa | G44: =EE22!D65 -> 6 | H44: =HYPERLINK("#'EE22'!A1","Abrir EE22") -> Abrir EE22
A45: EE23 | B45: EE | C45: Ajustar saldo | D45: =EE23!B60 -> 7 | E45: =EE23!D60 -> 5 | F45: =EE23!D64 -> Complexa | G45: =EE23!D65 -> 6 | H45: =HYPERLINK("#'EE23'!A1","Abrir EE23") -> Abrir EE23
A46: EE24 | B46: EE | C46: Estornar movimentação | D46: =EE24!B60 -> 4 | E46: =EE24!D60 -> 5 | F46: =EE24!D64 -> Moderada | G46: =EE24!D65 -> 4 | H46: =HYPERLINK("#'EE24'!A1","Abrir EE24") -> Abrir EE24
A47: EE25 | B47: EE | C47: Autenticar usuário | D47: =EE25!B60 -> 5 | E47: =EE25!D60 -> 3 | F47: =EE25!D64 -> Complexa | G47: =EE25!D65 -> 6 | H47: =HYPERLINK("#'EE25'!A1","Abrir EE25") -> Abrir EE25
A48: EE26 | B48: EE | C48: Selecionar loja de trabalho | D48: =EE26!B60 -> 3 | E48: =EE26!D60 -> 2 | F48: =EE26!D64 -> Simples | G48: =EE26!D65 -> 3 | H48: =HYPERLINK("#'EE26'!A1","Abrir EE26") -> Abrir EE26
A49: EE27 | B49: EE | C49: Sinalizar posição por LED | D49: =EE27!B60 -> 3 | E49: =EE27!D60 -> 3 | F49: =EE27!D64 -> Moderada | G49: =EE27!D65 -> 4 | H49: =HYPERLINK("#'EE27'!A1","Abrir EE27") -> Abrir EE27
A50: EE28 | B50: EE | C50: Encerrar sessão | D50: =EE28!B60 -> 2 | E50: =EE28!D60 -> 0 | F50: =EE28!D64 -> Simples | G50: =EE28!D65 -> 3 | H50: =HYPERLINK("#'EE28'!A1","Abrir EE28") -> Abrir EE28
A51: SE02 | B51: SE | C51: Valor potencial do estoque | D51: =SE02!B60 -> 8 | E51: =SE02!D60 -> 2 | F51: =SE02!D64 -> Moderada | G51: =SE02!D65 -> 5 | H51: =HYPERLINK("#'SE02'!A1","Abrir SE02") -> Abrir SE02
A52: SE04 | B52: SE | C52: Fluxo de movimentações | D52: =SE04!B60 -> 9 | E52: =SE04!D60 -> 2 | F52: =SE04!D64 -> Moderada | G52: =SE04!D65 -> 5 | H52: =HYPERLINK("#'SE04'!A1","Abrir SE04") -> Abrir SE04
A53: SE06 | B53: SE | C53: Pesquisar estoque e localizar produto | D53: =SE06!B60 -> 16 | E53: =SE06!D60 -> 4 | F53: =SE06!D64 -> Complexa | G53: =SE06!D65 -> 7 | H53: =HYPERLINK("#'SE06'!A1","Abrir SE06") -> Abrir SE06
A54: SE07 | B54: SE | C54: Mapa operacional de posições | D54: =SE07!B60 -> 13 | E54: =SE07!D60 -> 4 | F54: =SE07!D64 -> Complexa | G54: =SE07!D65 -> 7 | H54: =HYPERLINK("#'SE07'!A1","Abrir SE07") -> Abrir SE07
A55: SE08 | B55: SE | C55: Ler peso líquido e subtotal | D55: =SE08!B60 -> 9 | E55: =SE08!D60 -> 2 | F55: =SE08!D64 -> Moderada | G55: =SE08!D65 -> 5 | H55: =HYPERLINK("#'SE08'!A1","Abrir SE08") -> Abrir SE08
A56: SE09 | B56: SE | C56: Exportar histórico | D56: =SE09!B60 -> 13 | E56: =SE09!D60 -> 6 | F56: =SE09!D64 -> Complexa | G56: =SE09!D65 -> 7 | H56: =HYPERLINK("#'SE09'!A1","Abrir SE09") -> Abrir SE09
A57: SE10 | B57: SE | C57: Consultar histórico operacional | D57: =SE10!B60 -> 13 | E57: =SE10!D60 -> 5 | F57: =SE10!D64 -> Complexa | G57: =SE10!D65 -> 7 | H57: =HYPERLINK("#'SE10'!A1","Abrir SE10") -> Abrir SE10
A58: SE13 | B58: SE | C58: Comparar preços internos e ofertas externas | D58: =SE13!B60 -> 12 | E58: =SE13!D60 -> 2 | F58: =SE13!D64 -> Moderada | G58: =SE13!D65 -> 5 | H58: =HYPERLINK("#'SE13'!A1","Abrir SE13") -> Abrir SE13

Sheet Matrizes
A1: Matrizes e pesos da disciplina
A2: Convenção | B2: Índice 1 = simples; 2 = moderada; 3 = complexa. Matriz comum; limites por tipo abaixo.
A4: Faixa AR/RL × faixa TD | B4: TD baixo | C4: TD médio | D4: TD alto
A5: AR/RL baixo | B5: 1 | C5: 1 | D5: 2
A6: AR/RL médio | B6: 1 | C6: 2 | D6: 3
A7: AR/RL alto | B7: 2 | C7: 3 | D7: 3
B10: Simples | C10: Moderada | D10: Complexa
A12: Tipo | B12: Simples | C12: Moderada | D12: Complexa
A13: ALI | B13: 7 | C13: 10 | D13: 15
A14: AIE | B14: 5 | C14: 7 | D14: 10
A15: EE | B15: 3 | C15: 4 | D15: 6
A16: SE | B16: 4 | C16: 5 | D16: 7
A17: CE | B17: 3 | C17: 4 | D17: 6
A19: ALI/AIE | B19: TD 1–19 / 20–50 / 51+. RL 1 / 2–5 / 6+. Parte I, p. 19 e 28.
A20: EE / entrada CE | B20: TD 1–4 / 5–15 / 16+. AR 0–1 / 2 / 3+. Parte II EE, p. 9; Parte III, p. 10.
A21: SE / saída CE | B21: TD 1–5 / 6–19 / 20+. AR 0–1 / 2–3 / 4+. Parte II SE, p. 9; Parte III, p. 12.
A23: CE | B23: Escolher a maior complexidade das duas avaliações. Pesos 3/4/6, inclusive na saída da CE.
A25: Diferença do modelo | B25: O modelo original aplica matriz única ao total da CE. Corrigido aqui conforme Parte III, p. 10–13. Original preservado.
A27: FA | B27: Parte IV, p. 11: 0,65 + 0,01 × NI. A p. 15 usa 0,35 e limites incoerentes; adotada p. 11.

Sheet NI e estimativas
A1: NI e estimativas — premissas editáveis
A3: Característica | B3: Nota (0 a 5) | C3: Justificativa | D3: Evidência / natureza
A4: Comunicação de dados | B4: 5 | C4: Aplicação on-line com HTTP e MQTT; novo cliente HTTP de fornecedores. Mais de um protocolo. | D4: MqttGateway, controllers e FornecedorGateway — avaliação documental; não implica consenso da equipe.
A5: Processamento distribuído | B5: 3 | C5: Envia comandos para processamento no controlador IoT. Retorno de telemetria não demonstra transferência de processamento nas duas direções nem escolha dinâmica de CPU. | D5: IoTService.sinalizar — avaliação documental; não implica consenso da equipe.
A6: Desempenho | B6: 0 | C6: Timeout e paginação não comprovam requisitos de desempenho solicitados e revistos pelo usuário. Sem essa evidência, aplica-se nota 0 da tabela. | D6: application.properties, ProdutoRepository — avaliação documental; não implica consenso da equipe.
A7: Utilização de equipamento | B7: 2 | C7: Compose define limites de memória e pools; há considerações de recursos e segurança. Não exige CPU exclusiva. | D7: compose.yaml — avaliação documental; não implica consenso da equipe.
A8: Volume de transações | B8: 1 | C8: Premissa acadêmica: picos mensais de inventário. Volume real não medido; revisar se houver histórico operacional. | D8: Premissa de estimativa — premissa acadêmica, não fato medido.
A9: Entrada on-line | B9: 5 | C9: Mais de 30% dos processos de entrada são interativos: cadastros, movimentos e configurações. | D9: Controllers web — avaliação documental; não implica consenso da equipe.
A10: Eficiência do usuário final | B10: 4 | C10: Menus, mouse, paginação, navegação, ajuda contextual e poucas telas; redução de digitação por código de barras, voz e balança. Sem medição formal de eficiência. | D10: templates, speech.js, baixa rápida — avaliação documental; não implica consenso da equipe.
A11: Atualização on-line | B11: 4 | C11: Maioria dos ALIs atualizada on-line, com transações, bloqueios e idempotência contra perda/duplicação. Não se assume recuperação de volumes extremos. | D11: EstoqueService, repositories — avaliação documental; não implica consenso da equipe.
A12: Processamento complexo | B12: 2 | C12: Dois critérios: auditoria/segurança específica e lógica de negócio de estorno, saldo e permissões. Não se considera matemática extensiva nem reprocessamento batch complexo. | D12: Acesso, EstoqueService, AuditoriaRepository — avaliação documental; não implica consenso da equipe.
A13: Reutilização de código | B13: 4 | C13: Biblioteca de regras empacotável, documentada e com consumidor externo. Extensões exigem código; não se atribui customização geral por parâmetros. | D13: docs/reuso/README.md, scripts/empacotar-reuso.ps1 — avaliação documental; não implica consenso da equipe.
A14: Facilidade de implantação | B14: 1 | C14: Há procedimento de implantação; migrações Flyway criam/evoluem esquema, mas não comprovam requisitos e roteiros testados de conversão de dados legados. | D14: README, Flyway, Compose — avaliação documental; não implica consenso da equipe.
A15: Facilidade operacional | B15: 1 | C15: Relatórios minimizam papel. Scripts de inicialização, sem procedimento demonstrado de backup e recuperação, não comprovam o critério composto adicional. | D15: scripts/demo.ps1, relatórios — avaliação documental; não implica consenso da equipe.
... A17: Facilidade de mudanças | B17: 4 | C17: Consulta flexível sobre vários ALIs (2) e controles em tabelas alteráveis on-line com efeito imediato, como permissões/recursos (2). | D17: ProdutoRepository.pesquisar, PermissaoService, LojaService — avaliação documental; não implica consenso da equipe.
A19: NI | B19: =SUM(B4:B17) -> 38
A20: Constante FA | B20: 0.65
A21: Coeficiente NI | B21: 0.01
A22: FA | B22: =B20+B21*B19 -> 1.03
A23: PFB | B23: =Resumo!B10 -> 283
A24: PFA | B24: =B23*B22 -> 291.49
A27: Produtividade | B27: 10 | C27: horas-pessoa/PFA; premissa acadêmica
A28: Integrantes | B28: 3 | C28: pessoas com capacidade constante
A29: Jornada | B29: 8 | C29: horas/pessoa/dia útil; premissa
A30: Fração produtiva | B30: 0.75 | C30: 75% da jornada; premissa
A31: Valor-hora | B31: 25 | C31: R$/hora-pessoa; premissa
A32: Dias por semana | B32: 5 | C32: dias úteis/semana; premissa
A33: Reserva | B33: 0 | C33: fração do esforço base; sem contingência
A34: Custos adicionais | B34: 0 | C34: R$; infraestrutura e impostos não estimados
A36: Horas produtivas por pessoa | B36: =B29*B30 -> 6 | C36: h/pessoa/dia útil
A37: Esforço base | B37: =B24*B27 -> 2914.9 | C37: horas-pessoa
A38: Reserva em horas | B38: =B37*B33 -> 0 | C38: horas-pessoa
A39: Esforço total | B39: =SUM(B37:B38) -> 2914.9 | C39: horas-pessoa
A40: Capacidade diária | B40: =B28*B36 -> 18 | C40: horas-pessoa/dia útil
A41: Prazo fracionário | B41: =B39/B40 -> 161.93889 | C41: dias úteis
A42: Prazo arredondado | B42: =ROUNDUP(B41,0) -> 162 | C42: dias úteis inteiros
A43: Prazo em semanas | B43: =B42/B32 -> 32.4 | C43: semanas úteis
A44: Custo | B44: =B39*B31+B34 -> 72872.5 | C44: R$
A46: Esforço restante | B46: Não medido. Não aplicar PFA total como horas restantes para concluir o trabalho acadêmico.
A48: Consenso | B48: Notas são avaliação técnica revisada, com premissas identificadas. Reunião e aprovação coletiva não foram comprovadas.

Sheet Exemplos SE
A1: Exemplos numéricos conferíveis — dados didáticos
A2: Natureza | B2: Entradas fictícias para demonstrar as regras do código. Não são medições nem resultados extraídos das capturas.
A4: Função / cálculo | B4: Entrada 1 | C4: Entrada 2 | D4: Resultado por fórmula
A5: SE02: saldo × preço | B5: 5 | C5: 22 | D5: =ROUND(B5*C5,2) -> 110
A6: SE04: duas variações de entrada | B6: 3 | C6: 7 | D6: =SUM(B6:C6) -> 10
A7: SE06: saldo em duas posições | B7: 3 | C7: 7 | D7: =SUM(B7:C7) -> 10
A8: SE07: ocupado / capacidade | B8: 12 | C8: 10 | D8: =B8/C8 -> 1.2
A9: SE08: bruto − tara (kg) | B9: 1.44 | C9: 0.015 | D9: =B9-C9 -> 1.425
A10: SE08: líquido × preço/kg | B10: =D9 -> 1.425 | C10: 29.9 | D10: =ROUND(B10*C10,2) -> 42.61
A11: SE13: cotação − interno | B11: 89.9 | C11: 249.9 | D11: =ROUND(B11-C11,2) -> -160
A12: SE13: diferença / interno | B12: =D11 -> -160 | C12: =C11 -> 249.9 | D12: =IF(C12=0,"Não aplicável",B12/C12) -> -0.6402561
A13: SE10: reversores encontrados | B13: 1 | C13: 0 | D13: =IF(B13>C13,"Estornado","Sem estorno") -> Estornado
A16: SE02 | B16: Total da loja = soma dos valores por produto arredondados. Preço de venda, não custo histórico nem receita realizada.
A18: SE04 | B18: Duas operações e soma 3+7. Agrupa por produto e tipo. Não soma kg e unidades entre produtos. Datas em America/Sao_Paulo.
A20: SE07 | B20: O sistema compara ocupado > capacidade e apresenta alerta. A razão acima é explicação didática do medidor, não TD adicional contado.
A22: SE08 | B22: Captura real na loja granel: 1,440 kg bruto − 0,015 kg tara = 1,425 kg líquido; × R$ 29,90/kg = R$ 42,61. Simulador MQTT identificado, leitura com até 5 segundos; nenhum movimento registrado.
A24: SE09 | B24: Não atende sozinha ao requisito de valor numérico derivado: saída classificada por manutenção de auditoria. CSV e PDF contam uma função.
A26: SE10 | B26: EXISTS identifica reversor persistido. O status do movimento original é obtido por processamento, não um campo armazenado nele.
A28: Fusos distintos | B28: Fluxo gerencial usa Brasília; histórico/exportação usam UTC. Mesmos filtros de datas podem produzir conjuntos diferentes.

Sheet Critérios e fontes
A1: Critérios, fronteira e fontes
A3: Fronteira | B3: Dentro: aplicação Spring, regras, telas e dados persistidos. Fora: usuários, provedores independentes de fornecedores/ofertas e dispositivos IoT. MQTT transitório não é AIE.
A5: Grupos lógicos | B5: A01 modelos; A02 produtos; A03 posições; A04 vínculos/saldos; A05 movimentos; A06 usuários; A07 permissões; A08 lojas/configuração; A09 auditoria. Cada grupo tem intenção e manutenção próprias.
A7: AIEs | B7: X01 identidade e contato de fornecedores. X02 ofertas comerciais. Cada provedor mantém TSV por CLI independente. Clientes do estoque somente leem; HTTP sozinho não fundamenta AIE.
A9: Operações aplicáveis | B9: CRUD completo nos cadastros; produto/posição/usuário/loja têm exclusão lógica. Modelos sem uso e vínculos vazios têm exclusão física. Movimentos e auditoria não recebem edição/exclusão arbitrária.
A11: Unicidade | B11: IDs únicos no Catálogo. Canais de pesquisa, mapa/ocupação e formatos CSV/PDF não multiplicam funções. Os PFBs individuais não são somados.
A13: TD e controles | B13: Dados internos lidos para validação não são TD adicionais. Um conjunto de comandos e um campo de feedback por processo. Parte II EE p. 8 conta duas mensagens específicas: divergência de convenção explicitada; aceitação acadêmica deve ser confirmada.
A15: CE | B15: Entrada/saída separadas, repetição retirada da saída e MAX dos índices. AR de ambos os lados ficam explícitos. Sem etapa distinta de validação, os arquivos participam da seleção/recuperação da mesma consulta.
A17: Não contados | B17: CSRF, requestKey, fingerprint, versão de sessão, tentativas técnicas de login, healthcheck, tema, polling e paginação. Não são grupos/processos funcionais independentes nesta fronteira.
A19: Modelo visual | B19: docs/exemploEntregaPf.xlsx: fichas em quatro colunas, Arial, seções de contexto, campos, contagem e imagens. Abas ampliadas para catálogo coletivo e todas as 55 funções; não se conserva o recorte de outro sistema.
A21: Matrizes | B21: docs/pdfs/PF - Parte I.pdf p. 19/28; Parte II - EE.pdf p. 5/9; Parte II - SE.pdf p. 5/9; Parte III - CE.pdf p. 4/7/10–13.
A23: NI e planejamento | B23: docs/pdfs/Características Gerais do Software.pdf e PF - Parte IV - V2.pdf p. 9/11/14/15/18. Taxas de produtividade e dinheiro são hipóteses, não valores prescritos pelos slides.
A25: Código | B25: Referências curtas das fichas: Java em src/main/java/br/com/estoque; templates em src/main/resources/templates. Provedores em external/fornecedores e external/ofertas.
... A37: Fusos e limites | B37: Histórico/exportação: UTC e até 5.000 registros; fluxo gerencial: Brasília. Valores de ofertas são demonstrativos; não comprovam preço de mercado.

Sheet Conferência
A1: Atendimento e inconsistências da revisão
A3: ALI/AIE | B3: Atendido documentalmente: 9 ALIs e 2 AIEs, campos, RL, finalidade e código nas fichas.
A5: EE incluir/alterar/excluir | B5: 28 EEs identificadas; CRUD real de modelos executado. Exclusões lógicas/físicas e grupos sem CRUD arbitrário explicados.
A7: Ao menos cinco SEs | B7: Seis saídas numéricas demonstradas por exemplos e código. SE10 reclassificada; SE09 justificada por auditoria.
A9: Quatro CEs com entrada/saída | B9: CE04, CE05, CE08 e CE12 destacadas; oito CEs no coletivo. Protótipos de entrada/saída e TD deduplicados.
A11: Protótipos de todas as funções | B11: 55 fichas com 93 imagens reais incorporadas. Todas as EEs e CEs possuem entrada e saída; balança e LED mostram resposta real do simulador identificado, e SE09 inclui o PDF efetivamente exportado.
A13: Contagem completa | B13: Fórmulas em cada ficha alimentam catálogo e subtotais; cada ID uma vez.
A15: NI e justificativas | B15: 14 notas justificadas em NI e estimativas. Volume e múltiplos locais são premissas acadêmicas; a pontuação é avaliação técnica documental.
A17: FA e PFA | B17: Fórmulas ligadas ao PFB/NI. Divergência 0,35 versus 0,65 dos slides explicada.
A19: Esforço, prazo e custo | B19: Premissas editáveis, unidades e fórmulas; refere-se ao desenvolvimento integral. Esforço restante não medido.
A21: Preservação | B21: Modelo e três planilhas individuais preservados por verificação de SHA-256.
A23: Inconsistência CE06 | B23: Ficha anterior confundia campos internos do DTO com saída exibida. Removidos cinco campos não exibidos; adicionado código da posição.
A25: Inconsistência CE10 | B25: Status Estornado calculado por EXISTS não estava na ficha. Reclassificado como SE10, sem duplicação de função.
... A35: Pendência acadêmica | B35: Convenções de contagem e premissas estão explícitas. Não se declara consenso da equipe nem autoria individual não informada. Validação de compatibilidade realizada no LibreOffice; Microsoft Excel indisponível nesta máquina.

Sheet A01
A1: A01 — Modelos de produto
A2: Sistema e tipo | B2: Estoque Inteligente — ALI
A3: Intenção / finalidade | B3: Manter Modelos de produto como grupo lógico reconhecido pelo usuário.
A4: Fronteira e classificação | B4: Grupo persistente mantido pelo estoque; RL é tipo de registro, não quantidade de linhas.
A5: Rota / contexto | B5: /modelos
A6: Permissões | B6: Permissão cadastros para manutenção; consultar para leitura quando aplicável. Loja sempre validada.
A7: Evidência atual | B7: model/ModeloProduto.java; repository/ModeloProdutoRepository.java; service/ModeloProdutoService.java; templates/modelos.html
A8: Dados internos / regra | B8: Campos de negócio abaixo. Chaves técnicas, CSRF, versão de sessão e idempotência não são TD funcionais.
A10: Registro lógico | B10: Item de dado (TD) | C10: TD distinto | D10: RL distinto
A11: Registro de modelos de produto | B11: loja | C11: =IF(B11="",0,IF(COUNTIF($B$11:B11,B11)=1,1,0)) -> 1 | D11: =IF(A11="",0,IF(COUNTIF($A$11:A11,A11)=1,1,0)) -> 1
A12: Registro de modelos de produto | B12: código | C12: =IF(B12="",0,IF(COUNTIF($B$11:B12,B12)=1,1,0)) -> 1 | D12: =IF(A12="",0,IF(COUNTIF($A$11:A12,A12)=1,1,0)) -> 0
A13: Registro de modelos de produto | B13: nome | C13: =IF(B13="",0,IF(COUNTIF($B$11:B13,B13)=1,1,0)) -> 1 | D13: =IF(A13="",0,IF(COUNTIF($A$11:A13,A13)=1,1,0)) -> 0
A14: Registro de modelos de produto | B14: marca | C14: =IF(B14="",0,IF(COUNTIF($B$11:B14,B14)=1,1,0)) -> 1 | D14: =IF(A14="",0,IF(COUNTIF($A$11:A14,A14)=1,1,0)) -> 0
A15: Registro de modelos de produto | B15: categoria | C15: =IF(B15="",0,IF(COUNTIF($B$11:B15,B15)=1,1,0)) -> 1 | D15: =IF(A15="",0,IF(COUNTIF($A$11:A15,A15)=1,1,0)) -> 0
C16: =IF(B16="",0,IF(COUNTIF($B$11:B16,B16)=1,1,0)) -> 0 | D16: =IF(A16="",0,IF(COUNTIF($A$11:A16,A16)=1,1,0)) -> 0
C17: =IF(B17="",0,IF(COUNTIF($B$11:B17,B17)=1,1,0)) -> 0 | D17: =IF(A17="",0,IF(COUNTIF($A$11:A17,A17)=1,1,0)) -> 0
C18: =IF(B18="",0,IF(COUNTIF($B$11:B18,B18)=1,1,0)) -> 0 | D18: =IF(A18="",0,IF(COUNTIF($A$11:A18,A18)=1,1,0)) -> 0
C19: =IF(B19="",0,IF(COUNTIF($B$11:B19,B19)=1,1,0)) -> 0 | D19: =IF(A19="",0,IF(COUNTIF($A$11:A19,A19)=1,1,0)) -> 0
C20: =IF(B20="",0,IF(COUNTIF($B$11:B20,B20)=1,1,0)) -> 0 | D20: =IF(A20="",0,IF(COUNTIF($A$11:A20,A20)=1,1,0)) -> 0
C21: =IF(B21="",0,IF(COUNTIF($B$11:B21,B21)=1,1,0)) -> 0 | D21: =IF(A21="",0,IF(COUNTIF($A$11:A21,A21)=1,1,0)) -> 0
C22: =IF(B22="",0,IF(COUNTIF($B$11:B22,B22)=1,1,0)) -> 0 | D22: =IF(A22="",0,IF(COUNTIF($A$11:A22,A22)=1,1,0)) -> 0
C23: =IF(B23="",0,IF(COUNTIF($B$11:B23,B23)=1,1,0)) -> 0 | D23: =IF(A23="",0,IF(COUNTIF($A$11:A23,A23)=1,1,0)) -> 0
C24: =IF(B24="",0,IF(COUNTIF($B$11:B24,B24)=1,1,0)) -> 0 | D24: =IF(A24="",0,IF(COUNTIF($A$11:A24,A24)=1,1,0)) -> 0
C25: =IF(B25="",0,IF(COUNTIF($B$11:B25,B25)=1,1,0)) -> 0 | D25: =IF(A25="",0,IF(COUNTIF($A$11:A25,A25)=1,1,0)) -> 0
C26: =IF(B26="",0,IF(COUNTIF($B$11:B26,B26)=1,1,0)) -> 0 | D26: =IF(A26="",0,IF(COUNTIF($A$11:A26,A26)=1,1,0)) -> 0
C27: =IF(B27="",0,IF(COUNTIF($B$11:B27,B27)=1,1,0)) -> 0 | D27: =IF(A27="",0,IF(COUNTIF($A$11:A27,A27)=1,1,0)) -> 0
... C42: =IF(B42="",0,IF(COUNTIF($B$11:B42,B42)=1,1,0)) -> 0 | D42: =IF(A42="",0,IF(COUNTIF($A$11:A42,A42)=1,1,0)) -> 0
A44: Manutenção do grupo lógico
A45: ALI / AIE | B45: Finalidade da referência | C45: AR entrada CE | D45: AR saída CE
A46: Manutenção | B46: Inclusão, alteração e exclusão conforme as EEs de manutenção; consultar catálogo.
A57: Regra AR / RL | B57: Somar RL distintos, não linhas armazenadas. Campos repetidos contam uma vez.
A59: Contagem calculada — entradas editáveis acima
A60: TD total distinto | B60: =SUM(C11:C42) -> 5 | C60: RL distintos | D60: =SUM(D11:D42) -> 1
A61: TD entrada CE | B61: =0 -> 0 | C61: TD saída sem repetição | D61: =0 -> 0
A62: AR entrada CE | B62: =0 -> 0 | C62: AR saída CE | D62: =0 -> 0
A63: Índice entrada CE | B63: =0 -> 0 | C63: Índice saída CE | D63: =0 -> 0
A64: Índice adotado | B64: =INDEX(Matrizes!$B$5:$D$7,IF(D60<=1,1,IF(D60<=5,2,3)),IF(B60<=19,1,IF(B60<=50,2,3))) -> 1 | C64: Complexidade | D64: =INDEX(Matrizes!$B$10:$D$10,1,B64) -> Simples
A65: Peso apropriado ao tipo | B65: =INDEX(Matrizes!$B$13:$D$17,MATCH("ALI",Matrizes!$A$13:$A$17,0),B64) -> 7 | C65: PF desta função | D65: =B65 -> 7
A67: Justificativa da contagem | B67: Peso por TD/RL da Parte I. Cada grupo entra uma única vez no coletivo.
A69: Fluxo da função — leitura do protótipo real
A70: Entrada / contexto | B70: loja; código; nome; marca; categoria
A71: Acionamento | B71: Salvar / alterar / excluir quando permitido pelo grupo.
A72: Resultado / saída | B72: Estado persistido do grupo lógico; manutenção pelos processos indicados. Não representa execução de uma operação nesta figura.
A73: Evidência visual | B73: Capturas da aplicação nas páginas seguintes. Veja a legenda de cada estado e a origem registrada.
A75: A01 — captura real 1/1
A76: Captura real da aplicação atual; dados de demonstração.
A77: Origem: http://localhost:8080/modelos | Capturada em: 2026-10-25T22:02:45.447Z | A01.png

Sheet A02
A1: A02 — Produtos
A2: Sistema e tipo | B2: Estoque Inteligente — ALI
A3: Intenção / finalidade | B3: Manter Produtos como grupo lógico reconhecido pelo usuário.
A4: Fronteira e classificação | B4: Grupo persistente mantido pelo estoque; RL é tipo de registro, não quantidade de linhas.
A5: Rota / contexto | B5: /produtos
A6: Permissões | B6: Permissão cadastros para manutenção; consultar para leitura quando aplicável. Loja sempre validada.
A7: Evidência atual | B7: model/Produto.java; repository/ProdutoRepository.java; service/ProdutoService.java; templates/produtos.html
A8: Dados internos / regra | B8: Campos de negócio abaixo. Chaves técnicas, CSRF, versão de sessão e idempotência não são TD funcionais.
A10: Registro lógico | B10: Item de dado (TD) | C10: TD distinto | D10: RL distinto
A11: Registro de produtos | B11: loja | C11: =IF(B11="",0,IF(COUNTIF($B$11:B11,B11)=1,1,0)) -> 1 | D11: =IF(A11="",0,IF(COUNTIF($A$11:A11,A11)=1,1,0)) -> 1
A12: Registro de produtos | B12: código | C12: =IF(B12="",0,IF(COUNTIF($B$11:B12,B12)=1,1,0)) -> 1 | D12: =IF(A12="",0,IF(COUNTIF($A$11:A12,A12)=1,1,0)) -> 0
A13: Registro de produtos | B13: modelo | C13: =IF(B13="",0,IF(COUNTIF($B$11:B13,B13)=1,1,0)) -> 1 | D13: =IF(A13="",0,IF(COUNTIF($A$11:A13,A13)=1,1,0)) -> 0
A14: Registro de produtos | B14: SKU | C14: =IF(B14="",0,IF(COUNTIF($B$11:B14,B14)=1,1,0)) -> 1 | D14: =IF(A14="",0,IF(COUNTIF($A$11:A14,A14)=1,1,0)) -> 0
A15: Registro de produtos | B15: código de barras | C15: =IF(B15="",0,IF(COUNTIF($B$11:B15,B15)=1,1,0)) -> 1 | D15: =IF(A15="",0,IF(COUNTIF($A$11:A15,A15)=1,1,0)) -> 0
A16: Registro de produtos | B16: cor | C16: =IF(B16="",0,IF(COUNTIF($B$11:B16,B16)=1,1,0)) -> 1 | D16: =IF(A16="",0,IF(COUNTIF($A$11:A16,A16)=1,1,0)) -> 0
A17: Registro de produtos | B17: tamanho | C17: =IF(B17="",0,IF(COUNTIF($B$11:B17,B17)=1,1,0)) -> 1 | D17: =IF(A17="",0,IF(COUNTIF($A$11:A17,A17)=1,1,0)) -> 0
A18: Registro de produtos | B18: unidade | C18: =IF(B18="",0,IF(COUNTIF($B$11:B18,B18)=1,1,0)) -> 1 | D18: =IF(A18="",0,IF(COUNTIF($A$11:A18,A18)=1,1,0)) -> 0
A19: Registro de produtos | B19: preço | C19: =IF(B19="",0,IF(COUNTIF($B$11:B19,B19)=1,1,0)) -> 1 | D19: =IF(A19="",0,IF(COUNTIF($A$11:A19,A19)=1,1,0)) -> 0
A20: Registro de produtos | B20: características | C20: =IF(B20="",0,IF(COUNTIF($B$11:B20,B20)=1,1,0)) -> 1 | D20: =IF(A20="",0,IF(COUNTIF($A$11:A20,A20)=1,1,0)) -> 0
A21: Registro de produtos | B21: ativo | C21: =IF(B21="",0,IF(COUNTIF($B$11:B21,B21)=1,1,0)) -> 1 | D21: =IF(A21="",0,IF(COUNTIF($A$11:A21,A21)=1,1,0)) -> 0
C22: =IF(B22="",0,IF(COUNTIF($B$11:B22,B22)=1,1,0)) -> 0 | D22: =IF(A22="",0,IF(COUNTIF($A$11:A22,A22)=1,1,0)) -> 0
C23: =IF(B23="",0,IF(COUNTIF($B$11:B23,B23)=1,1,0)) -> 0 | D23: =IF(A23="",0,IF(COUNTIF($A$11:A23,A23)=1,1,0)) -> 0
C24: =IF(B24="",0,IF(COUNTIF($B$11:B24,B24)=1,1,0)) -> 0 | D24: =IF(A24="",0,IF(COUNTIF($A$11:A24,A24)=1,1,0)) -> 0
C25: =IF(B25="",0,IF(COUNTIF($B$11:B25,B25)=1,1,0)) -> 0 | D25: =IF(A25="",0,IF(COUNTIF($A$11:A25,A25)=1,1,0)) -> 0
C26: =IF(B26="",0,IF(COUNTIF($B$11:B26,B26)=1,1,0)) -> 0 | D26: =IF(A26="",0,IF(COUNTIF($A$11:A26,A26)=1,1,0)) -> 0
C27: =IF(B27="",0,IF(COUNTIF($B$11:B27,B27)=1,1,0)) -> 0 | D27: =IF(A27="",0,IF(COUNTIF($A$11:A27,A27)=1,1,0)) -> 0
C28: =IF(B28="",0,IF(COUNTIF($B$11:B28,B28)=1,1,0)) -> 0 | D28: =IF(A28="",0,IF(COUNTIF($A$11:A28,A28)=1,1,0)) -> 0
C29: =IF(B29="",0,IF(COUNTIF($B$11:B29,B29)=1,1,0)) -> 0 | D29: =IF(A29="",0,IF(COUNTIF($A$11:A29,A29)=1,1,0)) -> 0
C30: =IF(B30="",0,IF(COUNTIF($B$11:B30,B30)=1,1,0)) -> 0 | D30: =IF(A30="",0,IF(COUNTIF($A$11:A30,A30)=1,1,0)) -> 0
C31: =IF(B31="",0,IF(COUNTIF($B$11:B31,B31)=1,1,0)) -> 0 | D31: =IF(A31="",0,IF(COUNTIF($A$11:A31,A31)=1,1,0)) -> 0
C32: =IF(B32="",0,IF(COUNTIF($B$11:B32,B32)=1,1,0)) -> 0 | D32: =IF(A32="",0,IF(COUNTIF($A$11:A32,A32)=1,1,0)) -> 0
C33: =IF(B33="",0,IF(COUNTIF($B$11:B33,B33)=1,1,0)) -> 0 | D33: =IF(A33="",0,IF(COUNTIF($A$11:A33,A33)=1,1,0)) -> 0
... C42: =IF(B42="",0,IF(COUNTIF($B$11:B42,B42)=1,1,0)) -> 0 | D42: =IF(A42="",0,IF(COUNTIF($A$11:A42,A42)=1,1,0)) -> 0
A44: Manutenção do grupo lógico
A45: ALI / AIE | B45: Finalidade da referência | C45: AR entrada CE | D45: AR saída CE
A46: Manutenção | B46: Inclusão, alteração e exclusão conforme as EEs de manutenção; consultar catálogo.
A57: Regra AR / RL | B57: Somar RL distintos, não linhas armazenadas. Campos repetidos contam uma vez.
A59: Contagem calculada — entradas editáveis acima
A60: TD total distinto | B60: =SUM(C11:C42) -> 11 | C60: RL distintos | D60: =SUM(D11:D42) -> 1
A61: TD entrada CE | B61: =0 -> 0 | C61: TD saída sem repetição | D61: =0 -> 0
A62: AR entrada CE | B62: =0 -> 0 | C62: AR saída CE | D62: =0 -> 0
A63: Índice entrada CE | B63: =0 -> 0 | C63: Índice saída CE | D63: =0 -> 0
A64: Índice adotado | B64: =INDEX(Matrizes!$B$5:$D$7,IF(D60<=1,1,IF(D60<=5,2,3)),IF(B60<=19,1,IF(B60<=50,2,3))) -> 1 | C64: Complexidade | D64: =INDEX(Matrizes!$B$10:$D$10,1,B64) -> Simples
A65: Peso apropriado ao tipo | B65: =INDEX(Matrizes!$B$13:$D$17,MATCH("ALI",Matrizes!$A$13:$A$17,0),B64) -> 7 | C65: PF desta função | D65: =B65 -> 7
A67: Justificativa da contagem | B67: Peso por TD/RL da Parte I. Cada grupo entra uma única vez no coletivo.
A69: Fluxo da função — leitura do protótipo real
A70: Entrada / contexto | B70: loja; código; modelo; SKU; código de barras; cor; tamanho; unidade; preço; características; ativo
A71: Acionamento | B71: Salvar / alterar / excluir quando permitido pelo grupo.
A72: Resultado / saída | B72: Estado persistido do grupo lógico; manutenção pelos processos indicados. Não representa execução de uma operação nesta figura.
A73: Evidência visual | B73: Capturas da aplicação nas páginas seguintes. Veja a legenda de cada estado e a origem registrada.
A75: A02 — captura real 1/1
A76: Captura real da aplicação atual; dados de demonstração.
A77: Origem: http://localhost:8080/produtos | Capturada em: 2026-10-25T22:02:45.673Z | A02.png

Sheet A03
A1: A03 — Posições
A2: Sistema e tipo | B2: Estoque Inteligente — ALI
A3: Intenção / finalidade | B3: Manter Posições como grupo lógico reconhecido pelo usuário.
A4: Fronteira e classificação | B4: Grupo persistente mantido pelo estoque; RL é tipo de registro, não quantidade de linhas.
A5: Rota / contexto | B5: /posicoes
A6: Permissões | B6: Permissão cadastros para manutenção; consultar para leitura quando aplicável. Loja sempre validada.
A7: Evidência atual | B7: model/Posicao.java; repository/PosicaoRepository.java; service/PosicaoService.java; templates/posicoes.html
A8: Dados internos / regra | B8: Campos de negócio abaixo. Chaves técnicas, CSRF, versão de sessão e idempotência não são TD funcionais.
A10: Registro lógico | B10: Item de dado (TD) | C10: TD distinto | D10: RL distinto
A11: Registro de posições | B11: loja | C11: =IF(B11="",0,IF(COUNTIF($B$11:B11,B11)=1,1,0)) -> 1 | D11: =IF(A11="",0,IF(COUNTIF($A$11:A11,A11)=1,1,0)) -> 1
A12: Registro de posições | B12: identificador | C12: =IF(B12="",0,IF(COUNTIF($B$11:B12,B12)=1,1,0)) -> 1 | D12: =IF(A12="",0,IF(COUNTIF($A$11:A12,A12)=1,1,0)) -> 0
A13: Registro de posições | B13: código | C13: =IF(B13="",0,IF(COUNTIF($B$11:B13,B13)=1,1,0)) -> 1 | D13: =IF(A13="",0,IF(COUNTIF($A$11:A13,A13)=1,1,0)) -> 0
A14: Registro de posições | B14: setor | C14: =IF(B14="",0,IF(COUNTIF($B$11:B14,B14)=1,1,0)) -> 1 | D14: =IF(A14="",0,IF(COUNTIF($A$11:A14,A14)=1,1,0)) -> 0
A15: Registro de posições | B15: linha | C15: =IF(B15="",0,IF(COUNTIF($B$11:B15,B15)=1,1,0)) -> 1 | D15: =IF(A15="",0,IF(COUNTIF($A$11:A15,A15)=1,1,0)) -> 0
A16: Registro de posições | B16: coluna | C16: =IF(B16="",0,IF(COUNTIF($B$11:B16,B16)=1,1,0)) -> 1 | D16: =IF(A16="",0,IF(COUNTIF($A$11:A16,A16)=1,1,0)) -> 0
A17: Registro de posições | B17: capacidade | C17: =IF(B17="",0,IF(COUNTIF($B$11:B17,B17)=1,1,0)) -> 1 | D17: =IF(A17="",0,IF(COUNTIF($A$11:A17,A17)=1,1,0)) -> 0
A18: Registro de posições | B18: unidade | C18: =IF(B18="",0,IF(COUNTIF($B$11:B18,B18)=1,1,0)) -> 1 | D18: =IF(A18="",0,IF(COUNTIF($A$11:A18,A18)=1,1,0)) -> 0
A19: Registro de posições | B19: dispositivo | C19: =IF(B19="",0,IF(COUNTIF($B$11:B19,B19)=1,1,0)) -> 1 | D19: =IF(A19="",0,IF(COUNTIF($A$11:A19,A19)=1,1,0)) -> 0
A20: Registro de posições | B20: pino | C20: =IF(B20="",0,IF(COUNTIF($B$11:B20,B20)=1,1,0)) -> 1 | D20: =IF(A20="",0,IF(COUNTIF($A$11:A20,A20)=1,1,0)) -> 0
A21: Registro de posições | B21: ativo | C21: =IF(B21="",0,IF(COUNTIF($B$11:B21,B21)=1,1,0)) -> 1 | D21: =IF(A21="",0,IF(COUNTIF($A$11:A21,A21)=1,1,0)) -> 0
C22: =IF(B22="",0,IF(COUNTIF($B$11:B22,B22)=1,1,0)) -> 0 | D22: =IF(A22="",0,IF(COUNTIF($A$11:A22,A22)=1,1,0)) -> 0
C23: =IF(B23="",0,IF(COUNTIF($B$11:B23,B23)=1,1,0)) -> 0 | D23: =IF(A23="",0,IF(COUNTIF($A$11:A23,A23)=1,1,0)) -> 0
C24: =IF(B24="",0,IF(COUNTIF($B$11:B24,B24)=1,1,0)) -> 0 | D24: =IF(A24="",0,IF(COUNTIF($A$11:A24,A24)=1,1,0)) -> 0
C25: =IF(B25="",0,IF(COUNTIF($B$11:B25,B25)=1,1,0)) -> 0 | D25: =IF(A25="",0,IF(COUNTIF($A$11:A25,A25)=1,1,0)) -> 0
C26: =IF(B26="",0,IF(COUNTIF($B$11:B26,B26)=1,1,0)) -> 0 | D26: =IF(A26="",0,IF(COUNTIF($A$11:A26,A26)=1,1,0)) -> 0
C27: =IF(B27="",0,IF(COUNTIF($B$11:B27,B27)=1,1,0)) -> 0 | D27: =IF(A27="",0,IF(COUNTIF($A$11:A27,A27)=1,1,0)) -> 0
C28: =IF(B28="",0,IF(COUNTIF($B$11:B28,B28)=1,1,0)) -> 0 | D28: =IF(A28="",0,IF(COUNTIF($A$11:A28,A28)=1,1,0)) -> 0
C29: =IF(B29="",0,IF(COUNTIF($B$11:B29,B29)=1,1,0)) -> 0 | D29: =IF(A29="",0,IF(COUNTIF($A$11:A29,A29)=1,1,0)) -> 0
C30: =IF(B30="",0,IF(COUNTIF($B$11:B30,B30)=1,1,0)) -> 0 | D30: =IF(A30="",0,IF(COUNTIF($A$11:A30,A30)=1,1,0)) -> 0
C31: =IF(B31="",0,IF(COUNTIF($B$11:B31,B31)=1,1,0)) -> 0 | D31: =IF(A31="",0,IF(COUNTIF($A$11:A31,A31)=1,1,0)) -> 0
C32: =IF(B32="",0,IF(COUNTIF($B$11:B32,B32)=1,1,0)) -> 0 | D32: =IF(A32="",0,IF(COUNTIF($A$11:A32,A32)=1,1,0)) -> 0
C33: =IF(B33="",0,IF(COUNTIF($B$11:B33,B33)=1,1,0)) -> 0 | D33: =IF(A33="",0,IF(COUNTIF($A$11:A33,A33)=1,1,0)) -> 0
... C42: =IF(B42="",0,IF(COUNTIF($B$11:B42,B42)=1,1,0)) -> 0 | D42: =IF(A42="",0,IF(COUNTIF($A$11:A42,A42)=1,1,0)) -> 0
A44: Manutenção do grupo lógico
A45: ALI / AIE | B45: Finalidade da referência | C45: AR entrada CE | D45: AR saída CE
A46: Manutenção | B46: Inclusão, alteração e exclusão conforme as EEs de manutenção; consultar catálogo.
A57: Regra AR / RL | B57: Somar RL distintos, não linhas armazenadas. Campos repetidos contam uma vez.
A59: Contagem calculada — entradas editáveis acima
A60: TD total distinto | B60: =SUM(C11:C42) -> 11 | C60: RL distintos | D60: =SUM(D11:D42) -> 1
A61: TD entrada CE | B61: =0 -> 0 | C61: TD saída sem repetição | D61: =0 -> 0
A62: AR entrada CE | B62: =0 -> 0 | C62: AR saída CE | D62: =0 -> 0
A63: Índice entrada CE | B63: =0 -> 0 | C63: Índice saída CE | D63: =0 -> 0
A64: Índice adotado | B64: =INDEX(Matrizes!$B$5:$D$7,IF(D60<=1,1,IF(D60<=5,2,3)),IF(B60<=19,1,IF(B60<=50,2,3))) -> 1 | C64: Complexidade | D64: =INDEX(Matrizes!$B$10:$D$10,1,B64) -> Simples
A65: Peso apropriado ao tipo | B65: =INDEX(Matrizes!$B$13:$D$17,MATCH("ALI",Matrizes!$A$13:$A$17,0),B64) -> 7 | C65: PF desta função | D65: =B65 -> 7
A67: Justificativa da contagem | B67: Peso por TD/RL da Parte I. Cada grupo entra uma única vez no coletivo.
A69: Fluxo da função — leitura do protótipo real
A70: Entrada / contexto | B70: loja; identificador; código; setor; linha; coluna; capacidade; unidade; dispositivo; pino; ativo
A71: Acionamento | B71: Salvar / alterar / excluir quando permitido pelo grupo.
A72: Resultado / saída | B72: Estado persistido do grupo lógico; manutenção pelos processos indicados. Não representa execução de uma operação nesta figura.
A73: Evidência visual | B73: Capturas da aplicação nas páginas seguintes. Veja a legenda de cada estado e a origem registrada.
A75: A03 — captura real 1/1
A76: Captura real da aplicação atual; dados de demonstração.
A77: Origem: http://localhost:8080/posicoes | Capturada em: 2026-10-25T22:02:45.805Z | A03.png

Sheet A04
A1: A04 — Estoque por posição / vínculos
A2: Sistema e tipo | B2: Estoque Inteligente — ALI
A3: Intenção / finalidade | B3: Manter Estoque por posição / vínculos como grupo lógico reconhecido pelo usuário.
A4: Fronteira e classificação | B4: Grupo persistente mantido pelo estoque; RL é tipo de registro, não quantidade de linhas.
A5: Rota / contexto | B5: /vinculos
A6: Permissões | B6: Permissão cadastros para manutenção; consultar para leitura quando aplicável. Loja sempre validada.
A7: Evidência atual | B7: model/Ocupacao.java; repository/OcupacaoRepository.java; service/VinculoService.java; templates/vinculos.html
A8: Dados internos / regra | B8: Campos de negócio abaixo. Chaves técnicas, CSRF, versão de sessão e idempotência não são TD funcionais.
A10: Registro lógico | B10: Item de dado (TD) | C10: TD distinto | D10: RL distinto
A11: Registro de estoque por posição / vínculos | B11: loja | C11: =IF(B11="",0,IF(COUNTIF($B$11:B11,B11)=1,1,0)) -> 1 | D11: =IF(A11="",0,IF(COUNTIF($A$11:A11,A11)=1,1,0)) -> 1
A12: Registro de estoque por posição / vínculos | B12: produto | C12: =IF(B12="",0,IF(COUNTIF($B$11:B12,B12)=1,1,0)) -> 1 | D12: =IF(A12="",0,IF(COUNTIF($A$11:A12,A12)=1,1,0)) -> 0
A13: Registro de estoque por posição / vínculos | B13: posição | C13: =IF(B13="",0,IF(COUNTIF($B$11:B13,B13)=1,1,0)) -> 1 | D13: =IF(A13="",0,IF(COUNTIF($A$11:A13,A13)=1,1,0)) -> 0
A14: Registro de estoque por posição / vínculos | B14: quantidade | C14: =IF(B14="",0,IF(COUNTIF($B$11:B14,B14)=1,1,0)) -> 1 | D14: =IF(A14="",0,IF(COUNTIF($A$11:A14,A14)=1,1,0)) -> 0
C15: =IF(B15="",0,IF(COUNTIF($B$11:B15,B15)=1,1,0)) -> 0 | D15: =IF(A15="",0,IF(COUNTIF($A$11:A15,A15)=1,1,0)) -> 0
C16: =IF(B16="",0,IF(COUNTIF($B$11:B16,B16)=1,1,0)) -> 0 | D16: =IF(A16="",0,IF(COUNTIF($A$11:A16,A16)=1,1,0)) -> 0
C17: =IF(B17="",0,IF(COUNTIF($B$11:B17,B17)=1,1,0)) -> 0 | D17: =IF(A17="",0,IF(COUNTIF($A$11:A17,A17)=1,1,0)) -> 0
C18: =IF(B18="",0,IF(COUNTIF($B$11:B18,B18)=1,1,0)) -> 0 | D18: =IF(A18="",0,IF(COUNTIF($A$11:A18,A18)=1,1,0)) -> 0
C19: =IF(B19="",0,IF(COUNTIF($B$11:B19,B19)=1,1,0)) -> 0 | D19: =IF(A19="",0,IF(COUNTIF($A$11:A19,A19)=1,1,0)) -> 0
C20: =IF(B20="",0,IF(COUNTIF($B$11:B20,B20)=1,1,0)) -> 0 | D20: =IF(A20="",0,IF(COUNTIF($A$11:A20,A20)=1,1,0)) -> 0
C21: =IF(B21="",0,IF(COUNTIF($B$11:B21,B21)=1,1,0)) -> 0 | D21: =IF(A21="",0,IF(COUNTIF($A$11:A21,A21)=1,1,0)) -> 0
C22: =IF(B22="",0,IF(COUNTIF($B$11:B22,B22)=1,1,0)) -> 0 | D22: =IF(A22="",0,IF(COUNTIF($A$11:A22,A22)=1,1,0)) -> 0
C23: =IF(B23="",0,IF(COUNTIF($B$11:B23,B23)=1,1,0)) -> 0 | D23: =IF(A23="",0,IF(COUNTIF($A$11:A23,A23)=1,1,0)) -> 0
C24: =IF(B24="",0,IF(COUNTIF($B$11:B24,B24)=1,1,0)) -> 0 | D24: =IF(A24="",0,IF(COUNTIF($A$11:A24,A24)=1,1,0)) -> 0
C25: =IF(B25="",0,IF(COUNTIF($B$11:B25,B25)=1,1,0)) -> 0 | D25: =IF(A25="",0,IF(COUNTIF($A$11:A25,A25)=1,1,0)) -> 0
C26: =IF(B26="",0,IF(COUNTIF($B$11:B26,B26)=1,1,0)) -> 0 | D26: =IF(A26="",0,IF(COUNTIF($A$11:A26,A26)=1,1,0)) -> 0
... C42: =IF(B42="",0,IF(COUNTIF($B$11:B42,B42)=1,1,0)) -> 0 | D42: =IF(A42="",0,IF(COUNTIF($A$11:A42,A42)=1,1,0)) -> 0
A44: Manutenção do grupo lógico
A45: ALI / AIE | B45: Finalidade da referência | C45: AR entrada CE | D45: AR saída CE
A46: Manutenção | B46: Inclusão, alteração e exclusão conforme as EEs de manutenção; consultar catálogo.
A57: Regra AR / RL | B57: Somar RL distintos, não linhas armazenadas. Campos repetidos contam uma vez.
A59: Contagem calculada — entradas editáveis acima
A60: TD total distinto | B60: =SUM(C11:C42) -> 4 | C60: RL distintos | D60: =SUM(D11:D42) -> 1
A61: TD entrada CE | B61: =0 -> 0 | C61: TD saída sem repetição | D61: =0 -> 0
A62: AR entrada CE | B62: =0 -> 0 | C62: AR saída CE | D62: =0 -> 0
A63: Índice entrada CE | B63: =0 -> 0 | C63: Índice saída CE | D63: =0 -> 0
A64: Índice adotado | B64: =INDEX(Matrizes!$B$5:$D$7,IF(D60<=1,1,IF(D60<=5,2,3)),IF(B60<=19,1,IF(B60<=50,2,3))) -> 1 | C64: Complexidade | D64: =INDEX(Matrizes!$B$10:$D$10,1,B64) -> Simples
A65: Peso apropriado ao tipo | B65: =INDEX(Matrizes!$B$13:$D$17,MATCH("ALI",Matrizes!$A$13:$A$17,0),B64) -> 7 | C65: PF desta função | D65: =B65 -> 7
A67: Justificativa da contagem | B67: Peso por TD/RL da Parte I. Cada grupo entra uma única vez no coletivo.
A69: Fluxo da função — leitura do protótipo real
A70: Entrada / contexto | B70: loja; produto; posição; quantidade
A71: Acionamento | B71: Salvar / alterar / excluir quando permitido pelo grupo.
A72: Resultado / saída | B72: Estado persistido do grupo lógico; manutenção pelos processos indicados. Não representa execução de uma operação nesta figura.
A73: Evidência visual | B73: Capturas da aplicação nas páginas seguintes. Veja a legenda de cada estado e a origem registrada.
A75: A04 — captura real 1/1
A76: Captura real da aplicação atual; dados de demonstração.
A77: Origem: http://localhost:8080/vinculos | Capturada em: 2026-10-25T22:02:46.015Z | A04.png

Sheet A05
A1: A05 — Movimentações
A2: Sistema e tipo | B2: Estoque Inteligente — ALI
A3: Intenção / finalidade | B3: Manter Movimentações como grupo lógico reconhecido pelo usuário.
A4: Fronteira e classificação | B4: Grupo persistente mantido pelo estoque; RL é tipo de registro, não quantidade de linhas.
A5: Rota / contexto | B5: /historico
A6: Permissões | B6: Permissão historico e isolamento pela loja autenticada.
A7: Evidência atual | B7: model/Movimentacao.java; repository/MovimentacaoRepository.java; service/EstoqueService.java; templates/historico.html
A8: Dados internos / regra | B8: Campos de negócio abaixo. Chaves técnicas, CSRF, versão de sessão e idempotência não são TD funcionais.
A10: Registro lógico | B10: Item de dado (TD) | C10: TD distinto | D10: RL distinto
A11: Registro de movimentações | B11: loja | C11: =IF(B11="",0,IF(COUNTIF($B$11:B11,B11)=1,1,0)) -> 1 | D11: =IF(A11="",0,IF(COUNTIF($A$11:A11,A11)=1,1,0)) -> 1
A12: Registro de movimentações | B12: número | C12: =IF(B12="",0,IF(COUNTIF($B$11:B12,B12)=1,1,0)) -> 1 | D12: =IF(A12="",0,IF(COUNTIF($A$11:A12,A12)=1,1,0)) -> 0
A13: Registro de movimentações | B13: produto | C13: =IF(B13="",0,IF(COUNTIF($B$11:B13,B13)=1,1,0)) -> 1 | D13: =IF(A13="",0,IF(COUNTIF($A$11:A13,A13)=1,1,0)) -> 0
A14: Registro de movimentações | B14: posição | C14: =IF(B14="",0,IF(COUNTIF($B$11:B14,B14)=1,1,0)) -> 1 | D14: =IF(A14="",0,IF(COUNTIF($A$11:A14,A14)=1,1,0)) -> 0
A15: Registro de movimentações | B15: responsável | C15: =IF(B15="",0,IF(COUNTIF($B$11:B15,B15)=1,1,0)) -> 1 | D15: =IF(A15="",0,IF(COUNTIF($A$11:A15,A15)=1,1,0)) -> 0
A16: Registro de movimentações | B16: tipo | C16: =IF(B16="",0,IF(COUNTIF($B$11:B16,B16)=1,1,0)) -> 1 | D16: =IF(A16="",0,IF(COUNTIF($A$11:A16,A16)=1,1,0)) -> 0
A17: Registro de movimentações | B17: variação | C17: =IF(B17="",0,IF(COUNTIF($B$11:B17,B17)=1,1,0)) -> 1 | D17: =IF(A17="",0,IF(COUNTIF($A$11:A17,A17)=1,1,0)) -> 0
A18: Registro de movimentações | B18: saldo anterior | C18: =IF(B18="",0,IF(COUNTIF($B$11:B18,B18)=1,1,0)) -> 1 | D18: =IF(A18="",0,IF(COUNTIF($A$11:A18,A18)=1,1,0)) -> 0
A19: Registro de movimentações | B19: saldo posterior | C19: =IF(B19="",0,IF(COUNTIF($B$11:B19,B19)=1,1,0)) -> 1 | D19: =IF(A19="",0,IF(COUNTIF($A$11:A19,A19)=1,1,0)) -> 0
A20: Registro de movimentações | B20: motivo | C20: =IF(B20="",0,IF(COUNTIF($B$11:B20,B20)=1,1,0)) -> 1 | D20: =IF(A20="",0,IF(COUNTIF($A$11:A20,A20)=1,1,0)) -> 0
A21: Registro de movimentações | B21: data | C21: =IF(B21="",0,IF(COUNTIF($B$11:B21,B21)=1,1,0)) -> 1 | D21: =IF(A21="",0,IF(COUNTIF($A$11:A21,A21)=1,1,0)) -> 0
A22: Registro de movimentações | B22: movimento original | C22: =IF(B22="",0,IF(COUNTIF($B$11:B22,B22)=1,1,0)) -> 1 | D22: =IF(A22="",0,IF(COUNTIF($A$11:A22,A22)=1,1,0)) -> 0
C23: =IF(B23="",0,IF(COUNTIF($B$11:B23,B23)=1,1,0)) -> 0 | D23: =IF(A23="",0,IF(COUNTIF($A$11:A23,A23)=1,1,0)) -> 0
C24: =IF(B24="",0,IF(COUNTIF($B$11:B24,B24)=1,1,0)) -> 0 | D24: =IF(A24="",0,IF(COUNTIF($A$11:A24,A24)=1,1,0)) -> 0
C25: =IF(B25="",0,IF(COUNTIF($B$11:B25,B25)=1,1,0)) -> 0 | D25: =IF(A25="",0,IF(COUNTIF($A$11:A25,A25)=1,1,0)) -> 0
C26: =IF(B26="",0,IF(COUNTIF($B$11:B26,B26)=1,1,0)) -> 0 | D26: =IF(A26="",0,IF(COUNTIF($A$11:A26,A26)=1,1,0)) -> 0
C27: =IF(B27="",0,IF(COUNTIF($B$11:B27,B27)=1,1,0)) -> 0 | D27: =IF(A27="",0,IF(COUNTIF($A$11:A27,A27)=1,1,0)) -> 0
C28: =IF(B28="",0,IF(COUNTIF($B$11:B28,B28)=1,1,0)) -> 0 | D28: =IF(A28="",0,IF(COUNTIF($A$11:A28,A28)=1,1,0)) -> 0
C29: =IF(B29="",0,IF(COUNTIF($B$11:B29,B29)=1,1,0)) -> 0 | D29: =IF(A29="",0,IF(COUNTIF($A$11:A29,A29)=1,1,0)) -> 0
C30: =IF(B30="",0,IF(COUNTIF($B$11:B30,B30)=1,1,0)) -> 0 | D30: =IF(A30="",0,IF(COUNTIF($A$11:A30,A30)=1,1,0)) -> 0
C31: =IF(B31="",0,IF(COUNTIF($B$11:B31,B31)=1,1,0)) -> 0 | D31: =IF(A31="",0,IF(COUNTIF($A$11:A31,A31)=1,1,0)) -> 0
C32: =IF(B32="",0,IF(COUNTIF($B$11:B32,B32)=1,1,0)) -> 0 | D32: =IF(A32="",0,IF(COUNTIF($A$11:A32,A32)=1,1,0)) -> 0
C33: =IF(B33="",0,IF(COUNTIF($B$11:B33,B33)=1,1,0)) -> 0 | D33: =IF(A33="",0,IF(COUNTIF($A$11:A33,A33)=1,1,0)) -> 0
C34: =IF(B34="",0,IF(COUNTIF($B$11:B34,B34)=1,1,0)) -> 0 | D34: =IF(A34="",0,IF(COUNTIF($A$11:A34,A34)=1,1,0)) -> 0
... C42: =IF(B42="",0,IF(COUNTIF($B$11:B42,B42)=1,1,0)) -> 0 | D42: =IF(A42="",0,IF(COUNTIF($A$11:A42,A42)=1,1,0)) -> 0
A44: Manutenção do grupo lógico
A45: ALI / AIE | B45: Finalidade da referência | C45: AR entrada CE | D45: AR saída CE
A46: Manutenção | B46: Registro imutável por movimentos; correção por estorno, sem CRUD arbitrário.
A57: Regra AR / RL | B57: Somar RL distintos, não linhas armazenadas. Campos repetidos contam uma vez.
A59: Contagem calculada — entradas editáveis acima
A60: TD total distinto | B60: =SUM(C11:C42) -> 12 | C60: RL distintos | D60: =SUM(D11:D42) -> 1
A61: TD entrada CE | B61: =0 -> 0 | C61: TD saída sem repetição | D61: =0 -> 0
A62: AR entrada CE | B62: =0 -> 0 | C62: AR saída CE | D62: =0 -> 0
A63: Índice entrada CE | B63: =0 -> 0 | C63: Índice saída CE | D63: =0 -> 0
A64: Índice adotado | B64: =INDEX(Matrizes!$B$5:$D$7,IF(D60<=1,1,IF(D60<=5,2,3)),IF(B60<=19,1,IF(B60<=50,2,3))) -> 1 | C64: Complexidade | D64: =INDEX(Matrizes!$B$10:$D$10,1,B64) -> Simples
A65: Peso apropriado ao tipo | B65: =INDEX(Matrizes!$B$13:$D$17,MATCH("ALI",Matrizes!$A$13:$A$17,0),B64) -> 7 | C65: PF desta função | D65: =B65 -> 7
A67: Justificativa da contagem | B67: Peso por TD/RL da Parte I. Cada grupo entra uma única vez no coletivo.
A69: Fluxo da função — leitura do protótipo real
A70: Entrada / contexto | B70: loja; número; produto; posição; responsável; tipo; variação; saldo anterior; saldo posterior; motivo; data; movimento original
A71: Acionamento | B71: Salvar / alterar / excluir quando permitido pelo grupo.
A72: Resultado / saída | B72: Estado persistido do grupo lógico; manutenção pelos processos indicados. Não representa execução de uma operação nesta figura.
A73: Evidência visual | B73: Capturas da aplicação nas páginas seguintes. Veja a legenda de cada estado e a origem registrada.
A75: A05 — captura real 1/1
A76: Captura real da aplicação atual; dados de demonstração.
A77: Origem: http://localhost:8080/historico | Capturada em: 2026-10-25T22:02:46.171Z | A05.png

Sheet A06
A1: A06 — Usuários
A2: Sistema e tipo | B2: Estoque Inteligente — ALI
A3: Intenção / finalidade | B3: Manter Usuários como grupo lógico reconhecido pelo usuário.
A4: Fronteira e classificação | B4: Grupo persistente mantido pelo estoque; RL é tipo de registro, não quantidade de linhas.
A5: Rota / contexto | B5: /usuarios
A6: Permissões | B6: Permissão usuarios; proteção do último administrador e impedimento de autoexclusão.
A7: Evidência atual | B7: model/Usuario.java; repository/UsuarioRepository.java; service/UsuarioService.java; templates/usuarios.html
A8: Dados internos / regra | B8: Campos de negócio abaixo. Chaves técnicas, CSRF, versão de sessão e idempotência não são TD funcionais.
A10: Registro lógico | B10: Item de dado (TD) | C10: TD distinto | D10: RL distinto
A11: Registro de usuários | B11: loja | C11: =IF(B11="",0,IF(COUNTIF($B$11:B11,B11)=1,1,0)) -> 1 | D11: =IF(A11="",0,IF(COUNTIF($A$11:A11,A11)=1,1,0)) -> 1
A12: Registro de usuários | B12: código | C12: =IF(B12="",0,IF(COUNTIF($B$11:B12,B12)=1,1,0)) -> 1 | D12: =IF(A12="",0,IF(COUNTIF($A$11:A12,A12)=1,1,0)) -> 0
A13: Registro de usuários | B13: nome de usuário | C13: =IF(B13="",0,IF(COUNTIF($B$11:B13,B13)=1,1,0)) -> 1 | D13: =IF(A13="",0,IF(COUNTIF($A$11:A13,A13)=1,1,0)) -> 0
A14: Registro de usuários | B14: senha | C14: =IF(B14="",0,IF(COUNTIF($B$11:B14,B14)=1,1,0)) -> 1 | D14: =IF(A14="",0,IF(COUNTIF($A$11:A14,A14)=1,1,0)) -> 0
A15: Registro de usuários | B15: perfil | C15: =IF(B15="",0,IF(COUNTIF($B$11:B15,B15)=1,1,0)) -> 1 | D15: =IF(A15="",0,IF(COUNTIF($A$11:A15,A15)=1,1,0)) -> 0
A16: Registro de usuários | B16: ativo | C16: =IF(B16="",0,IF(COUNTIF($B$11:B16,B16)=1,1,0)) -> 1 | D16: =IF(A16="",0,IF(COUNTIF($A$11:A16,A16)=1,1,0)) -> 0
C17: =IF(B17="",0,IF(COUNTIF($B$11:B17,B17)=1,1,0)) -> 0 | D17: =IF(A17="",0,IF(COUNTIF($A$11:A17,A17)=1,1,0)) -> 0
C18: =IF(B18="",0,IF(COUNTIF($B$11:B18,B18)=1,1,0)) -> 0 | D18: =IF(A18="",0,IF(COUNTIF($A$11:A18,A18)=1,1,0)) -> 0
C19: =IF(B19="",0,IF(COUNTIF($B$11:B19,B19)=1,1,0)) -> 0 | D19: =IF(A19="",0,IF(COUNTIF($A$11:A19,A19)=1,1,0)) -> 0
C20: =IF(B20="",0,IF(COUNTIF($B$11:B20,B20)=1,1,0)) -> 0 | D20: =IF(A20="",0,IF(COUNTIF($A$11:A20,A20)=1,1,0)) -> 0
C21: =IF(B21="",0,IF(COUNTIF($B$11:B21,B21)=1,1,0)) -> 0 | D21: =IF(A21="",0,IF(COUNTIF($A$11:A21,A21)=1,1,0)) -> 0
C22: =IF(B22="",0,IF(COUNTIF($B$11:B22,B22)=1,1,0)) -> 0 | D22: =IF(A22="",0,IF(COUNTIF($A$11:A22,A22)=1,1,0)) -> 0
C23: =IF(B23="",0,IF(COUNTIF($B$11:B23,B23)=1,1,0)) -> 0 | D23: =IF(A23="",0,IF(COUNTIF($A$11:A23,A23)=1,1,0)) -> 0
C24: =IF(B24="",0,IF(COUNTIF($B$11:B24,B24)=1,1,0)) -> 0 | D24: =IF(A24="",0,IF(COUNTIF($A$11:A24,A24)=1,1,0)) -> 0
C25: =IF(B25="",0,IF(COUNTIF($B$11:B25,B25)=1,1,0)) -> 0 | D25: =IF(A25="",0,IF(COUNTIF($A$11:A25,A25)=1,1,0)) -> 0
C26: =IF(B26="",0,IF(COUNTIF($B$11:B26,B26)=1,1,0)) -> 0 | D26: =IF(A26="",0,IF(COUNTIF($A$11:A26,A26)=1,1,0)) -> 0
C27: =IF(B27="",0,IF(COUNTIF($B$11:B27,B27)=1,1,0)) -> 0 | D27: =IF(A27="",0,IF(COUNTIF($A$11:A27,A27)=1,1,0)) -> 0
C28: =IF(B28="",0,IF(COUNTIF($B$11:B28,B28)=1,1,0)) -> 0 | D28: =IF(A28="",0,IF(COUNTIF($A$11:A28,A28)=1,1,0)) -> 0
... C42: =IF(B42="",0,IF(COUNTIF($B$11:B42,B42)=1,1,0)) -> 0 | D42: =IF(A42="",0,IF(COUNTIF($A$11:A42,A42)=1,1,0)) -> 0
A44: Manutenção do grupo lógico
A45: ALI / AIE | B45: Finalidade da referência | C45: AR entrada CE | D45: AR saída CE
A46: Manutenção | B46: Inclusão, alteração e exclusão conforme as EEs de manutenção; consultar catálogo.
A57: Regra AR / RL | B57: Somar RL distintos, não linhas armazenadas. Campos repetidos contam uma vez.
A59: Contagem calculada — entradas editáveis acima
A60: TD total distinto | B60: =SUM(C11:C42) -> 6 | C60: RL distintos | D60: =SUM(D11:D42) -> 1
A61: TD entrada CE | B61: =0 -> 0 | C61: TD saída sem repetição | D61: =0 -> 0
A62: AR entrada CE | B62: =0 -> 0 | C62: AR saída CE | D62: =0 -> 0
A63: Índice entrada CE | B63: =0 -> 0 | C63: Índice saída CE | D63: =0 -> 0
A64: Índice adotado | B64: =INDEX(Matrizes!$B$5:$D$7,IF(D60<=1,1,IF(D60<=5,2,3)),IF(B60<=19,1,IF(B60<=50,2,3))) -> 1 | C64: Complexidade | D64: =INDEX(Matrizes!$B$10:$D$10,1,B64) -> Simples
A65: Peso apropriado ao tipo | B65: =INDEX(Matrizes!$B$13:$D$17,MATCH("ALI",Matrizes!$A$13:$A$17,0),B64) -> 7 | C65: PF desta função | D65: =B65 -> 7
A67: Justificativa da contagem | B67: Peso por TD/RL da Parte I. Cada grupo entra uma única vez no coletivo.
A69: Fluxo da função — leitura do protótipo real
A70: Entrada / contexto | B70: loja; código; nome de usuário; senha; perfil; ativo
A71: Acionamento | B71: Salvar / alterar / excluir quando permitido pelo grupo.
A72: Resultado / saída | B72: Estado persistido do grupo lógico; manutenção pelos processos indicados. Não representa execução de uma operação nesta figura.
A73: Evidência visual | B73: Capturas da aplicação nas páginas seguintes. Veja a legenda de cada estado e a origem registrada.
A75: A06 — captura real 1/1
A76: Captura real da aplicação atual; dados de demonstração.
A77: Origem: http://localhost:8080/usuarios | Capturada em: 2026-10-25T22:02:46.381Z | A06.png

Sheet A07
A1: A07 — Permissões por perfil
A2: Sistema e tipo | B2: Estoque Inteligente — ALI
A3: Intenção / finalidade | B3: Manter Permissões por perfil como grupo lógico reconhecido pelo usuário.
A4: Fronteira e classificação | B4: Grupo persistente mantido pelo estoque; RL é tipo de registro, não quantidade de linhas.
A5: Rota / contexto | B5: /usuarios
A6: Permissões | B6: Administrador ou global, permissão rbac; consulta da matriz exige usuarios e exibição exige rbac.
A7: Evidência atual | B7: model/PermissaoPerfil.java; repository/PermissaoRepository.java; service/PermissaoService.java; templates/usuarios.html
A8: Dados internos / regra | B8: Campos de negócio abaixo. Chaves técnicas, CSRF, versão de sessão e idempotência não são TD funcionais.
A10: Registro lógico | B10: Item de dado (TD) | C10: TD distinto | D10: RL distinto
A11: Registro de permissões por perfil | B11: loja | C11: =IF(B11="",0,IF(COUNTIF($B$11:B11,B11)=1,1,0)) -> 1 | D11: =IF(A11="",0,IF(COUNTIF($A$11:A11,A11)=1,1,0)) -> 1
A12: Registro de permissões por perfil | B12: perfil | C12: =IF(B12="",0,IF(COUNTIF($B$11:B12,B12)=1,1,0)) -> 1 | D12: =IF(A12="",0,IF(COUNTIF($A$11:A12,A12)=1,1,0)) -> 0
A13: Registro de permissões por perfil | B13: permissão | C13: =IF(B13="",0,IF(COUNTIF($B$11:B13,B13)=1,1,0)) -> 1 | D13: =IF(A13="",0,IF(COUNTIF($A$11:A13,A13)=1,1,0)) -> 0
C14: =IF(B14="",0,IF(COUNTIF($B$11:B14,B14)=1,1,0)) -> 0 | D14: =IF(A14="",0,IF(COUNTIF($A$11:A14,A14)=1,1,0)) -> 0
C15: =IF(B15="",0,IF(COUNTIF($B$11:B15,B15)=1,1,0)) -> 0 | D15: =IF(A15="",0,IF(COUNTIF($A$11:A15,A15)=1,1,0)) -> 0
C16: =IF(B16="",0,IF(COUNTIF($B$11:B16,B16)=1,1,0)) -> 0 | D16: =IF(A16="",0,IF(COUNTIF($A$11:A16,A16)=1,1,0)) -> 0
C17: =IF(B17="",0,IF(COUNTIF($B$11:B17,B17)=1,1,0)) -> 0 | D17: =IF(A17="",0,IF(COUNTIF($A$11:A17,A17)=1,1,0)) -> 0
C18: =IF(B18="",0,IF(COUNTIF($B$11:B18,B18)=1,1,0)) -> 0 | D18: =IF(A18="",0,IF(COUNTIF($A$11:A18,A18)=1,1,0)) -> 0
C19: =IF(B19="",0,IF(COUNTIF($B$11:B19,B19)=1,1,0)) -> 0 | D19: =IF(A19="",0,IF(COUNTIF($A$11:A19,A19)=1,1,0)) -> 0
C20: =IF(B20="",0,IF(COUNTIF($B$11:B20,B20)=1,1,0)) -> 0 | D20: =IF(A20="",0,IF(COUNTIF($A$11:A20,A20)=1,1,0)) -> 0
C21: =IF(B21="",0,IF(COUNTIF($B$11:B21,B21)=1,1,0)) -> 0 | D21: =IF(A21="",0,IF(COUNTIF($A$11:A21,A21)=1,1,0)) -> 0
C22: =IF(B22="",0,IF(COUNTIF($B$11:B22,B22)=1,1,0)) -> 0 | D22: =IF(A22="",0,IF(COUNTIF($A$11:A22,A22)=1,1,0)) -> 0
C23: =IF(B23="",0,IF(COUNTIF($B$11:B23,B23)=1,1,0)) -> 0 | D23: =IF(A23="",0,IF(COUNTIF($A$11:A23,A23)=1,1,0)) -> 0
C24: =IF(B24="",0,IF(COUNTIF($B$11:B24,B24)=1,1,0)) -> 0 | D24: =IF(A24="",0,IF(COUNTIF($A$11:A24,A24)=1,1,0)) -> 0
C25: =IF(B25="",0,IF(COUNTIF($B$11:B25,B25)=1,1,0)) -> 0 | D25: =IF(A25="",0,IF(COUNTIF($A$11:A25,A25)=1,1,0)) -> 0
... C42: =IF(B42="",0,IF(COUNTIF($B$11:B42,B42)=1,1,0)) -> 0 | D42: =IF(A42="",0,IF(COUNTIF($A$11:A42,A42)=1,1,0)) -> 0
A44: Manutenção do grupo lógico
A45: ALI / AIE | B45: Finalidade da referência | C45: AR entrada CE | D45: AR saída CE
A46: Manutenção | B46: Inicialização junto da loja; matriz alterada por EE19. Não existe cadastro independente de novos perfis.
A57: Regra AR / RL | B57: Somar RL distintos, não linhas armazenadas. Campos repetidos contam uma vez.
A59: Contagem calculada — entradas editáveis acima
A60: TD total distinto | B60: =SUM(C11:C42) -> 3 | C60: RL distintos | D60: =SUM(D11:D42) -> 1
A61: TD entrada CE | B61: =0 -> 0 | C61: TD saída sem repetição | D61: =0 -> 0
A62: AR entrada CE | B62: =0 -> 0 | C62: AR saída CE | D62: =0 -> 0
A63: Índice entrada CE | B63: =0 -> 0 | C63: Índice saída CE | D63: =0 -> 0
A64: Índice adotado | B64: =INDEX(Matrizes!$B$5:$D$7,IF(D60<=1,1,IF(D60<=5,2,3)),IF(B60<=19,1,IF(B60<=50,2,3))) -> 1 | C64: Complexidade | D64: =INDEX(Matrizes!$B$10:$D$10,1,B64) -> Simples
A65: Peso apropriado ao tipo | B65: =INDEX(Matrizes!$B$13:$D$17,MATCH("ALI",Matrizes!$A$13:$A$17,0),B64) -> 7 | C65: PF desta função | D65: =B65 -> 7
A67: Justificativa da contagem | B67: Peso por TD/RL da Parte I. Cada grupo entra uma única vez no coletivo.
A69: Fluxo da função — leitura do protótipo real
A70: Entrada / contexto | B70: loja; perfil; permissão
A71: Acionamento | B71: Salvar / alterar / excluir quando permitido pelo grupo.
A72: Resultado / saída | B72: Estado persistido do grupo lógico; manutenção pelos processos indicados. Não representa execução de uma operação nesta figura.
A73: Evidência visual | B73: Capturas da aplicação nas páginas seguintes. Veja a legenda de cada estado e a origem registrada.
A75: A07 — captura real 1/1
A76: Captura real da aplicação atual; dados de demonstração.
A77: Origem: http://localhost:8080/usuarios | Capturada em: 2026-10-25T22:02:46.577Z | A07.png

Sheet A08
A1: A08 — Lojas e configuração
A2: Sistema e tipo | B2: Estoque Inteligente — ALI
A3: Intenção / finalidade | B3: Manter Lojas e configuração como grupo lógico reconhecido pelo usuário.
A4: Fronteira e classificação | B4: Grupo persistente mantido pelo estoque; RL é tipo de registro, não quantidade de linhas.
A5: Rota / contexto | B5: /global e /iot/configuracao
A6: Permissões | B6: Superadministrador global; configuração IoT exige permissão iot e recurso iot.
A7: Evidência atual | B7: model/Loja.java; repository/LojaRepository.java; service/LojaService.java; service/ConfiguracaoIoTService.java; templates/global.html e iot.html
A8: Dados internos / regra | B8: Campos de negócio abaixo. Chaves técnicas, CSRF, versão de sessão e idempotência não são TD funcionais.
A10: Registro lógico | B10: Item de dado (TD) | C10: TD distinto | D10: RL distinto
A11: Registro de lojas e configuração | B11: código | C11: =IF(B11="",0,IF(COUNTIF($B$11:B11,B11)=1,1,0)) -> 1 | D11: =IF(A11="",0,IF(COUNTIF($A$11:A11,A11)=1,1,0)) -> 1
A12: Registro de lojas e configuração | B12: identificador público | C12: =IF(B12="",0,IF(COUNTIF($B$11:B12,B12)=1,1,0)) -> 1 | D12: =IF(A12="",0,IF(COUNTIF($A$11:A12,A12)=1,1,0)) -> 0
A13: Registro de lojas e configuração | B13: nome | C13: =IF(B13="",0,IF(COUNTIF($B$11:B13,B13)=1,1,0)) -> 1 | D13: =IF(A13="",0,IF(COUNTIF($A$11:A13,A13)=1,1,0)) -> 0
A14: Registro de lojas e configuração | B14: IoT | C14: =IF(B14="",0,IF(COUNTIF($B$11:B14,B14)=1,1,0)) -> 1 | D14: =IF(A14="",0,IF(COUNTIF($A$11:A14,A14)=1,1,0)) -> 0
A15: Registro de lojas e configuração | B15: relatórios | C15: =IF(B15="",0,IF(COUNTIF($B$11:B15,B15)=1,1,0)) -> 1 | D15: =IF(A15="",0,IF(COUNTIF($A$11:A15,A15)=1,1,0)) -> 0
A16: Registro de lojas e configuração | B16: ocupação | C16: =IF(B16="",0,IF(COUNTIF($B$11:B16,B16)=1,1,0)) -> 1 | D16: =IF(A16="",0,IF(COUNTIF($A$11:A16,A16)=1,1,0)) -> 0
A17: Registro de lojas e configuração | B17: fracionados | C17: =IF(B17="",0,IF(COUNTIF($B$11:B17,B17)=1,1,0)) -> 1 | D17: =IF(A17="",0,IF(COUNTIF($A$11:A17,A17)=1,1,0)) -> 0
A18: Registro de lojas e configuração | B18: host MQTT | C18: =IF(B18="",0,IF(COUNTIF($B$11:B18,B18)=1,1,0)) -> 1 | D18: =IF(A18="",0,IF(COUNTIF($A$11:A18,A18)=1,1,0)) -> 0
A19: Registro de lojas e configuração | B19: porta MQTT | C19: =IF(B19="",0,IF(COUNTIF($B$11:B19,B19)=1,1,0)) -> 1 | D19: =IF(A19="",0,IF(COUNTIF($A$11:A19,A19)=1,1,0)) -> 0
A20: Registro de lojas e configuração | B20: QoS | C20: =IF(B20="",0,IF(COUNTIF($B$11:B20,B20)=1,1,0)) -> 1 | D20: =IF(A20="",0,IF(COUNTIF($A$11:A20,A20)=1,1,0)) -> 0
A21: Registro de lojas e configuração | B21: tempo LED | C21: =IF(B21="",0,IF(COUNTIF($B$11:B21,B21)=1,1,0)) -> 1 | D21: =IF(A21="",0,IF(COUNTIF($A$11:A21,A21)=1,1,0)) -> 0
A22: Registro de lojas e configuração | B22: ativo | C22: =IF(B22="",0,IF(COUNTIF($B$11:B22,B22)=1,1,0)) -> 1 | D22: =IF(A22="",0,IF(COUNTIF($A$11:A22,A22)=1,1,0)) -> 0
C23: =IF(B23="",0,IF(COUNTIF($B$11:B23,B23)=1,1,0)) -> 0 | D23: =IF(A23="",0,IF(COUNTIF($A$11:A23,A23)=1,1,0)) -> 0
C24: =IF(B24="",0,IF(COUNTIF($B$11:B24,B24)=1,1,0)) -> 0 | D24: =IF(A24="",0,IF(COUNTIF($A$11:A24,A24)=1,1,0)) -> 0
C25: =IF(B25="",0,IF(COUNTIF($B$11:B25,B25)=1,1,0)) -> 0 | D25: =IF(A25="",0,IF(COUNTIF($A$11:A25,A25)=1,1,0)) -> 0
C26: =IF(B26="",0,IF(COUNTIF($B$11:B26,B26)=1,1,0)) -> 0 | D26: =IF(A26="",0,IF(COUNTIF($A$11:A26,A26)=1,1,0)) -> 0
C27: =IF(B27="",0,IF(COUNTIF($B$11:B27,B27)=1,1,0)) -> 0 | D27: =IF(A27="",0,IF(COUNTIF($A$11:A27,A27)=1,1,0)) -> 0
C28: =IF(B28="",0,IF(COUNTIF($B$11:B28,B28)=1,1,0)) -> 0 | D28: =IF(A28="",0,IF(COUNTIF($A$11:A28,A28)=1,1,0)) -> 0
C29: =IF(B29="",0,IF(COUNTIF($B$11:B29,B29)=1,1,0)) -> 0 | D29: =IF(A29="",0,IF(COUNTIF($A$11:A29,A29)=1,1,0)) -> 0
C30: =IF(B30="",0,IF(COUNTIF($B$11:B30,B30)=1,1,0)) -> 0 | D30: =IF(A30="",0,IF(COUNTIF($A$11:A30,A30)=1,1,0)) -> 0
C31: =IF(B31="",0,IF(COUNTIF($B$11:B31,B31)=1,1,0)) -> 0 | D31: =IF(A31="",0,IF(COUNTIF($A$11:A31,A31)=1,1,0)) -> 0
C32: =IF(B32="",0,IF(COUNTIF($B$11:B32,B32)=1,1,0)) -> 0 | D32: =IF(A32="",0,IF(COUNTIF($A$11:A32,A32)=1,1,0)) -> 0
C33: =IF(B33="",0,IF(COUNTIF($B$11:B33,B33)=1,1,0)) -> 0 | D33: =IF(A33="",0,IF(COUNTIF($A$11:A33,A33)=1,1,0)) -> 0
C34: =IF(B34="",0,IF(COUNTIF($B$11:B34,B34)=1,1,0)) -> 0 | D34: =IF(A34="",0,IF(COUNTIF($A$11:A34,A34)=1,1,0)) -> 0
... C42: =IF(B42="",0,IF(COUNTIF($B$11:B42,B42)=1,1,0)) -> 0 | D42: =IF(A42="",0,IF(COUNTIF($A$11:A42,A42)=1,1,0)) -> 0
A44: Manutenção do grupo lógico
A45: ALI / AIE | B45: Finalidade da referência | C45: AR entrada CE | D45: AR saída CE
A46: Manutenção | B46: Criar, alterar e desativar loja; configuração IoT é parte deste grupo.
A57: Regra AR / RL | B57: Somar RL distintos, não linhas armazenadas. Campos repetidos contam uma vez.
A59: Contagem calculada — entradas editáveis acima
A60: TD total distinto | B60: =SUM(C11:C42) -> 12 | C60: RL distintos | D60: =SUM(D11:D42) -> 1
A61: TD entrada CE | B61: =0 -> 0 | C61: TD saída sem repetição | D61: =0 -> 0
A62: AR entrada CE | B62: =0 -> 0 | C62: AR saída CE | D62: =0 -> 0
A63: Índice entrada CE | B63: =0 -> 0 | C63: Índice saída CE | D63: =0 -> 0
A64: Índice adotado | B64: =INDEX(Matrizes!$B$5:$D$7,IF(D60<=1,1,IF(D60<=5,2,3)),IF(B60<=19,1,IF(B60<=50,2,3))) -> 1 | C64: Complexidade | D64: =INDEX(Matrizes!$B$10:$D$10,1,B64) -> Simples
A65: Peso apropriado ao tipo | B65: =INDEX(Matrizes!$B$13:$D$17,MATCH("ALI",Matrizes!$A$13:$A$17,0),B64) -> 7 | C65: PF desta função | D65: =B65 -> 7
A67: Justificativa da contagem | B67: Peso por TD/RL da Parte I. Cada grupo entra uma única vez no coletivo.
A69: Fluxo da função — leitura do protótipo real
A70: Entrada / contexto | B70: código; identificador público; nome; IoT; relatórios; ocupação; fracionados; host MQTT; porta MQTT; QoS; tempo LED; ativo
A71: Acionamento | B71: Salvar / alterar / excluir quando permitido pelo grupo.
A72: Resultado / saída | B72: Estado persistido do grupo lógico; manutenção pelos processos indicados. Não representa execução de uma operação nesta figura.
A73: Evidência visual | B73: Capturas da aplicação nas páginas seguintes. Veja a legenda de cada estado e a origem registrada.
A75: A08 — captura real 1/1
A76: Captura real da aplicação atual; dados de demonstração.
A77: Origem: http://localhost:8080/iot/configuracao | Capturada em: 2026-10-25T22:02:46.703Z | A08.png

Sheet A09
A1: A09 — Auditoria consultável
A2: Sistema e tipo | B2: Estoque Inteligente — ALI
A3: Intenção / finalidade | B3: Manter Auditoria consultável como grupo lógico reconhecido pelo usuário.
A4: Fronteira e classificação | B4: Grupo persistente mantido pelo estoque; RL é tipo de registro, não quantidade de linhas.
A5: Rota / contexto | B5: /historico (Auditoria recente)
A6: Permissões | B6: Permissão historico e isolamento pela loja autenticada.
A7: Evidência atual | B7: model/RegistroAuditoria.java; repository/AuditoriaRepository.java; service/HistoricoService.java; templates/historico.html
A8: Dados internos / regra | B8: Campos de negócio abaixo. Chaves técnicas, CSRF, versão de sessão e idempotência não são TD funcionais.
A10: Registro lógico | B10: Item de dado (TD) | C10: TD distinto | D10: RL distinto
A11: Registro de auditoria consultável | B11: loja | C11: =IF(B11="",0,IF(COUNTIF($B$11:B11,B11)=1,1,0)) -> 1 | D11: =IF(A11="",0,IF(COUNTIF($A$11:A11,A11)=1,1,0)) -> 1
A12: Registro de auditoria consultável | B12: número | C12: =IF(B12="",0,IF(COUNTIF($B$11:B12,B12)=1,1,0)) -> 1 | D12: =IF(A12="",0,IF(COUNTIF($A$11:A12,A12)=1,1,0)) -> 0
A13: Registro de auditoria consultável | B13: responsável | C13: =IF(B13="",0,IF(COUNTIF($B$11:B13,B13)=1,1,0)) -> 1 | D13: =IF(A13="",0,IF(COUNTIF($A$11:A13,A13)=1,1,0)) -> 0
A14: Registro de auditoria consultável | B14: ação | C14: =IF(B14="",0,IF(COUNTIF($B$11:B14,B14)=1,1,0)) -> 1 | D14: =IF(A14="",0,IF(COUNTIF($A$11:A14,A14)=1,1,0)) -> 0
A15: Registro de auditoria consultável | B15: detalhe | C15: =IF(B15="",0,IF(COUNTIF($B$11:B15,B15)=1,1,0)) -> 1 | D15: =IF(A15="",0,IF(COUNTIF($A$11:A15,A15)=1,1,0)) -> 0
A16: Registro de auditoria consultável | B16: data | C16: =IF(B16="",0,IF(COUNTIF($B$11:B16,B16)=1,1,0)) -> 1 | D16: =IF(A16="",0,IF(COUNTIF($A$11:A16,A16)=1,1,0)) -> 0
C17: =IF(B17="",0,IF(COUNTIF($B$11:B17,B17)=1,1,0)) -> 0 | D17: =IF(A17="",0,IF(COUNTIF($A$11:A17,A17)=1,1,0)) -> 0
C18: =IF(B18="",0,IF(COUNTIF($B$11:B18,B18)=1,1,0)) -> 0 | D18: =IF(A18="",0,IF(COUNTIF($A$11:A18,A18)=1,1,0)) -> 0
C19: =IF(B19="",0,IF(COUNTIF($B$11:B19,B19)=1,1,0)) -> 0 | D19: =IF(A19="",0,IF(COUNTIF($A$11:A19,A19)=1,1,0)) -> 0
C20: =IF(B20="",0,IF(COUNTIF($B$11:B20,B20)=1,1,0)) -> 0 | D20: =IF(A20="",0,IF(COUNTIF($A$11:A20,A20)=1,1,0)) -> 0
C21: =IF(B21="",0,IF(COUNTIF($B$11:B21,B21)=1,1,0)) -> 0 | D21: =IF(A21="",0,IF(COUNTIF($A$11:A21,A21)=1,1,0)) -> 0
C22: =IF(B22="",0,IF(COUNTIF($B$11:B22,B22)=1,1,0)) -> 0 | D22: =IF(A22="",0,IF(COUNTIF($A$11:A22,A22)=1,1,0)) -> 0
C23: =IF(B23="",0,IF(COUNTIF($B$11:B23,B23)=1,1,0)) -> 0 | D23: =IF(A23="",0,IF(COUNTIF($A$11:A23,A23)=1,1,0)) -> 0
C24: =IF(B24="",0,IF(COUNTIF($B$11:B24,B24)=1,1,0)) -> 0 | D24: =IF(A24="",0,IF(COUNTIF($A$11:A24,A24)=1,1,0)) -> 0
C25: =IF(B25="",0,IF(COUNTIF($B$11:B25,B25)=1,1,0)) -> 0 | D25: =IF(A25="",0,IF(COUNTIF($A$11:A25,A25)=1,1,0)) -> 0
C26: =IF(B26="",0,IF(COUNTIF($B$11:B26,B26)=1,1,0)) -> 0 | D26: =IF(A26="",0,IF(COUNTIF($A$11:A26,A26)=1,1,0)) -> 0
C27: =IF(B27="",0,IF(COUNTIF($B$11:B27,B27)=1,1,0)) -> 0 | D27: =IF(A27="",0,IF(COUNTIF($A$11:A27,A27)=1,1,0)) -> 0
C28: =IF(B28="",0,IF(COUNTIF($B$11:B28,B28)=1,1,0)) -> 0 | D28: =IF(A28="",0,IF(COUNTIF($A$11:A28,A28)=1,1,0)) -> 0
... C42: =IF(B42="",0,IF(COUNTIF($B$11:B42,B42)=1,1,0)) -> 0 | D42: =IF(A42="",0,IF(COUNTIF($A$11:A42,A42)=1,1,0)) -> 0
A44: Manutenção do grupo lógico
A45: ALI / AIE | B45: Finalidade da referência | C45: AR entrada CE | D45: AR saída CE
A46: Manutenção | B46: Escrita automática pelas operações auditadas; consulta pelo histórico. Sem edição/exclusão pelo usuário.
A57: Regra AR / RL | B57: Somar RL distintos, não linhas armazenadas. Campos repetidos contam uma vez.
A59: Contagem calculada — entradas editáveis acima
A60: TD total distinto | B60: =SUM(C11:C42) -> 6 | C60: RL distintos | D60: =SUM(D11:D42) -> 1
A61: TD entrada CE | B61: =0 -> 0 | C61: TD saída sem repetição | D61: =0 -> 0
A62: AR entrada CE | B62: =0 -> 0 | C62: AR saída CE | D62: =0 -> 0
A63: Índice entrada CE | B63: =0 -> 0 | C63: Índice saída CE | D63: =0 -> 0
A64: Índice adotado | B64: =INDEX(Matrizes!$B$5:$D$7,IF(D60<=1,1,IF(D60<=5,2,3)),IF(B60<=19,1,IF(B60<=50,2,3))) -> 1 | C64: Complexidade | D64: =INDEX(Matrizes!$B$10:$D$10,1,B64) -> Simples
A65: Peso apropriado ao tipo | B65: =INDEX(Matrizes!$B$13:$D$17,MATCH("ALI",Matrizes!$A$13:$A$17,0),B64) -> 7 | C65: PF desta função | D65: =B65 -> 7
A67: Justificativa da contagem | B67: Peso por TD/RL da Parte I. Cada grupo entra uma única vez no coletivo.
A69: Fluxo da função — leitura do protótipo real
A70: Entrada / contexto | B70: loja; número; responsável; ação; detalhe; data
A71: Acionamento | B71: Salvar / alterar / excluir quando permitido pelo grupo.
A72: Resultado / saída | B72: Estado persistido do grupo lógico; manutenção pelos processos indicados. Não representa execução de uma operação nesta figura.
A73: Evidência visual | B73: Capturas da aplicação nas páginas seguintes. Veja a legenda de cada estado e a origem registrada.
A75: A09 — captura real 1/1
A76: Auditoria consultável real; dados de demonstração.
A77: Origem: http://localhost:8080/historico | Capturada em: 2026-10-25T22:02:48.686Z | A09.png

Sheet X01
A1: X01 — Fornecedores externos
A2: Sistema e tipo | B2: Estoque Inteligente — AIE
A3: Intenção / finalidade | B3: Consultar Fornecedores externos mantidos fora da fronteira.
A4: Fronteira e classificação | B4: Persistência TSV e manutenção CLI no provedor independente. O estoque executa somente GET.
A5: Rota / contexto | B5: /fornecedores
A6: Permissões | B6: Permissão consultar; /ocupacao também exige relatorios e recurso occupancy. Sem acesso entre lojas.
A7: Evidência atual | B7: external/fornecedores/Provedor.java; fornecedores.tsv; integration/FornecedorGateway.java
A8: Dados internos / regra | B8: Campos de negócio abaixo. Chaves técnicas, CSRF, versão de sessão e idempotência não são TD funcionais.
A10: Registro lógico | B10: Item de dado (TD) | C10: TD distinto | D10: RL distinto
A11: Registro de fornecedores externos | B11: código | C11: =IF(B11="",0,IF(COUNTIF($B$11:B11,B11)=1,1,0)) -> 1 | D11: =IF(A11="",0,IF(COUNTIF($A$11:A11,A11)=1,1,0)) -> 1
A12: Registro de fornecedores externos | B12: nome | C12: =IF(B12="",0,IF(COUNTIF($B$11:B12,B12)=1,1,0)) -> 1 | D12: =IF(A12="",0,IF(COUNTIF($A$11:A12,A12)=1,1,0)) -> 0
A13: Registro de fornecedores externos | B13: documento | C13: =IF(B13="",0,IF(COUNTIF($B$11:B13,B13)=1,1,0)) -> 1 | D13: =IF(A13="",0,IF(COUNTIF($A$11:A13,A13)=1,1,0)) -> 0
A14: Registro de fornecedores externos | B14: e-mail | C14: =IF(B14="",0,IF(COUNTIF($B$11:B14,B14)=1,1,0)) -> 1 | D14: =IF(A14="",0,IF(COUNTIF($A$11:A14,A14)=1,1,0)) -> 0
A15: Registro de fornecedores externos | B15: telefone | C15: =IF(B15="",0,IF(COUNTIF($B$11:B15,B15)=1,1,0)) -> 1 | D15: =IF(A15="",0,IF(COUNTIF($A$11:A15,A15)=1,1,0)) -> 0
C16: =IF(B16="",0,IF(COUNTIF($B$11:B16,B16)=1,1,0)) -> 0 | D16: =IF(A16="",0,IF(COUNTIF($A$11:A16,A16)=1,1,0)) -> 0
C17: =IF(B17="",0,IF(COUNTIF($B$11:B17,B17)=1,1,0)) -> 0 | D17: =IF(A17="",0,IF(COUNTIF($A$11:A17,A17)=1,1,0)) -> 0
C18: =IF(B18="",0,IF(COUNTIF($B$11:B18,B18)=1,1,0)) -> 0 | D18: =IF(A18="",0,IF(COUNTIF($A$11:A18,A18)=1,1,0)) -> 0
C19: =IF(B19="",0,IF(COUNTIF($B$11:B19,B19)=1,1,0)) -> 0 | D19: =IF(A19="",0,IF(COUNTIF($A$11:A19,A19)=1,1,0)) -> 0
C20: =IF(B20="",0,IF(COUNTIF($B$11:B20,B20)=1,1,0)) -> 0 | D20: =IF(A20="",0,IF(COUNTIF($A$11:A20,A20)=1,1,0)) -> 0
C21: =IF(B21="",0,IF(COUNTIF($B$11:B21,B21)=1,1,0)) -> 0 | D21: =IF(A21="",0,IF(COUNTIF($A$11:A21,A21)=1,1,0)) -> 0
C22: =IF(B22="",0,IF(COUNTIF($B$11:B22,B22)=1,1,0)) -> 0 | D22: =IF(A22="",0,IF(COUNTIF($A$11:A22,A22)=1,1,0)) -> 0
C23: =IF(B23="",0,IF(COUNTIF($B$11:B23,B23)=1,1,0)) -> 0 | D23: =IF(A23="",0,IF(COUNTIF($A$11:A23,A23)=1,1,0)) -> 0
C24: =IF(B24="",0,IF(COUNTIF($B$11:B24,B24)=1,1,0)) -> 0 | D24: =IF(A24="",0,IF(COUNTIF($A$11:A24,A24)=1,1,0)) -> 0
C25: =IF(B25="",0,IF(COUNTIF($B$11:B25,B25)=1,1,0)) -> 0 | D25: =IF(A25="",0,IF(COUNTIF($A$11:A25,A25)=1,1,0)) -> 0
C26: =IF(B26="",0,IF(COUNTIF($B$11:B26,B26)=1,1,0)) -> 0 | D26: =IF(A26="",0,IF(COUNTIF($A$11:A26,A26)=1,1,0)) -> 0
C27: =IF(B27="",0,IF(COUNTIF($B$11:B27,B27)=1,1,0)) -> 0 | D27: =IF(A27="",0,IF(COUNTIF($A$11:A27,A27)=1,1,0)) -> 0
... C42: =IF(B42="",0,IF(COUNTIF($B$11:B42,B42)=1,1,0)) -> 0 | D42: =IF(A42="",0,IF(COUNTIF($A$11:A42,A42)=1,1,0)) -> 0
A44: Manutenção do grupo lógico
A45: ALI / AIE | B45: Finalidade da referência | C45: AR entrada CE | D45: AR saída CE
A46: Manutenção | B46: CLI externa salvar/excluir; não incluída nas EEs do estoque.
A57: Regra AR / RL | B57: Somar RL distintos, não linhas armazenadas. Campos repetidos contam uma vez.
A59: Contagem calculada — entradas editáveis acima
A60: TD total distinto | B60: =SUM(C11:C42) -> 5 | C60: RL distintos | D60: =SUM(D11:D42) -> 1
A61: TD entrada CE | B61: =0 -> 0 | C61: TD saída sem repetição | D61: =0 -> 0
A62: AR entrada CE | B62: =0 -> 0 | C62: AR saída CE | D62: =0 -> 0
A63: Índice entrada CE | B63: =0 -> 0 | C63: Índice saída CE | D63: =0 -> 0
A64: Índice adotado | B64: =INDEX(Matrizes!$B$5:$D$7,IF(D60<=1,1,IF(D60<=5,2,3)),IF(B60<=19,1,IF(B60<=50,2,3))) -> 1 | C64: Complexidade | D64: =INDEX(Matrizes!$B$10:$D$10,1,B64) -> Simples
A65: Peso apropriado ao tipo | B65: =INDEX(Matrizes!$B$13:$D$17,MATCH("AIE",Matrizes!$A$13:$A$17,0),B64) -> 5 | C65: PF desta função | D65: =B65 -> 5
A67: Justificativa da contagem | B67: Peso por TD/RL da Parte I. Cada grupo entra uma única vez no coletivo.
A69: Fluxo da função — leitura do protótipo real
A70: Entrada / contexto | B70: código; nome; documento; e-mail; telefone
A71: Acionamento | B71: Consultar no estoque; manter no provedor externo.
A72: Resultado / saída | B72: Registros recuperados do provedor independente. Inclusão/alteração/exclusão via CLI externa, fora do PFB do estoque.
A73: Evidência visual | B73: Capturas da aplicação nas páginas seguintes. Veja a legenda de cada estado e a origem registrada.
A75: X01 — captura real 1/1
A76: Dados mantidos no provedor externo de fornecedores, consultados pela aplicação.
A77: Origem: http://localhost:8080/fornecedores | Capturada em: 2026-10-25T23:50:46.440373+00:00 | X01.png

Sheet X02
A1: X02 — Ofertas externas
A2: Sistema e tipo | B2: Estoque Inteligente — AIE
A3: Intenção / finalidade | B3: Consultar Ofertas externas mantidos fora da fronteira.
A4: Fronteira e classificação | B4: Persistência TSV e manutenção CLI no provedor independente. O estoque executa somente GET.
A5: Rota / contexto | B5: /ofertas
A6: Permissões | B6: Permissão consultar; /ocupacao também exige relatorios e recurso occupancy. Sem acesso entre lojas.
A7: Evidência atual | B7: external/ofertas/Provedor.java; ofertas.tsv; integration/OfertaGateway.java
A8: Dados internos / regra | B8: Campos de negócio abaixo. Chaves técnicas, CSRF, versão de sessão e idempotência não são TD funcionais.
A10: Registro lógico | B10: Item de dado (TD) | C10: TD distinto | D10: RL distinto
A11: Oferta comercial externa | B11: GTIN | C11: =IF(B11="",0,IF(COUNTIF($B$11:B11,B11)=1,1,0)) -> 1 | D11: =IF(A11="",0,IF(COUNTIF($A$11:A11,A11)=1,1,0)) -> 1
A12: Oferta comercial externa | B12: código do fornecedor | C12: =IF(B12="",0,IF(COUNTIF($B$11:B12,B12)=1,1,0)) -> 1 | D12: =IF(A12="",0,IF(COUNTIF($A$11:A12,A12)=1,1,0)) -> 0
A13: Oferta comercial externa | B13: SKU externo | C13: =IF(B13="",0,IF(COUNTIF($B$11:B13,B13)=1,1,0)) -> 1 | D13: =IF(A13="",0,IF(COUNTIF($A$11:A13,A13)=1,1,0)) -> 0
A14: Oferta comercial externa | B14: descrição | C14: =IF(B14="",0,IF(COUNTIF($B$11:B14,B14)=1,1,0)) -> 1 | D14: =IF(A14="",0,IF(COUNTIF($A$11:A14,A14)=1,1,0)) -> 0
A15: Oferta comercial externa | B15: marca | C15: =IF(B15="",0,IF(COUNTIF($B$11:B15,B15)=1,1,0)) -> 1 | D15: =IF(A15="",0,IF(COUNTIF($A$11:A15,A15)=1,1,0)) -> 0
A16: Oferta comercial externa | B16: unidade | C16: =IF(B16="",0,IF(COUNTIF($B$11:B16,B16)=1,1,0)) -> 1 | D16: =IF(A16="",0,IF(COUNTIF($A$11:A16,A16)=1,1,0)) -> 0
A17: Oferta comercial externa | B17: preço cotado | C17: =IF(B17="",0,IF(COUNTIF($B$11:B17,B17)=1,1,0)) -> 1 | D17: =IF(A17="",0,IF(COUNTIF($A$11:A17,A17)=1,1,0)) -> 0
A18: Oferta comercial externa | B18: disponibilidade | C18: =IF(B18="",0,IF(COUNTIF($B$11:B18,B18)=1,1,0)) -> 1 | D18: =IF(A18="",0,IF(COUNTIF($A$11:A18,A18)=1,1,0)) -> 0
A19: Oferta comercial externa | B19: data de atualização | C19: =IF(B19="",0,IF(COUNTIF($B$11:B19,B19)=1,1,0)) -> 1 | D19: =IF(A19="",0,IF(COUNTIF($A$11:A19,A19)=1,1,0)) -> 0
C20: =IF(B20="",0,IF(COUNTIF($B$11:B20,B20)=1,1,0)) -> 0 | D20: =IF(A20="",0,IF(COUNTIF($A$11:A20,A20)=1,1,0)) -> 0
C21: =IF(B21="",0,IF(COUNTIF($B$11:B21,B21)=1,1,0)) -> 0 | D21: =IF(A21="",0,IF(COUNTIF($A$11:A21,A21)=1,1,0)) -> 0
C22: =IF(B22="",0,IF(COUNTIF($B$11:B22,B22)=1,1,0)) -> 0 | D22: =IF(A22="",0,IF(COUNTIF($A$11:A22,A22)=1,1,0)) -> 0
C23: =IF(B23="",0,IF(COUNTIF($B$11:B23,B23)=1,1,0)) -> 0 | D23: =IF(A23="",0,IF(COUNTIF($A$11:A23,A23)=1,1,0)) -> 0
C24: =IF(B24="",0,IF(COUNTIF($B$11:B24,B24)=1,1,0)) -> 0 | D24: =IF(A24="",0,IF(COUNTIF($A$11:A24,A24)=1,1,0)) -> 0
C25: =IF(B25="",0,IF(COUNTIF($B$11:B25,B25)=1,1,0)) -> 0 | D25: =IF(A25="",0,IF(COUNTIF($A$11:A25,A25)=1,1,0)) -> 0
C26: =IF(B26="",0,IF(COUNTIF($B$11:B26,B26)=1,1,0)) -> 0 | D26: =IF(A26="",0,IF(COUNTIF($A$11:A26,A26)=1,1,0)) -> 0
C27: =IF(B27="",0,IF(COUNTIF($B$11:B27,B27)=1,1,0)) -> 0 | D27: =IF(A27="",0,IF(COUNTIF($A$11:A27,A27)=1,1,0)) -> 0
C28: =IF(B28="",0,IF(COUNTIF($B$11:B28,B28)=1,1,0)) -> 0 | D28: =IF(A28="",0,IF(COUNTIF($A$11:A28,A28)=1,1,0)) -> 0
C29: =IF(B29="",0,IF(COUNTIF($B$11:B29,B29)=1,1,0)) -> 0 | D29: =IF(A29="",0,IF(COUNTIF($A$11:A29,A29)=1,1,0)) -> 0
C30: =IF(B30="",0,IF(COUNTIF($B$11:B30,B30)=1,1,0)) -> 0 | D30: =IF(A30="",0,IF(COUNTIF($A$11:A30,A30)=1,1,0)) -> 0
C31: =IF(B31="",0,IF(COUNTIF($B$11:B31,B31)=1,1,0)) -> 0 | D31: =IF(A31="",0,IF(COUNTIF($A$11:A31,A31)=1,1,0)) -> 0
... C42: =IF(B42="",0,IF(COUNTIF($B$11:B42,B42)=1,1,0)) -> 0 | D42: =IF(A42="",0,IF(COUNTIF($A$11:A42,A42)=1,1,0)) -> 0
A44: Manutenção do grupo lógico
A45: ALI / AIE | B45: Finalidade da referência | C45: AR entrada CE | D45: AR saída CE
A46: Manutenção | B46: CLI externa salvar/excluir; não incluída nas EEs do estoque.
A57: Regra AR / RL | B57: Somar RL distintos, não linhas armazenadas. Campos repetidos contam uma vez.
A59: Contagem calculada — entradas editáveis acima
A60: TD total distinto | B60: =SUM(C11:C42) -> 9 | C60: RL distintos | D60: =SUM(D11:D42) -> 1
A61: TD entrada CE | B61: =0 -> 0 | C61: TD saída sem repetição | D61: =0 -> 0
A62: AR entrada CE | B62: =0 -> 0 | C62: AR saída CE | D62: =0 -> 0
A63: Índice entrada CE | B63: =0 -> 0 | C63: Índice saída CE | D63: =0 -> 0
A64: Índice adotado | B64: =INDEX(Matrizes!$B$5:$D$7,IF(D60<=1,1,IF(D60<=5,2,3)),IF(B60<=19,1,IF(B60<=50,2,3))) -> 1 | C64: Complexidade | D64: =INDEX(Matrizes!$B$10:$D$10,1,B64) -> Simples
A65: Peso apropriado ao tipo | B65: =INDEX(Matrizes!$B$13:$D$17,MATCH("AIE",Matrizes!$A$13:$A$17,0),B64) -> 5 | C65: PF desta função | D65: =B65 -> 5
A67: Justificativa da contagem | B67: Peso por TD/RL da Parte I. Cada grupo entra uma única vez no coletivo.
A69: Fluxo da função — leitura do protótipo real
A70: Entrada / contexto | B70: GTIN; código do fornecedor; SKU externo; descrição; marca; unidade; preço cotado; disponibilidade; data de atualização
A71: Acionamento | B71: Consultar no estoque; manter no provedor externo.
A72: Resultado / saída | B72: Registros recuperados do provedor independente. Inclusão/alteração/exclusão via CLI externa, fora do PFB do estoque.
A73: Evidência visual | B73: Capturas da aplicação nas páginas seguintes. Veja a legenda de cada estado e a origem registrada.
A75: X02 — captura real 1/1
A76: Dados mantidos no provedor externo de ofertas, consultados pela aplicação.
A77: Origem: http://localhost:8080/ofertas | Capturada em: 2026-10-25T23:50:47.142290+00:00 | X02.png

Sheet CE04
A1: CE04 — Consultar fornecedores externos
A2: Sistema e tipo | B2: Estoque Inteligente — CE
A3: Intenção / finalidade | B3: Consultar fornecedores externos
A4: Fronteira e classificação | B4: Consulta externa: recupera dados; não mantém arquivos nem deriva informação de negócio.
A5: Rota / contexto | B5: /fornecedores?q=F001
A6: Permissões | B6: Permissão consultar; /ocupacao também exige relatorios e recurso occupancy. Sem acesso entre lojas.
A7: Evidência atual | B7: GET /fornecedores?q=; AnaliseService.consultar; FornecedorGateway
A8: Dados internos / regra | B8: X01: código, nome, documento, e-mail, telefone
A10: Item que cruza a fronteira | B10: Fluxo | C10: TD entrada | D10: TD saída exclusiva
A11: filtro código, nome ou documento | B11: Entrada | C11: =IF(AND(A11<>"",B11<>"Saída",COUNTIF($A$11:A11,A11)=1),1,0) -> 1 | D11: =IF(AND(A11<>"",B11="Saída",COUNTIF($A$11:A11,A11)=1),1,0) -> 0
A12: acionamento | B12: Controle | C12: =IF(AND(A12<>"",B12<>"Saída",COUNTIF($A$11:A12,A12)=1),1,0) -> 1 | D12: =IF(AND(A12<>"",B12="Saída",COUNTIF($A$11:A12,A12)=1),1,0) -> 0
A13: mensagem de resultado | B13: Controle | C13: =IF(AND(A13<>"",B13<>"Saída",COUNTIF($A$11:A13,A13)=1),1,0) -> 1 | D13: =IF(AND(A13<>"",B13="Saída",COUNTIF($A$11:A13,A13)=1),1,0) -> 0
A14: código | B14: Saída | C14: =IF(AND(A14<>"",B14<>"Saída",COUNTIF($A$11:A14,A14)=1),1,0) -> 0 | D14: =IF(AND(A14<>"",B14="Saída",COUNTIF($A$11:A14,A14)=1),1,0) -> 1
A15: nome | B15: Saída | C15: =IF(AND(A15<>"",B15<>"Saída",COUNTIF($A$11:A15,A15)=1),1,0) -> 0 | D15: =IF(AND(A15<>"",B15="Saída",COUNTIF($A$11:A15,A15)=1),1,0) -> 1
A16: documento | B16: Saída | C16: =IF(AND(A16<>"",B16<>"Saída",COUNTIF($A$11:A16,A16)=1),1,0) -> 0 | D16: =IF(AND(A16<>"",B16="Saída",COUNTIF($A$11:A16,A16)=1),1,0) -> 1
A17: e-mail | B17: Saída | C17: =IF(AND(A17<>"",B17<>"Saída",COUNTIF($A$11:A17,A17)=1),1,0) -> 0 | D17: =IF(AND(A17<>"",B17="Saída",COUNTIF($A$11:A17,A17)=1),1,0) -> 1
A18: telefone | B18: Saída | C18: =IF(AND(A18<>"",B18<>"Saída",COUNTIF($A$11:A18,A18)=1),1,0) -> 0 | D18: =IF(AND(A18<>"",B18="Saída",COUNTIF($A$11:A18,A18)=1),1,0) -> 1
C19: =IF(AND(A19<>"",B19<>"Saída",COUNTIF($A$11:A19,A19)=1),1,0) -> 0 | D19: =IF(AND(A19<>"",B19="Saída",COUNTIF($A$11:A19,A19)=1),1,0) -> 0
C20: =IF(AND(A20<>"",B20<>"Saída",COUNTIF($A$11:A20,A20)=1),1,0) -> 0 | D20: =IF(AND(A20<>"",B20="Saída",COUNTIF($A$11:A20,A20)=1),1,0) -> 0
C21: =IF(AND(A21<>"",B21<>"Saída",COUNTIF($A$11:A21,A21)=1),1,0) -> 0 | D21: =IF(AND(A21<>"",B21="Saída",COUNTIF($A$11:A21,A21)=1),1,0) -> 0
C22: =IF(AND(A22<>"",B22<>"Saída",COUNTIF($A$11:A22,A22)=1),1,0) -> 0 | D22: =IF(AND(A22<>"",B22="Saída",COUNTIF($A$11:A22,A22)=1),1,0) -> 0
C23: =IF(AND(A23<>"",B23<>"Saída",COUNTIF($A$11:A23,A23)=1),1,0) -> 0 | D23: =IF(AND(A23<>"",B23="Saída",COUNTIF($A$11:A23,A23)=1),1,0) -> 0
C24: =IF(AND(A24<>"",B24<>"Saída",COUNTIF($A$11:A24,A24)=1),1,0) -> 0 | D24: =IF(AND(A24<>"",B24="Saída",COUNTIF($A$11:A24,A24)=1),1,0) -> 0
C25: =IF(AND(A25<>"",B25<>"Saída",COUNTIF($A$11:A25,A25)=1),1,0) -> 0 | D25: =IF(AND(A25<>"",B25="Saída",COUNTIF($A$11:A25,A25)=1),1,0) -> 0
C26: =IF(AND(A26<>"",B26<>"Saída",COUNTIF($A$11:A26,A26)=1),1,0) -> 0 | D26: =IF(AND(A26<>"",B26="Saída",COUNTIF($A$11:A26,A26)=1),1,0) -> 0
C27: =IF(AND(A27<>"",B27<>"Saída",COUNTIF($A$11:A27,A27)=1),1,0) -> 0 | D27: =IF(AND(A27<>"",B27="Saída",COUNTIF($A$11:A27,A27)=1),1,0) -> 0
C28: =IF(AND(A28<>"",B28<>"Saída",COUNTIF($A$11:A28,A28)=1),1,0) -> 0 | D28: =IF(AND(A28<>"",B28="Saída",COUNTIF($A$11:A28,A28)=1),1,0) -> 0
C29: =IF(AND(A29<>"",B29<>"Saída",COUNTIF($A$11:A29,A29)=1),1,0) -> 0 | D29: =IF(AND(A29<>"",B29="Saída",COUNTIF($A$11:A29,A29)=1),1,0) -> 0
C30: =IF(AND(A30<>"",B30<>"Saída",COUNTIF($A$11:A30,A30)=1),1,0) -> 0 | D30: =IF(AND(A30<>"",B30="Saída",COUNTIF($A$11:A30,A30)=1),1,0) -> 0
... C42: =IF(AND(A42<>"",B42<>"Saída",COUNTIF($A$11:A42,A42)=1),1,0) -> 0 | D42: =IF(AND(A42<>"",B42="Saída",COUNTIF($A$11:A42,A42)=1),1,0) -> 0
A44: Arquivos referenciados (cada grupo uma única vez)
A45: ALI / AIE | B45: Finalidade da referência | C45: AR entrada CE | D45: AR saída CE
A46: X01 | B46: Fornecedores externos | C46: 1 | D46: 1
A57: Regra AR / RL | B57: X01 aplica o filtro por código/nome/documento e fornece os dados recuperados. Na função, cada arquivo conta uma vez na união; as avaliações de entrada/saída usam suas referências próprias.
A59: Contagem calculada — entradas editáveis acima
A60: TD total distinto | B60: =SUM(C11:D42) -> 8 | C60: AR distintos | D60: =COUNTA(A46:A56) -> 1
A61: TD entrada CE | B61: =SUM(C11:C42) -> 3 | C61: TD saída sem repetição | D61: =SUM(D11:D42) -> 5
A62: AR entrada CE | B62: =SUM(C46:C56) -> 1 | C62: AR saída CE | D62: =SUM(D46:D56) -> 1
A63: Índice entrada CE | B63: =INDEX(Matrizes!$B$5:$D$7,IF(B62<=1,1,IF(B62<=2,2,3)),IF(B61<=4,1,IF(B61<=15,2,3))) -> 1 | C63: Índice saída CE | D63: =INDEX(Matrizes!$B$5:$D$7,IF(D62<=1,1,IF(D62<=3,2,3)),IF(D61<=5,1,IF(D61<=19,2,3))) -> 1
A64: Índice adotado | B64: =MAX(B63,D63) -> 1 | C64: Complexidade | D64: =INDEX(Matrizes!$B$10:$D$10,1,B64) -> Simples
A65: Peso apropriado ao tipo | B65: =INDEX(Matrizes!$B$13:$D$17,MATCH("CE",Matrizes!$A$13:$A$17,0),B64) -> 3 | C65: PF desta função | D65: =B65 -> 3
A67: Justificativa da contagem | B67: Parte III, p. 7 e 10–13: retirar TD repetidos, classificar entrada e saída separadamente, selecionar MAX. AR de cada lado ficam editáveis em C/D46:56.
A69: Fluxo da função — leitura do protótipo real
A70: Entrada / contexto | B70: filtro código, nome ou documento
A71: Acionamento | B71: Consultar / filtrar / selecionar; não enviar formulário de manutenção.
A72: Resultado / saída | B72: Campos recuperados: código; nome; documento; e-mail; telefone. Sem escrita nem dado de negócio derivado.
A73: Evidência visual | B73: Capturas da aplicação nas páginas seguintes. Veja a legenda de cada estado e a origem registrada.
A75: CE04 — captura real 1/2
A76: Captura real da aplicação atual; dados de demonstração.
A77: Origem: http://localhost:8080/fornecedores | Capturada em: 2026-10-25T22:02:47.534Z | CE04-entrada.png
A131: CE04 — captura real 2/2
A132: Captura real da aplicação atual; dados de demonstração.
A133: Origem: http://localhost:8080/fornecedores?q=F001 | Capturada em: 2026-10-25T22:02:47.652Z | CE04-saida.png

Sheet CE05
A1: CE05 — Consultar modelos
A2: Sistema e tipo | B2: Estoque Inteligente — CE
A3: Intenção / finalidade | B3: Consultar modelos
A4: Fronteira e classificação | B4: Consulta externa: recupera dados; não mantém arquivos nem deriva informação de negócio.
A5: Rota / contexto | B5: /modelos?id=…
A6: Permissões | B6: Permissão cadastros para manutenção; consultar para leitura quando aplicável. Loja sempre validada.
A7: Evidência atual | B7: ModeloProdutoService.listar/buscar
A8: Dados internos / regra | B8: A01: loja, código, nome, marca, categoria
A10: Item que cruza a fronteira | B10: Fluxo | C10: TD entrada | D10: TD saída exclusiva
A11: modelo | B11: Entrada | C11: =IF(AND(A11<>"",B11<>"Saída",COUNTIF($A$11:A11,A11)=1),1,0) -> 1 | D11: =IF(AND(A11<>"",B11="Saída",COUNTIF($A$11:A11,A11)=1),1,0) -> 0
A12: acionamento | B12: Controle | C12: =IF(AND(A12<>"",B12<>"Saída",COUNTIF($A$11:A12,A12)=1),1,0) -> 1 | D12: =IF(AND(A12<>"",B12="Saída",COUNTIF($A$11:A12,A12)=1),1,0) -> 0
A13: mensagem de resultado | B13: Controle | C13: =IF(AND(A13<>"",B13<>"Saída",COUNTIF($A$11:A13,A13)=1),1,0) -> 1 | D13: =IF(AND(A13<>"",B13="Saída",COUNTIF($A$11:A13,A13)=1),1,0) -> 0
A14: nome | B14: Saída | C14: =IF(AND(A14<>"",B14<>"Saída",COUNTIF($A$11:A14,A14)=1),1,0) -> 0 | D14: =IF(AND(A14<>"",B14="Saída",COUNTIF($A$11:A14,A14)=1),1,0) -> 1
A15: marca | B15: Saída | C15: =IF(AND(A15<>"",B15<>"Saída",COUNTIF($A$11:A15,A15)=1),1,0) -> 0 | D15: =IF(AND(A15<>"",B15="Saída",COUNTIF($A$11:A15,A15)=1),1,0) -> 1
A16: categoria | B16: Saída | C16: =IF(AND(A16<>"",B16<>"Saída",COUNTIF($A$11:A16,A16)=1),1,0) -> 0 | D16: =IF(AND(A16<>"",B16="Saída",COUNTIF($A$11:A16,A16)=1),1,0) -> 1
C17: =IF(AND(A17<>"",B17<>"Saída",COUNTIF($A$11:A17,A17)=1),1,0) -> 0 | D17: =IF(AND(A17<>"",B17="Saída",COUNTIF($A$11:A17,A17)=1),1,0) -> 0
C18: =IF(AND(A18<>"",B18<>"Saída",COUNTIF($A$11:A18,A18)=1),1,0) -> 0 | D18: =IF(AND(A18<>"",B18="Saída",COUNTIF($A$11:A18,A18)=1),1,0) -> 0
C19: =IF(AND(A19<>"",B19<>"Saída",COUNTIF($A$11:A19,A19)=1),1,0) -> 0 | D19: =IF(AND(A19<>"",B19="Saída",COUNTIF($A$11:A19,A19)=1),1,0) -> 0
C20: =IF(AND(A20<>"",B20<>"Saída",COUNTIF($A$11:A20,A20)=1),1,0) -> 0 | D20: =IF(AND(A20<>"",B20="Saída",COUNTIF($A$11:A20,A20)=1),1,0) -> 0
C21: =IF(AND(A21<>"",B21<>"Saída",COUNTIF($A$11:A21,A21)=1),1,0) -> 0 | D21: =IF(AND(A21<>"",B21="Saída",COUNTIF($A$11:A21,A21)=1),1,0) -> 0
C22: =IF(AND(A22<>"",B22<>"Saída",COUNTIF($A$11:A22,A22)=1),1,0) -> 0 | D22: =IF(AND(A22<>"",B22="Saída",COUNTIF($A$11:A22,A22)=1),1,0) -> 0
C23: =IF(AND(A23<>"",B23<>"Saída",COUNTIF($A$11:A23,A23)=1),1,0) -> 0 | D23: =IF(AND(A23<>"",B23="Saída",COUNTIF($A$11:A23,A23)=1),1,0) -> 0
C24: =IF(AND(A24<>"",B24<>"Saída",COUNTIF($A$11:A24,A24)=1),1,0) -> 0 | D24: =IF(AND(A24<>"",B24="Saída",COUNTIF($A$11:A24,A24)=1),1,0) -> 0
C25: =IF(AND(A25<>"",B25<>"Saída",COUNTIF($A$11:A25,A25)=1),1,0) -> 0 | D25: =IF(AND(A25<>"",B25="Saída",COUNTIF($A$11:A25,A25)=1),1,0) -> 0
C26: =IF(AND(A26<>"",B26<>"Saída",COUNTIF($A$11:A26,A26)=1),1,0) -> 0 | D26: =IF(AND(A26<>"",B26="Saída",COUNTIF($A$11:A26,A26)=1),1,0) -> 0
C27: =IF(AND(A27<>"",B27<>"Saída",COUNTIF($A$11:A27,A27)=1),1,0) -> 0 | D27: =IF(AND(A27<>"",B27="Saída",COUNTIF($A$11:A27,A27)=1),1,0) -> 0
C28: =IF(AND(A28<>"",B28<>"Saída",COUNTIF($A$11:A28,A28)=1),1,0) -> 0 | D28: =IF(AND(A28<>"",B28="Saída",COUNTIF($A$11:A28,A28)=1),1,0) -> 0
... C42: =IF(AND(A42<>"",B42<>"Saída",COUNTIF($A$11:A42,A42)=1),1,0) -> 0 | D42: =IF(AND(A42<>"",B42="Saída",COUNTIF($A$11:A42,A42)=1),1,0) -> 0
A44: Arquivos referenciados (cada grupo uma única vez)
A45: ALI / AIE | B45: Finalidade da referência | C45: AR entrada CE | D45: AR saída CE
A46: A01 | B46: Modelos de produto | C46: 1 | D46: 1
A57: Regra AR / RL | B57: A01 localiza o modelo pelo ID e fornece nome, marca e categoria. Na função, cada arquivo conta uma vez na união; as avaliações de entrada/saída usam suas referências próprias.
A59: Contagem calculada — entradas editáveis acima
A60: TD total distinto | B60: =SUM(C11:D42) -> 6 | C60: AR distintos | D60: =COUNTA(A46:A56) -> 1
A61: TD entrada CE | B61: =SUM(C11:C42) -> 3 | C61: TD saída sem repetição | D61: =SUM(D11:D42) -> 3
A62: AR entrada CE | B62: =SUM(C46:C56) -> 1 | C62: AR saída CE | D62: =SUM(D46:D56) -> 1
A63: Índice entrada CE | B63: =INDEX(Matrizes!$B$5:$D$7,IF(B62<=1,1,IF(B62<=2,2,3)),IF(B61<=4,1,IF(B61<=15,2,3))) -> 1 | C63: Índice saída CE | D63: =INDEX(Matrizes!$B$5:$D$7,IF(D62<=1,1,IF(D62<=3,2,3)),IF(D61<=5,1,IF(D61<=19,2,3))) -> 1
A64: Índice adotado | B64: =MAX(B63,D63) -> 1 | C64: Complexidade | D64: =INDEX(Matrizes!$B$10:$D$10,1,B64) -> Simples
A65: Peso apropriado ao tipo | B65: =INDEX(Matrizes!$B$13:$D$17,MATCH("CE",Matrizes!$A$13:$A$17,0),B64) -> 3 | C65: PF desta função | D65: =B65 -> 3
A67: Justificativa da contagem | B67: Parte III, p. 7 e 10–13: retirar TD repetidos, classificar entrada e saída separadamente, selecionar MAX. AR de cada lado ficam editáveis em C/D46:56.
A69: Fluxo da função — leitura do protótipo real
A70: Entrada / contexto | B70: modelo
A71: Acionamento | B71: Consultar / filtrar / selecionar; não enviar formulário de manutenção.
A72: Resultado / saída | B72: Campos recuperados: nome; marca; categoria. Sem escrita nem dado de negócio derivado.
A73: Evidência visual | B73: Capturas da aplicação nas páginas seguintes. Veja a legenda de cada estado e a origem registrada.
A75: CE05 — captura real 1/2
A76: Seleção do modelo na lista pelo link Editar; consulta GET anterior a qualquer manutenção.
A77: Origem: http://localhost:8080/modelos | Capturada em: 2026-10-25T23:50:44.961692+00:00 | CE05-entrada.png
A131: CE05 — captura real 2/2
A132: Nome, marca e categoria recuperados pelo ID; nenhum formulário de alteração foi enviado.
A133: Origem: http://localhost:8080/modelos?id=3 | Capturada em: 2026-10-25T23:50:45.718741+00:00 | CE05-saida.png

Sheet CE06
A1: CE06 — Consultar vínculos
A2: Sistema e tipo | B2: Estoque Inteligente — CE
A3: Intenção / finalidade | B3: Consultar vínculos
A4: Fronteira e classificação | B4: Consulta externa: recupera dados; não mantém arquivos nem deriva informação de negócio.
A5: Rota / contexto | B5: /vinculos?productId=…&positionId=…
A6: Permissões | B6: Permissão cadastros para manutenção; consultar para leitura quando aplicável. Loja sempre validada.
A7: Evidência atual | B7: VinculoService.listar/buscar
A8: Dados internos / regra | B8: A01: loja, código, nome, marca, categoria | A02: loja, código, modelo, SKU, código de barras, cor, tamanho, unidade, preço, características, ativo | A03: loja, identificador, código, setor, linha, coluna, capacidade, unidade, dispositivo, pino, ativo | A04: loja, produto, posição, quantidade
A10: Item que cruza a fronteira | B10: Fluxo | C10: TD entrada | D10: TD saída exclusiva
A11: produto | B11: Entrada | C11: =IF(AND(A11<>"",B11<>"Saída",COUNTIF($A$11:A11,A11)=1),1,0) -> 1 | D11: =IF(AND(A11<>"",B11="Saída",COUNTIF($A$11:A11,A11)=1),1,0) -> 0
A12: posição | B12: Entrada | C12: =IF(AND(A12<>"",B12<>"Saída",COUNTIF($A$11:A12,A12)=1),1,0) -> 1 | D12: =IF(AND(A12<>"",B12="Saída",COUNTIF($A$11:A12,A12)=1),1,0) -> 0
A13: acionamento | B13: Controle | C13: =IF(AND(A13<>"",B13<>"Saída",COUNTIF($A$11:A13,A13)=1),1,0) -> 1 | D13: =IF(AND(A13<>"",B13="Saída",COUNTIF($A$11:A13,A13)=1),1,0) -> 0
A14: mensagem de resultado | B14: Controle | C14: =IF(AND(A14<>"",B14<>"Saída",COUNTIF($A$11:A14,A14)=1),1,0) -> 1 | D14: =IF(AND(A14<>"",B14="Saída",COUNTIF($A$11:A14,A14)=1),1,0) -> 0
A15: SKU | B15: Saída | C15: =IF(AND(A15<>"",B15<>"Saída",COUNTIF($A$11:A15,A15)=1),1,0) -> 0 | D15: =IF(AND(A15<>"",B15="Saída",COUNTIF($A$11:A15,A15)=1),1,0) -> 1
A16: nome | B16: Saída | C16: =IF(AND(A16<>"",B16<>"Saída",COUNTIF($A$11:A16,A16)=1),1,0) -> 0 | D16: =IF(AND(A16<>"",B16="Saída",COUNTIF($A$11:A16,A16)=1),1,0) -> 1
A17: código da posição | B17: Saída | C17: =IF(AND(A17<>"",B17<>"Saída",COUNTIF($A$11:A17,A17)=1),1,0) -> 0 | D17: =IF(AND(A17<>"",B17="Saída",COUNTIF($A$11:A17,A17)=1),1,0) -> 1
A18: setor | B18: Saída | C18: =IF(AND(A18<>"",B18<>"Saída",COUNTIF($A$11:A18,A18)=1),1,0) -> 0 | D18: =IF(AND(A18<>"",B18="Saída",COUNTIF($A$11:A18,A18)=1),1,0) -> 1
A19: unidade | B19: Saída | C19: =IF(AND(A19<>"",B19<>"Saída",COUNTIF($A$11:A19,A19)=1),1,0) -> 0 | D19: =IF(AND(A19<>"",B19="Saída",COUNTIF($A$11:A19,A19)=1),1,0) -> 1
A20: quantidade | B20: Saída | C20: =IF(AND(A20<>"",B20<>"Saída",COUNTIF($A$11:A20,A20)=1),1,0) -> 0 | D20: =IF(AND(A20<>"",B20="Saída",COUNTIF($A$11:A20,A20)=1),1,0) -> 1
C21: =IF(AND(A21<>"",B21<>"Saída",COUNTIF($A$11:A21,A21)=1),1,0) -> 0 | D21: =IF(AND(A21<>"",B21="Saída",COUNTIF($A$11:A21,A21)=1),1,0) -> 0
C22: =IF(AND(A22<>"",B22<>"Saída",COUNTIF($A$11:A22,A22)=1),1,0) -> 0 | D22: =IF(AND(A22<>"",B22="Saída",COUNTIF($A$11:A22,A22)=1),1,0) -> 0
C23: =IF(AND(A23<>"",B23<>"Saída",COUNTIF($A$11:A23,A23)=1),1,0) -> 0 | D23: =IF(AND(A23<>"",B23="Saída",COUNTIF($A$11:A23,A23)=1),1,0) -> 0
C24: =IF(AND(A24<>"",B24<>"Saída",COUNTIF($A$11:A24,A24)=1),1,0) -> 0 | D24: =IF(AND(A24<>"",B24="Saída",COUNTIF($A$11:A24,A24)=1),1,0) -> 0
C25: =IF(AND(A25<>"",B25<>"Saída",COUNTIF($A$11:A25,A25)=1),1,0) -> 0 | D25: =IF(AND(A25<>"",B25="Saída",COUNTIF($A$11:A25,A25)=1),1,0) -> 0
C26: =IF(AND(A26<>"",B26<>"Saída",COUNTIF($A$11:A26,A26)=1),1,0) -> 0 | D26: =IF(AND(A26<>"",B26="Saída",COUNTIF($A$11:A26,A26)=1),1,0) -> 0
C27: =IF(AND(A27<>"",B27<>"Saída",COUNTIF($A$11:A27,A27)=1),1,0) -> 0 | D27: =IF(AND(A27<>"",B27="Saída",COUNTIF($A$11:A27,A27)=1),1,0) -> 0
C28: =IF(AND(A28<>"",B28<>"Saída",COUNTIF($A$11:A28,A28)=1),1,0) -> 0 | D28: =IF(AND(A28<>"",B28="Saída",COUNTIF($A$11:A28,A28)=1),1,0) -> 0
C29: =IF(AND(A29<>"",B29<>"Saída",COUNTIF($A$11:A29,A29)=1),1,0) -> 0 | D29: =IF(AND(A29<>"",B29="Saída",COUNTIF($A$11:A29,A29)=1),1,0) -> 0
C30: =IF(AND(A30<>"",B30<>"Saída",COUNTIF($A$11:A30,A30)=1),1,0) -> 0 | D30: =IF(AND(A30<>"",B30="Saída",COUNTIF($A$11:A30,A30)=1),1,0) -> 0
C31: =IF(AND(A31<>"",B31<>"Saída",COUNTIF($A$11:A31,A31)=1),1,0) -> 0 | D31: =IF(AND(A31<>"",B31="Saída",COUNTIF($A$11:A31,A31)=1),1,0) -> 0
C32: =IF(AND(A32<>"",B32<>"Saída",COUNTIF($A$11:A32,A32)=1),1,0) -> 0 | D32: =IF(AND(A32<>"",B32="Saída",COUNTIF($A$11:A32,A32)=1),1,0) -> 0
... C42: =IF(AND(A42<>"",B42<>"Saída",COUNTIF($A$11:A42,A42)=1),1,0) -> 0 | D42: =IF(AND(A42<>"",B42="Saída",COUNTIF($A$11:A42,A42)=1),1,0) -> 0
A44: Arquivos referenciados (cada grupo uma única vez)
A45: ALI / AIE | B45: Finalidade da referência | C45: AR entrada CE | D45: AR saída CE
A46: A01 | B46: Modelos de produto | C46: 1 | D46: 1
A47: A02 | B47: Produtos | C47: 1 | D47: 1
A48: A03 | B48: Posições | C48: 1 | D48: 1
A49: A04 | B49: Estoque por posição / vínculos | C49: 1 | D49: 1
A57: Regra AR / RL | B57: A01/A02/A03/A04 participam da busca do vínculo pela chave produto/posição e da apresentação do vínculo. A busca q do seletor de produtos reutiliza SE06 e não é nova função CE. Na função, cada arquivo conta uma vez na união; as avaliações de entrada/saída usam suas referências próprias.
A59: Contagem calculada — entradas editáveis acima
A60: TD total distinto | B60: =SUM(C11:D42) -> 10 | C60: AR distintos | D60: =COUNTA(A46:A56) -> 4
A61: TD entrada CE | B61: =SUM(C11:C42) -> 4 | C61: TD saída sem repetição | D61: =SUM(D11:D42) -> 6
A62: AR entrada CE | B62: =SUM(C46:C56) -> 4 | C62: AR saída CE | D62: =SUM(D46:D56) -> 4
A63: Índice entrada CE | B63: =INDEX(Matrizes!$B$5:$D$7,IF(B62<=1,1,IF(B62<=2,2,3)),IF(B61<=4,1,IF(B61<=15,2,3))) -> 2 | C63: Índice saída CE | D63: =INDEX(Matrizes!$B$5:$D$7,IF(D62<=1,1,IF(D62<=3,2,3)),IF(D61<=5,1,IF(D61<=19,2,3))) -> 3
A64: Índice adotado | B64: =MAX(B63,D63) -> 3 | C64: Complexidade | D64: =INDEX(Matrizes!$B$10:$D$10,1,B64) -> Complexa
A65: Peso apropriado ao tipo | B65: =INDEX(Matrizes!$B$13:$D$17,MATCH("CE",Matrizes!$A$13:$A$17,0),B64) -> 6 | C65: PF desta função | D65: =B65 -> 6
A67: Justificativa da contagem | B67: Parte III, p. 7 e 10–13: retirar TD repetidos, classificar entrada e saída separadamente, selecionar MAX. AR de cada lado ficam editáveis em C/D46:56.
A69: Fluxo da função — leitura do protótipo real
A70: Entrada / contexto | B70: produto; posição
A71: Acionamento | B71: Consultar / filtrar / selecionar; não enviar formulário de manutenção.
A72: Resultado / saída | B72: Campos recuperados: SKU; nome; código da posição; setor; unidade; quantidade. Sem escrita nem dado de negócio derivado.
A73: Evidência visual | B73: Capturas da aplicação nas páginas seguintes. Veja a legenda de cada estado e a origem registrada.
A75: CE06 — captura real 1/2
A76: Acionamento da consulta pela navegação autenticada; não há filtro obrigatório para a listagem.
A77: Origem: http://localhost:8080/ | Capturada em: 2026-10-25T23:50:47.843515+00:00 | CE06-entrada.png
A131: CE06 — captura real 2/2
A132: Resultado real da consulta na loja ativa. Os formulários visíveis não foram submetidos.
A133: Origem: http://localhost:8080/vinculos | Capturada em: 2026-10-25T23:50:48.569602+00:00 | CE06-saida.png

Sheet CE07
A1: CE07 — Consultar equipe e permissões
A2: Sistema e tipo | B2: Estoque Inteligente — CE
A3: Intenção / finalidade | B3: Consultar equipe e permissões
A4: Fronteira e classificação | B4: Consulta externa: recupera dados; não mantém arquivos nem deriva informação de negócio.
A5: Rota / contexto | B5: /usuarios?id=…
A6: Permissões | B6: Permissão usuarios; proteção do último administrador e impedimento de autoexclusão.
A7: Evidência atual | B7: UsuarioController.listar
A8: Dados internos / regra | B8: A06: loja, código, nome de usuário, senha, perfil, ativo | A07: loja, perfil, permissão
A10: Item que cruza a fronteira | B10: Fluxo | C10: TD entrada | D10: TD saída exclusiva
A11: usuário | B11: Entrada | C11: =IF(AND(A11<>"",B11<>"Saída",COUNTIF($A$11:A11,A11)=1),1,0) -> 1 | D11: =IF(AND(A11<>"",B11="Saída",COUNTIF($A$11:A11,A11)=1),1,0) -> 0
A12: acionamento | B12: Controle | C12: =IF(AND(A12<>"",B12<>"Saída",COUNTIF($A$11:A12,A12)=1),1,0) -> 1 | D12: =IF(AND(A12<>"",B12="Saída",COUNTIF($A$11:A12,A12)=1),1,0) -> 0
A13: mensagem de resultado | B13: Controle | C13: =IF(AND(A13<>"",B13<>"Saída",COUNTIF($A$11:A13,A13)=1),1,0) -> 1 | D13: =IF(AND(A13<>"",B13="Saída",COUNTIF($A$11:A13,A13)=1),1,0) -> 0
A14: nome de usuário | B14: Saída | C14: =IF(AND(A14<>"",B14<>"Saída",COUNTIF($A$11:A14,A14)=1),1,0) -> 0 | D14: =IF(AND(A14<>"",B14="Saída",COUNTIF($A$11:A14,A14)=1),1,0) -> 1
A15: perfil | B15: Saída | C15: =IF(AND(A15<>"",B15<>"Saída",COUNTIF($A$11:A15,A15)=1),1,0) -> 0 | D15: =IF(AND(A15<>"",B15="Saída",COUNTIF($A$11:A15,A15)=1),1,0) -> 1
A16: permissão | B16: Saída | C16: =IF(AND(A16<>"",B16<>"Saída",COUNTIF($A$11:A16,A16)=1),1,0) -> 0 | D16: =IF(AND(A16<>"",B16="Saída",COUNTIF($A$11:A16,A16)=1),1,0) -> 1
C17: =IF(AND(A17<>"",B17<>"Saída",COUNTIF($A$11:A17,A17)=1),1,0) -> 0 | D17: =IF(AND(A17<>"",B17="Saída",COUNTIF($A$11:A17,A17)=1),1,0) -> 0
C18: =IF(AND(A18<>"",B18<>"Saída",COUNTIF($A$11:A18,A18)=1),1,0) -> 0 | D18: =IF(AND(A18<>"",B18="Saída",COUNTIF($A$11:A18,A18)=1),1,0) -> 0
C19: =IF(AND(A19<>"",B19<>"Saída",COUNTIF($A$11:A19,A19)=1),1,0) -> 0 | D19: =IF(AND(A19<>"",B19="Saída",COUNTIF($A$11:A19,A19)=1),1,0) -> 0
C20: =IF(AND(A20<>"",B20<>"Saída",COUNTIF($A$11:A20,A20)=1),1,0) -> 0 | D20: =IF(AND(A20<>"",B20="Saída",COUNTIF($A$11:A20,A20)=1),1,0) -> 0
C21: =IF(AND(A21<>"",B21<>"Saída",COUNTIF($A$11:A21,A21)=1),1,0) -> 0 | D21: =IF(AND(A21<>"",B21="Saída",COUNTIF($A$11:A21,A21)=1),1,0) -> 0
C22: =IF(AND(A22<>"",B22<>"Saída",COUNTIF($A$11:A22,A22)=1),1,0) -> 0 | D22: =IF(AND(A22<>"",B22="Saída",COUNTIF($A$11:A22,A22)=1),1,0) -> 0
C23: =IF(AND(A23<>"",B23<>"Saída",COUNTIF($A$11:A23,A23)=1),1,0) -> 0 | D23: =IF(AND(A23<>"",B23="Saída",COUNTIF($A$11:A23,A23)=1),1,0) -> 0
C24: =IF(AND(A24<>"",B24<>"Saída",COUNTIF($A$11:A24,A24)=1),1,0) -> 0 | D24: =IF(AND(A24<>"",B24="Saída",COUNTIF($A$11:A24,A24)=1),1,0) -> 0
C25: =IF(AND(A25<>"",B25<>"Saída",COUNTIF($A$11:A25,A25)=1),1,0) -> 0 | D25: =IF(AND(A25<>"",B25="Saída",COUNTIF($A$11:A25,A25)=1),1,0) -> 0
C26: =IF(AND(A26<>"",B26<>"Saída",COUNTIF($A$11:A26,A26)=1),1,0) -> 0 | D26: =IF(AND(A26<>"",B26="Saída",COUNTIF($A$11:A26,A26)=1),1,0) -> 0
C27: =IF(AND(A27<>"",B27<>"Saída",COUNTIF($A$11:A27,A27)=1),1,0) -> 0 | D27: =IF(AND(A27<>"",B27="Saída",COUNTIF($A$11:A27,A27)=1),1,0) -> 0
C28: =IF(AND(A28<>"",B28<>"Saída",COUNTIF($A$11:A28,A28)=1),1,0) -> 0 | D28: =IF(AND(A28<>"",B28="Saída",COUNTIF($A$11:A28,A28)=1),1,0) -> 0
... C42: =IF(AND(A42<>"",B42<>"Saída",COUNTIF($A$11:A42,A42)=1),1,0) -> 0 | D42: =IF(AND(A42<>"",B42="Saída",COUNTIF($A$11:A42,A42)=1),1,0) -> 0
A44: Arquivos referenciados (cada grupo uma única vez)
A45: ALI / AIE | B45: Finalidade da referência | C45: AR entrada CE | D45: AR saída CE
A46: A06 | B46: Usuários | C46: 1 | D46: 1
A47: A07 | B47: Permissões por perfil | C47: 0 | D47: 1
A57: Regra AR / RL | B57: A06 localiza o usuário selecionado. A saída consulta A06 e A07 para apresentar usuários, perfis e a matriz de permissões; A07 não valida a entrada do usuário. Na função, cada arquivo conta uma vez na união; as avaliações de entrada/saída usam suas referências próprias.
A59: Contagem calculada — entradas editáveis acima
A60: TD total distinto | B60: =SUM(C11:D42) -> 6 | C60: AR distintos | D60: =COUNTA(A46:A56) -> 2
A61: TD entrada CE | B61: =SUM(C11:C42) -> 3 | C61: TD saída sem repetição | D61: =SUM(D11:D42) -> 3
A62: AR entrada CE | B62: =SUM(C46:C56) -> 1 | C62: AR saída CE | D62: =SUM(D46:D56) -> 2
A63: Índice entrada CE | B63: =INDEX(Matrizes!$B$5:$D$7,IF(B62<=1,1,IF(B62<=2,2,3)),IF(B61<=4,1,IF(B61<=15,2,3))) -> 1 | C63: Índice saída CE | D63: =INDEX(Matrizes!$B$5:$D$7,IF(D62<=1,1,IF(D62<=3,2,3)),IF(D61<=5,1,IF(D61<=19,2,3))) -> 1
A64: Índice adotado | B64: =MAX(B63,D63) -> 1 | C64: Complexidade | D64: =INDEX(Matrizes!$B$10:$D$10,1,B64) -> Simples
A65: Peso apropriado ao tipo | B65: =INDEX(Matrizes!$B$13:$D$17,MATCH("CE",Matrizes!$A$13:$A$17,0),B64) -> 3 | C65: PF desta função | D65: =B65 -> 3
A67: Justificativa da contagem | B67: Parte III, p. 7 e 10–13: retirar TD repetidos, classificar entrada e saída separadamente, selecionar MAX. AR de cada lado ficam editáveis em C/D46:56.
A69: Fluxo da função — leitura do protótipo real
A70: Entrada / contexto | B70: usuário
A71: Acionamento | B71: Consultar / filtrar / selecionar; não enviar formulário de manutenção.
A72: Resultado / saída | B72: Campos recuperados: nome de usuário; perfil; permissão. Sem escrita nem dado de negócio derivado.
A73: Evidência visual | B73: Capturas da aplicação nas páginas seguintes. Veja a legenda de cada estado e a origem registrada.
A75: CE07 — captura real 1/2
A76: Acionamento da consulta pela navegação autenticada; não há filtro obrigatório para a listagem.
A77: Origem: http://localhost:8080/ | Capturada em: 2026-10-25T23:50:49.384829+00:00 | CE07-entrada.png
A131: CE07 — captura real 2/2
A132: Resultado real da consulta na loja ativa. Os formulários visíveis não foram submetidos.
A133: Origem: http://localhost:8080/usuarios | Capturada em: 2026-10-25T23:50:50.105227+00:00 | CE07-saida.png

Sheet CE08
A1: CE08 — Consultar lojas
A2: Sistema e tipo | B2: Estoque Inteligente — CE
A3: Intenção / finalidade | B3: Consultar lojas
A4: Fronteira e classificação | B4: Consulta externa: recupera dados; não mantém arquivos nem deriva informação de negócio.
A5: Rota / contexto | B5: /global?id=…
A6: Permissões | B6: Superadministrador global; configuração IoT exige permissão iot e recurso iot.
A7: Evidência atual | B7: LojaController /global; LojaService.listar/editar
A8: Dados internos / regra | B8: A08: código, identificador público, nome, IoT, relatórios, ocupação, fracionados, host MQTT, porta MQTT, QoS, tempo LED, ativo
A10: Item que cruza a fronteira | B10: Fluxo | C10: TD entrada | D10: TD saída exclusiva
A11: loja | B11: Entrada | C11: =IF(AND(A11<>"",B11<>"Saída",COUNTIF($A$11:A11,A11)=1),1,0) -> 1 | D11: =IF(AND(A11<>"",B11="Saída",COUNTIF($A$11:A11,A11)=1),1,0) -> 0
A12: acionamento | B12: Controle | C12: =IF(AND(A12<>"",B12<>"Saída",COUNTIF($A$11:A12,A12)=1),1,0) -> 1 | D12: =IF(AND(A12<>"",B12="Saída",COUNTIF($A$11:A12,A12)=1),1,0) -> 0
A13: mensagem de resultado | B13: Controle | C13: =IF(AND(A13<>"",B13<>"Saída",COUNTIF($A$11:A13,A13)=1),1,0) -> 1 | D13: =IF(AND(A13<>"",B13="Saída",COUNTIF($A$11:A13,A13)=1),1,0) -> 0
A14: identificador público | B14: Saída | C14: =IF(AND(A14<>"",B14<>"Saída",COUNTIF($A$11:A14,A14)=1),1,0) -> 0 | D14: =IF(AND(A14<>"",B14="Saída",COUNTIF($A$11:A14,A14)=1),1,0) -> 1
A15: nome | B15: Saída | C15: =IF(AND(A15<>"",B15<>"Saída",COUNTIF($A$11:A15,A15)=1),1,0) -> 0 | D15: =IF(AND(A15<>"",B15="Saída",COUNTIF($A$11:A15,A15)=1),1,0) -> 1
A16: IoT | B16: Saída | C16: =IF(AND(A16<>"",B16<>"Saída",COUNTIF($A$11:A16,A16)=1),1,0) -> 0 | D16: =IF(AND(A16<>"",B16="Saída",COUNTIF($A$11:A16,A16)=1),1,0) -> 1
A17: relatórios | B17: Saída | C17: =IF(AND(A17<>"",B17<>"Saída",COUNTIF($A$11:A17,A17)=1),1,0) -> 0 | D17: =IF(AND(A17<>"",B17="Saída",COUNTIF($A$11:A17,A17)=1),1,0) -> 1
A18: ocupação | B18: Saída | C18: =IF(AND(A18<>"",B18<>"Saída",COUNTIF($A$11:A18,A18)=1),1,0) -> 0 | D18: =IF(AND(A18<>"",B18="Saída",COUNTIF($A$11:A18,A18)=1),1,0) -> 1
A19: fracionados | B19: Saída | C19: =IF(AND(A19<>"",B19<>"Saída",COUNTIF($A$11:A19,A19)=1),1,0) -> 0 | D19: =IF(AND(A19<>"",B19="Saída",COUNTIF($A$11:A19,A19)=1),1,0) -> 1
C20: =IF(AND(A20<>"",B20<>"Saída",COUNTIF($A$11:A20,A20)=1),1,0) -> 0 | D20: =IF(AND(A20<>"",B20="Saída",COUNTIF($A$11:A20,A20)=1),1,0) -> 0
C21: =IF(AND(A21<>"",B21<>"Saída",COUNTIF($A$11:A21,A21)=1),1,0) -> 0 | D21: =IF(AND(A21<>"",B21="Saída",COUNTIF($A$11:A21,A21)=1),1,0) -> 0
C22: =IF(AND(A22<>"",B22<>"Saída",COUNTIF($A$11:A22,A22)=1),1,0) -> 0 | D22: =IF(AND(A22<>"",B22="Saída",COUNTIF($A$11:A22,A22)=1),1,0) -> 0
C23: =IF(AND(A23<>"",B23<>"Saída",COUNTIF($A$11:A23,A23)=1),1,0) -> 0 | D23: =IF(AND(A23<>"",B23="Saída",COUNTIF($A$11:A23,A23)=1),1,0) -> 0
C24: =IF(AND(A24<>"",B24<>"Saída",COUNTIF($A$11:A24,A24)=1),1,0) -> 0 | D24: =IF(AND(A24<>"",B24="Saída",COUNTIF($A$11:A24,A24)=1),1,0) -> 0
C25: =IF(AND(A25<>"",B25<>"Saída",COUNTIF($A$11:A25,A25)=1),1,0) -> 0 | D25: =IF(AND(A25<>"",B25="Saída",COUNTIF($A$11:A25,A25)=1),1,0) -> 0
C26: =IF(AND(A26<>"",B26<>"Saída",COUNTIF($A$11:A26,A26)=1),1,0) -> 0 | D26: =IF(AND(A26<>"",B26="Saída",COUNTIF($A$11:A26,A26)=1),1,0) -> 0
C27: =IF(AND(A27<>"",B27<>"Saída",COUNTIF($A$11:A27,A27)=1),1,0) -> 0 | D27: =IF(AND(A27<>"",B27="Saída",COUNTIF($A$11:A27,A27)=1),1,0) -> 0
C28: =IF(AND(A28<>"",B28<>"Saída",COUNTIF($A$11:A28,A28)=1),1,0) -> 0 | D28: =IF(AND(A28<>"",B28="Saída",COUNTIF($A$11:A28,A28)=1),1,0) -> 0
C29: =IF(AND(A29<>"",B29<>"Saída",COUNTIF($A$11:A29,A29)=1),1,0) -> 0 | D29: =IF(AND(A29<>"",B29="Saída",COUNTIF($A$11:A29,A29)=1),1,0) -> 0
C30: =IF(AND(A30<>"",B30<>"Saída",COUNTIF($A$11:A30,A30)=1),1,0) -> 0 | D30: =IF(AND(A30<>"",B30="Saída",COUNTIF($A$11:A30,A30)=1),1,0) -> 0
C31: =IF(AND(A31<>"",B31<>"Saída",COUNTIF($A$11:A31,A31)=1),1,0) -> 0 | D31: =IF(AND(A31<>"",B31="Saída",COUNTIF($A$11:A31,A31)=1),1,0) -> 0
... C42: =IF(AND(A42<>"",B42<>"Saída",COUNTIF($A$11:A42,A42)=1),1,0) -> 0 | D42: =IF(AND(A42<>"",B42="Saída",COUNTIF($A$11:A42,A42)=1),1,0) -> 0
A44: Arquivos referenciados (cada grupo uma única vez)
A45: ALI / AIE | B45: Finalidade da referência | C45: AR entrada CE | D45: AR saída CE
A46: A08 | B46: Lojas e configuração | C46: 1 | D46: 1
A57: Regra AR / RL | B57: A08 localiza a loja selecionada e fornece seus dados e recursos. Na função, cada arquivo conta uma vez na união; as avaliações de entrada/saída usam suas referências próprias.
A59: Contagem calculada — entradas editáveis acima
A60: TD total distinto | B60: =SUM(C11:D42) -> 9 | C60: AR distintos | D60: =COUNTA(A46:A56) -> 1
A61: TD entrada CE | B61: =SUM(C11:C42) -> 3 | C61: TD saída sem repetição | D61: =SUM(D11:D42) -> 6
A62: AR entrada CE | B62: =SUM(C46:C56) -> 1 | C62: AR saída CE | D62: =SUM(D46:D56) -> 1
A63: Índice entrada CE | B63: =INDEX(Matrizes!$B$5:$D$7,IF(B62<=1,1,IF(B62<=2,2,3)),IF(B61<=4,1,IF(B61<=15,2,3))) -> 1 | C63: Índice saída CE | D63: =INDEX(Matrizes!$B$5:$D$7,IF(D62<=1,1,IF(D62<=3,2,3)),IF(D61<=5,1,IF(D61<=19,2,3))) -> 1
A64: Índice adotado | B64: =MAX(B63,D63) -> 1 | C64: Complexidade | D64: =INDEX(Matrizes!$B$10:$D$10,1,B64) -> Simples
A65: Peso apropriado ao tipo | B65: =INDEX(Matrizes!$B$13:$D$17,MATCH("CE",Matrizes!$A$13:$A$17,0),B64) -> 3 | C65: PF desta função | D65: =B65 -> 3
A67: Justificativa da contagem | B67: Parte III, p. 7 e 10–13: retirar TD repetidos, classificar entrada e saída separadamente, selecionar MAX. AR de cada lado ficam editáveis em C/D46:56.
A69: Fluxo da função — leitura do protótipo real
A70: Entrada / contexto | B70: loja
A71: Acionamento | B71: Consultar / filtrar / selecionar; não enviar formulário de manutenção.
A72: Resultado / saída | B72: Campos recuperados: identificador público; nome; IoT; relatórios; ocupação; fracionados. Sem escrita nem dado de negócio derivado.
A73: Evidência visual | B73: Capturas da aplicação nas páginas seguintes. Veja a legenda de cada estado e a origem registrada.
A75: CE08 — captura real 1/2
A76: Consulta global, entrada e lista.
A77: Origem: http://localhost:8080/global | Capturada em: 2026-10-25T22:02:50.760Z | CE08-entrada.png
A131: CE08 — captura real 2/2
A132: Loja selecionada e atributos recuperados.
A133: Origem: http://localhost:8080/global?id=3 | Capturada em: 2026-10-25T22:02:50.905Z | CE08-saida.png

Sheet CE09
A1: CE09 — Consultar configuração IoT
A2: Sistema e tipo | B2: Estoque Inteligente — CE
A3: Intenção / finalidade | B3: Consultar configuração IoT
A4: Fronteira e classificação | B4: Consulta externa: recupera dados; não mantém arquivos nem deriva informação de negócio.
A5: Rota / contexto | B5: /iot/configuracao
A6: Permissões | B6: Permissão iot e recurso iot habilitado.
A7: Evidência atual | B7: ConfiguracaoIoTService.buscar
A8: Dados internos / regra | B8: A08: código, identificador público, nome, IoT, relatórios, ocupação, fracionados, host MQTT, porta MQTT, QoS, tempo LED, ativo
A10: Item que cruza a fronteira | B10: Fluxo | C10: TD entrada | D10: TD saída exclusiva
A11: acionamento | B11: Controle | C11: =IF(AND(A11<>"",B11<>"Saída",COUNTIF($A$11:A11,A11)=1),1,0) -> 1 | D11: =IF(AND(A11<>"",B11="Saída",COUNTIF($A$11:A11,A11)=1),1,0) -> 0
A12: mensagem de resultado | B12: Controle | C12: =IF(AND(A12<>"",B12<>"Saída",COUNTIF($A$11:A12,A12)=1),1,0) -> 1 | D12: =IF(AND(A12<>"",B12="Saída",COUNTIF($A$11:A12,A12)=1),1,0) -> 0
A13: host MQTT | B13: Saída | C13: =IF(AND(A13<>"",B13<>"Saída",COUNTIF($A$11:A13,A13)=1),1,0) -> 0 | D13: =IF(AND(A13<>"",B13="Saída",COUNTIF($A$11:A13,A13)=1),1,0) -> 1
A14: porta MQTT | B14: Saída | C14: =IF(AND(A14<>"",B14<>"Saída",COUNTIF($A$11:A14,A14)=1),1,0) -> 0 | D14: =IF(AND(A14<>"",B14="Saída",COUNTIF($A$11:A14,A14)=1),1,0) -> 1
A15: QoS | B15: Saída | C15: =IF(AND(A15<>"",B15<>"Saída",COUNTIF($A$11:A15,A15)=1),1,0) -> 0 | D15: =IF(AND(A15<>"",B15="Saída",COUNTIF($A$11:A15,A15)=1),1,0) -> 1
A16: tempo LED | B16: Saída | C16: =IF(AND(A16<>"",B16<>"Saída",COUNTIF($A$11:A16,A16)=1),1,0) -> 0 | D16: =IF(AND(A16<>"",B16="Saída",COUNTIF($A$11:A16,A16)=1),1,0) -> 1
C17: =IF(AND(A17<>"",B17<>"Saída",COUNTIF($A$11:A17,A17)=1),1,0) -> 0 | D17: =IF(AND(A17<>"",B17="Saída",COUNTIF($A$11:A17,A17)=1),1,0) -> 0
C18: =IF(AND(A18<>"",B18<>"Saída",COUNTIF($A$11:A18,A18)=1),1,0) -> 0 | D18: =IF(AND(A18<>"",B18="Saída",COUNTIF($A$11:A18,A18)=1),1,0) -> 0
C19: =IF(AND(A19<>"",B19<>"Saída",COUNTIF($A$11:A19,A19)=1),1,0) -> 0 | D19: =IF(AND(A19<>"",B19="Saída",COUNTIF($A$11:A19,A19)=1),1,0) -> 0
C20: =IF(AND(A20<>"",B20<>"Saída",COUNTIF($A$11:A20,A20)=1),1,0) -> 0 | D20: =IF(AND(A20<>"",B20="Saída",COUNTIF($A$11:A20,A20)=1),1,0) -> 0
C21: =IF(AND(A21<>"",B21<>"Saída",COUNTIF($A$11:A21,A21)=1),1,0) -> 0 | D21: =IF(AND(A21<>"",B21="Saída",COUNTIF($A$11:A21,A21)=1),1,0) -> 0
C22: =IF(AND(A22<>"",B22<>"Saída",COUNTIF($A$11:A22,A22)=1),1,0) -> 0 | D22: =IF(AND(A22<>"",B22="Saída",COUNTIF($A$11:A22,A22)=1),1,0) -> 0
C23: =IF(AND(A23<>"",B23<>"Saída",COUNTIF($A$11:A23,A23)=1),1,0) -> 0 | D23: =IF(AND(A23<>"",B23="Saída",COUNTIF($A$11:A23,A23)=1),1,0) -> 0
C24: =IF(AND(A24<>"",B24<>"Saída",COUNTIF($A$11:A24,A24)=1),1,0) -> 0 | D24: =IF(AND(A24<>"",B24="Saída",COUNTIF($A$11:A24,A24)=1),1,0) -> 0
C25: =IF(AND(A25<>"",B25<>"Saída",COUNTIF($A$11:A25,A25)=1),1,0) -> 0 | D25: =IF(AND(A25<>"",B25="Saída",COUNTIF($A$11:A25,A25)=1),1,0) -> 0
C26: =IF(AND(A26<>"",B26<>"Saída",COUNTIF($A$11:A26,A26)=1),1,0) -> 0 | D26: =IF(AND(A26<>"",B26="Saída",COUNTIF($A$11:A26,A26)=1),1,0) -> 0
C27: =IF(AND(A27<>"",B27<>"Saída",COUNTIF($A$11:A27,A27)=1),1,0) -> 0 | D27: =IF(AND(A27<>"",B27="Saída",COUNTIF($A$11:A27,A27)=1),1,0) -> 0
C28: =IF(AND(A28<>"",B28<>"Saída",COUNTIF($A$11:A28,A28)=1),1,0) -> 0 | D28: =IF(AND(A28<>"",B28="Saída",COUNTIF($A$11:A28,A28)=1),1,0) -> 0
... C42: =IF(AND(A42<>"",B42<>"Saída",COUNTIF($A$11:A42,A42)=1),1,0) -> 0 | D42: =IF(AND(A42<>"",B42="Saída",COUNTIF($A$11:A42,A42)=1),1,0) -> 0
A44: Arquivos referenciados (cada grupo uma única vez)
A45: ALI / AIE | B45: Finalidade da referência | C45: AR entrada CE | D45: AR saída CE
A46: A08 | B46: Lojas e configuração | C46: 0 | D46: 1
A57: Regra AR / RL | B57: Sem seleção de registro nem validação de dado de negócio na entrada; o acionamento usa a loja da sessão. A08 é lido para apresentar a configuração. Na função, cada arquivo conta uma vez na união; as avaliações de entrada/saída usam suas referências próprias.
A59: Contagem calculada — entradas editáveis acima
A60: TD total distinto | B60: =SUM(C11:D42) -> 6 | C60: AR distintos | D60: =COUNTA(A46:A56) -> 1
A61: TD entrada CE | B61: =SUM(C11:C42) -> 2 | C61: TD saída sem repetição | D61: =SUM(D11:D42) -> 4
A62: AR entrada CE | B62: =SUM(C46:C56) -> 0 | C62: AR saída CE | D62: =SUM(D46:D56) -> 1
A63: Índice entrada CE | B63: =INDEX(Matrizes!$B$5:$D$7,IF(B62<=1,1,IF(B62<=2,2,3)),IF(B61<=4,1,IF(B61<=15,2,3))) -> 1 | C63: Índice saída CE | D63: =INDEX(Matrizes!$B$5:$D$7,IF(D62<=1,1,IF(D62<=3,2,3)),IF(D61<=5,1,IF(D61<=19,2,3))) -> 1
A64: Índice adotado | B64: =MAX(B63,D63) -> 1 | C64: Complexidade | D64: =INDEX(Matrizes!$B$10:$D$10,1,B64) -> Simples
A65: Peso apropriado ao tipo | B65: =INDEX(Matrizes!$B$13:$D$17,MATCH("CE",Matrizes!$A$13:$A$17,0),B64) -> 3 | C65: PF desta função | D65: =B65 -> 3
A67: Justificativa da contagem | B67: Parte III, p. 7 e 10–13: retirar TD repetidos, classificar entrada e saída separadamente, selecionar MAX. AR de cada lado ficam editáveis em C/D46:56.
A69: Fluxo da função — leitura do protótipo real
A70: Entrada / contexto | B70: Acessar a rota e acionar a consulta/comando; contexto de loja vem da sessão.
A71: Acionamento | B71: Consultar / filtrar / selecionar; não enviar formulário de manutenção.
A72: Resultado / saída | B72: Campos recuperados: host MQTT; porta MQTT; QoS; tempo LED. Sem escrita nem dado de negócio derivado.
A73: Evidência visual | B73: Capturas da aplicação nas páginas seguintes. Veja a legenda de cada estado e a origem registrada.
A75: CE09 — captura real 1/2
A76: Acionamento da consulta pela navegação autenticada; não há filtro obrigatório para a listagem.
A77: Origem: http://localhost:8080/ | Capturada em: 2026-10-25T23:50:50.820940+00:00 | CE09-entrada.png
A131: CE09 — captura real 2/2
A132: Resultado real da consulta na loja ativa. Os formulários visíveis não foram submetidos.
A133: Origem: http://localhost:8080/iot/configuracao | Capturada em: 2026-10-25T23:50:51.537994+00:00 | CE09-saida.png

Sheet CE11
A1: CE11 — Consultar auditoria
A2: Sistema e tipo | B2: Estoque Inteligente — CE
A3: Intenção / finalidade | B3: Consultar auditoria
A4: Fronteira e classificação | B4: Consulta externa: recupera dados; não mantém arquivos nem deriva informação de negócio.
A5: Rota / contexto | B5: /historico (Auditoria recente)
A6: Permissões | B6: Permissão historico e isolamento pela loja autenticada.
A7: Evidência atual | B7: HistoricoService.auditoria
A8: Dados internos / regra | B8: A06: loja, código, nome de usuário, senha, perfil, ativo | A09: loja, número, responsável, ação, detalhe, data
A10: Item que cruza a fronteira | B10: Fluxo | C10: TD entrada | D10: TD saída exclusiva
A11: acionamento | B11: Controle | C11: =IF(AND(A11<>"",B11<>"Saída",COUNTIF($A$11:A11,A11)=1),1,0) -> 1 | D11: =IF(AND(A11<>"",B11="Saída",COUNTIF($A$11:A11,A11)=1),1,0) -> 0
A12: mensagem de resultado | B12: Controle | C12: =IF(AND(A12<>"",B12<>"Saída",COUNTIF($A$11:A12,A12)=1),1,0) -> 1 | D12: =IF(AND(A12<>"",B12="Saída",COUNTIF($A$11:A12,A12)=1),1,0) -> 0
A13: data | B13: Saída | C13: =IF(AND(A13<>"",B13<>"Saída",COUNTIF($A$11:A13,A13)=1),1,0) -> 0 | D13: =IF(AND(A13<>"",B13="Saída",COUNTIF($A$11:A13,A13)=1),1,0) -> 1
A14: responsável | B14: Saída | C14: =IF(AND(A14<>"",B14<>"Saída",COUNTIF($A$11:A14,A14)=1),1,0) -> 0 | D14: =IF(AND(A14<>"",B14="Saída",COUNTIF($A$11:A14,A14)=1),1,0) -> 1
A15: ação | B15: Saída | C15: =IF(AND(A15<>"",B15<>"Saída",COUNTIF($A$11:A15,A15)=1),1,0) -> 0 | D15: =IF(AND(A15<>"",B15="Saída",COUNTIF($A$11:A15,A15)=1),1,0) -> 1
A16: detalhe | B16: Saída | C16: =IF(AND(A16<>"",B16<>"Saída",COUNTIF($A$11:A16,A16)=1),1,0) -> 0 | D16: =IF(AND(A16<>"",B16="Saída",COUNTIF($A$11:A16,A16)=1),1,0) -> 1
C17: =IF(AND(A17<>"",B17<>"Saída",COUNTIF($A$11:A17,A17)=1),1,0) -> 0 | D17: =IF(AND(A17<>"",B17="Saída",COUNTIF($A$11:A17,A17)=1),1,0) -> 0
C18: =IF(AND(A18<>"",B18<>"Saída",COUNTIF($A$11:A18,A18)=1),1,0) -> 0 | D18: =IF(AND(A18<>"",B18="Saída",COUNTIF($A$11:A18,A18)=1),1,0) -> 0
C19: =IF(AND(A19<>"",B19<>"Saída",COUNTIF($A$11:A19,A19)=1),1,0) -> 0 | D19: =IF(AND(A19<>"",B19="Saída",COUNTIF($A$11:A19,A19)=1),1,0) -> 0
C20: =IF(AND(A20<>"",B20<>"Saída",COUNTIF($A$11:A20,A20)=1),1,0) -> 0 | D20: =IF(AND(A20<>"",B20="Saída",COUNTIF($A$11:A20,A20)=1),1,0) -> 0
C21: =IF(AND(A21<>"",B21<>"Saída",COUNTIF($A$11:A21,A21)=1),1,0) -> 0 | D21: =IF(AND(A21<>"",B21="Saída",COUNTIF($A$11:A21,A21)=1),1,0) -> 0
C22: =IF(AND(A22<>"",B22<>"Saída",COUNTIF($A$11:A22,A22)=1),1,0) -> 0 | D22: =IF(AND(A22<>"",B22="Saída",COUNTIF($A$11:A22,A22)=1),1,0) -> 0
C23: =IF(AND(A23<>"",B23<>"Saída",COUNTIF($A$11:A23,A23)=1),1,0) -> 0 | D23: =IF(AND(A23<>"",B23="Saída",COUNTIF($A$11:A23,A23)=1),1,0) -> 0
C24: =IF(AND(A24<>"",B24<>"Saída",COUNTIF($A$11:A24,A24)=1),1,0) -> 0 | D24: =IF(AND(A24<>"",B24="Saída",COUNTIF($A$11:A24,A24)=1),1,0) -> 0
C25: =IF(AND(A25<>"",B25<>"Saída",COUNTIF($A$11:A25,A25)=1),1,0) -> 0 | D25: =IF(AND(A25<>"",B25="Saída",COUNTIF($A$11:A25,A25)=1),1,0) -> 0
C26: =IF(AND(A26<>"",B26<>"Saída",COUNTIF($A$11:A26,A26)=1),1,0) -> 0 | D26: =IF(AND(A26<>"",B26="Saída",COUNTIF($A$11:A26,A26)=1),1,0) -> 0
C27: =IF(AND(A27<>"",B27<>"Saída",COUNTIF($A$11:A27,A27)=1),1,0) -> 0 | D27: =IF(AND(A27<>"",B27="Saída",COUNTIF($A$11:A27,A27)=1),1,0) -> 0
C28: =IF(AND(A28<>"",B28<>"Saída",COUNTIF($A$11:A28,A28)=1),1,0) -> 0 | D28: =IF(AND(A28<>"",B28="Saída",COUNTIF($A$11:A28,A28)=1),1,0) -> 0
... C42: =IF(AND(A42<>"",B42<>"Saída",COUNTIF($A$11:A42,A42)=1),1,0) -> 0 | D42: =IF(AND(A42<>"",B42="Saída",COUNTIF($A$11:A42,A42)=1),1,0) -> 0
A44: Arquivos referenciados (cada grupo uma única vez)
A45: ALI / AIE | B45: Finalidade da referência | C45: AR entrada CE | D45: AR saída CE
A46: A06 | B46: Usuários | C46: 0 | D46: 1
A47: A09 | B47: Auditoria consultável | C47: 0 | D47: 1
A57: Regra AR / RL | B57: Sem filtro de negócio na entrada; o acionamento usa a loja da sessão. A09 e A06 são lidos na saída para listar eventos e responsáveis. Na função, cada arquivo conta uma vez na união; as avaliações de entrada/saída usam suas referências próprias.
A59: Contagem calculada — entradas editáveis acima
A60: TD total distinto | B60: =SUM(C11:D42) -> 6 | C60: AR distintos | D60: =COUNTA(A46:A56) -> 2
A61: TD entrada CE | B61: =SUM(C11:C42) -> 2 | C61: TD saída sem repetição | D61: =SUM(D11:D42) -> 4
A62: AR entrada CE | B62: =SUM(C46:C56) -> 0 | C62: AR saída CE | D62: =SUM(D46:D56) -> 2
A63: Índice entrada CE | B63: =INDEX(Matrizes!$B$5:$D$7,IF(B62<=1,1,IF(B62<=2,2,3)),IF(B61<=4,1,IF(B61<=15,2,3))) -> 1 | C63: Índice saída CE | D63: =INDEX(Matrizes!$B$5:$D$7,IF(D62<=1,1,IF(D62<=3,2,3)),IF(D61<=5,1,IF(D61<=19,2,3))) -> 1
A64: Índice adotado | B64: =MAX(B63,D63) -> 1 | C64: Complexidade | D64: =INDEX(Matrizes!$B$10:$D$10,1,B64) -> Simples
A65: Peso apropriado ao tipo | B65: =INDEX(Matrizes!$B$13:$D$17,MATCH("CE",Matrizes!$A$13:$A$17,0),B64) -> 3 | C65: PF desta função | D65: =B65 -> 3
A67: Justificativa da contagem | B67: Parte III, p. 7 e 10–13: retirar TD repetidos, classificar entrada e saída separadamente, selecionar MAX. AR de cada lado ficam editáveis em C/D46:56.
A69: Fluxo da função — leitura do protótipo real
A70: Entrada / contexto | B70: Acessar a rota e acionar a consulta/comando; contexto de loja vem da sessão.
A71: Acionamento | B71: Consultar / filtrar / selecionar; não enviar formulário de manutenção.
A72: Resultado / saída | B72: Campos recuperados: data; responsável; ação; detalhe. Sem escrita nem dado de negócio derivado.
A73: Evidência visual | B73: Capturas da aplicação nas páginas seguintes. Veja a legenda de cada estado e a origem registrada.
A75: CE11 — captura real 1/2
A76: Acionamento da consulta de auditoria pelo menu Histórico; escopo definido pela loja da sessão.
A77: Origem: http://localhost:8080/ | Capturada em: 2026-10-25T23:50:52.227404+00:00 | CE11-entrada.png
A131: CE11 — captura real 2/2
A132: Registros reais de auditoria consultável, armazenados pela aplicação.
A133: Origem: http://localhost:8080/historico | Capturada em: 2026-10-25T23:50:53.026254+00:00 | CE11-saida.png

Sheet CE12
A1: CE12 — Consultar ofertas externas
A2: Sistema e tipo | B2: Estoque Inteligente — CE
A3: Intenção / finalidade | B3: Consultar ofertas externas
A4: Fronteira e classificação | B4: Consulta externa: recupera dados; não mantém arquivos nem deriva informação de negócio.
A5: Rota / contexto | B5: /ofertas?gtin=…&fornecedor=…
A6: Permissões | B6: Permissão consultar; /ocupacao também exige relatorios e recurso occupancy. Sem acesso entre lojas.
A7: Evidência atual | B7: GET /ofertas; OfertaService.consultar; OfertaGateway; external/ofertas/Provedor.java
A8: Dados internos / regra | B8: X02: nove campos da oferta. Filtros exatos opcionais combinados por GTIN e código do fornecedor. Não mantém arquivos nem deriva dados.
A10: Item que cruza a fronteira | B10: Fluxo | C10: TD entrada | D10: TD saída exclusiva
A11: GTIN | B11: Entrada | C11: =IF(AND(A11<>"",B11<>"Saída",COUNTIF($A$11:A11,A11)=1),1,0) -> 1 | D11: =IF(AND(A11<>"",B11="Saída",COUNTIF($A$11:A11,A11)=1),1,0) -> 0
A12: código do fornecedor | B12: Entrada | C12: =IF(AND(A12<>"",B12<>"Saída",COUNTIF($A$11:A12,A12)=1),1,0) -> 1 | D12: =IF(AND(A12<>"",B12="Saída",COUNTIF($A$11:A12,A12)=1),1,0) -> 0
A13: acionamento | B13: Controle | C13: =IF(AND(A13<>"",B13<>"Saída",COUNTIF($A$11:A13,A13)=1),1,0) -> 1 | D13: =IF(AND(A13<>"",B13="Saída",COUNTIF($A$11:A13,A13)=1),1,0) -> 0
A14: mensagem de resultado | B14: Controle | C14: =IF(AND(A14<>"",B14<>"Saída",COUNTIF($A$11:A14,A14)=1),1,0) -> 1 | D14: =IF(AND(A14<>"",B14="Saída",COUNTIF($A$11:A14,A14)=1),1,0) -> 0
A15: GTIN | B15: Saída | C15: =IF(AND(A15<>"",B15<>"Saída",COUNTIF($A$11:A15,A15)=1),1,0) -> 0 | D15: =IF(AND(A15<>"",B15="Saída",COUNTIF($A$11:A15,A15)=1),1,0) -> 0
A16: código do fornecedor | B16: Saída | C16: =IF(AND(A16<>"",B16<>"Saída",COUNTIF($A$11:A16,A16)=1),1,0) -> 0 | D16: =IF(AND(A16<>"",B16="Saída",COUNTIF($A$11:A16,A16)=1),1,0) -> 0
A17: SKU externo | B17: Saída | C17: =IF(AND(A17<>"",B17<>"Saída",COUNTIF($A$11:A17,A17)=1),1,0) -> 0 | D17: =IF(AND(A17<>"",B17="Saída",COUNTIF($A$11:A17,A17)=1),1,0) -> 1
A18: descrição | B18: Saída | C18: =IF(AND(A18<>"",B18<>"Saída",COUNTIF($A$11:A18,A18)=1),1,0) -> 0 | D18: =IF(AND(A18<>"",B18="Saída",COUNTIF($A$11:A18,A18)=1),1,0) -> 1
A19: marca | B19: Saída | C19: =IF(AND(A19<>"",B19<>"Saída",COUNTIF($A$11:A19,A19)=1),1,0) -> 0 | D19: =IF(AND(A19<>"",B19="Saída",COUNTIF($A$11:A19,A19)=1),1,0) -> 1
A20: unidade | B20: Saída | C20: =IF(AND(A20<>"",B20<>"Saída",COUNTIF($A$11:A20,A20)=1),1,0) -> 0 | D20: =IF(AND(A20<>"",B20="Saída",COUNTIF($A$11:A20,A20)=1),1,0) -> 1
A21: preço cotado | B21: Saída | C21: =IF(AND(A21<>"",B21<>"Saída",COUNTIF($A$11:A21,A21)=1),1,0) -> 0 | D21: =IF(AND(A21<>"",B21="Saída",COUNTIF($A$11:A21,A21)=1),1,0) -> 1
A22: disponibilidade | B22: Saída | C22: =IF(AND(A22<>"",B22<>"Saída",COUNTIF($A$11:A22,A22)=1),1,0) -> 0 | D22: =IF(AND(A22<>"",B22="Saída",COUNTIF($A$11:A22,A22)=1),1,0) -> 1
A23: data de atualização | B23: Saída | C23: =IF(AND(A23<>"",B23<>"Saída",COUNTIF($A$11:A23,A23)=1),1,0) -> 0 | D23: =IF(AND(A23<>"",B23="Saída",COUNTIF($A$11:A23,A23)=1),1,0) -> 1
C24: =IF(AND(A24<>"",B24<>"Saída",COUNTIF($A$11:A24,A24)=1),1,0) -> 0 | D24: =IF(AND(A24<>"",B24="Saída",COUNTIF($A$11:A24,A24)=1),1,0) -> 0
C25: =IF(AND(A25<>"",B25<>"Saída",COUNTIF($A$11:A25,A25)=1),1,0) -> 0 | D25: =IF(AND(A25<>"",B25="Saída",COUNTIF($A$11:A25,A25)=1),1,0) -> 0
C26: =IF(AND(A26<>"",B26<>"Saída",COUNTIF($A$11:A26,A26)=1),1,0) -> 0 | D26: =IF(AND(A26<>"",B26="Saída",COUNTIF($A$11:A26,A26)=1),1,0) -> 0
C27: =IF(AND(A27<>"",B27<>"Saída",COUNTIF($A$11:A27,A27)=1),1,0) -> 0 | D27: =IF(AND(A27<>"",B27="Saída",COUNTIF($A$11:A27,A27)=1),1,0) -> 0
C28: =IF(AND(A28<>"",B28<>"Saída",COUNTIF($A$11:A28,A28)=1),1,0) -> 0 | D28: =IF(AND(A28<>"",B28="Saída",COUNTIF($A$11:A28,A28)=1),1,0) -> 0
C29: =IF(AND(A29<>"",B29<>"Saída",COUNTIF($A$11:A29,A29)=1),1,0) -> 0 | D29: =IF(AND(A29<>"",B29="Saída",COUNTIF($A$11:A29,A29)=1),1,0) -> 0
C30: =IF(AND(A30<>"",B30<>"Saída",COUNTIF($A$11:A30,A30)=1),1,0) -> 0 | D30: =IF(AND(A30<>"",B30="Saída",COUNTIF($A$11:A30,A30)=1),1,0) -> 0
C31: =IF(AND(A31<>"",B31<>"Saída",COUNTIF($A$11:A31,A31)=1),1,0) -> 0 | D31: =IF(AND(A31<>"",B31="Saída",COUNTIF($A$11:A31,A31)=1),1,0) -> 0
C32: =IF(AND(A32<>"",B32<>"Saída",COUNTIF($A$11:A32,A32)=1),1,0) -> 0 | D32: =IF(AND(A32<>"",B32="Saída",COUNTIF($A$11:A32,A32)=1),1,0) -> 0
C33: =IF(AND(A33<>"",B33<>"Saída",COUNTIF($A$11:A33,A33)=1),1,0) -> 0 | D33: =IF(AND(A33<>"",B33="Saída",COUNTIF($A$11:A33,A33)=1),1,0) -> 0
C34: =IF(AND(A34<>"",B34<>"Saída",COUNTIF($A$11:A34,A34)=1),1,0) -> 0 | D34: =IF(AND(A34<>"",B34="Saída",COUNTIF($A$11:A34,A34)=1),1,0) -> 0
C35: =IF(AND(A35<>"",B35<>"Saída",COUNTIF($A$11:A35,A35)=1),1,0) -> 0 | D35: =IF(AND(A35<>"",B35="Saída",COUNTIF($A$11:A35,A35)=1),1,0) -> 0
... C42: =IF(AND(A42<>"",B42<>"Saída",COUNTIF($A$11:A42,A42)=1),1,0) -> 0 | D42: =IF(AND(A42<>"",B42="Saída",COUNTIF($A$11:A42,A42)=1),1,0) -> 0
A44: Arquivos referenciados (cada grupo uma única vez)
A45: ALI / AIE | B45: Finalidade da referência | C45: AR entrada CE | D45: AR saída CE
A46: X02 | B46: Ofertas externas | C46: 1 | D46: 1
A57: Regra AR / RL | B57: X02 aplica GTIN/fornecedor e fornece os campos recuperados da oferta. Na função, cada arquivo conta uma vez na união; as avaliações de entrada/saída usam suas referências próprias.
A59: Contagem calculada — entradas editáveis acima
A60: TD total distinto | B60: =SUM(C11:D42) -> 11 | C60: AR distintos | D60: =COUNTA(A46:A56) -> 1
A61: TD entrada CE | B61: =SUM(C11:C42) -> 4 | C61: TD saída sem repetição | D61: =SUM(D11:D42) -> 7
A62: AR entrada CE | B62: =SUM(C46:C56) -> 1 | C62: AR saída CE | D62: =SUM(D46:D56) -> 1
A63: Índice entrada CE | B63: =INDEX(Matrizes!$B$5:$D$7,IF(B62<=1,1,IF(B62<=2,2,3)),IF(B61<=4,1,IF(B61<=15,2,3))) -> 1 | C63: Índice saída CE | D63: =INDEX(Matrizes!$B$5:$D$7,IF(D62<=1,1,IF(D62<=3,2,3)),IF(D61<=5,1,IF(D61<=19,2,3))) -> 1
A64: Índice adotado | B64: =MAX(B63,D63) -> 1 | C64: Complexidade | D64: =INDEX(Matrizes!$B$10:$D$10,1,B64) -> Simples
A65: Peso apropriado ao tipo | B65: =INDEX(Matrizes!$B$13:$D$17,MATCH("CE",Matrizes!$A$13:$A$17,0),B64) -> 3 | C65: PF desta função | D65: =B65 -> 3
A67: Justificativa da contagem | B67: Parte III, p. 7 e 10–13: retirar TD repetidos, classificar entrada e saída separadamente, selecionar MAX. AR de cada lado ficam editáveis em C/D46:56.
A69: Fluxo da função — leitura do protótipo real
A70: Entrada / contexto | B70: GTIN; código do fornecedor
A71: Acionamento | B71: Consultar / filtrar / selecionar; não enviar formulário de manutenção.
A72: Resultado / saída | B72: Campos recuperados: GTIN; código do fornecedor; SKU externo; descrição; marca; unidade; preço cotado; disponibilidade; data de atualização. Sem escrita nem dado de negócio derivado.
A73: Evidência visual | B73: Capturas da aplicação nas páginas seguintes. Veja a legenda de cada estado e a origem registrada.
A75: CE12 — captura real 1/2
A76: Captura real da aplicação atual; dados de demonstração.
A77: Origem: http://localhost:8080/ofertas | Capturada em: 2026-10-25T22:02:47.935Z | CE12-entrada.png
A131: CE12 — captura real 2/2
A132: Captura real da aplicação atual; dados de demonstração.
A133: Origem: http://localhost:8080/ofertas?fornecedor=F001 | Capturada em: 2026-10-25T22:02:48.056Z | CE12-saida.png

Sheet EE01
A1: EE01 — Incluir produto, inclusive grade e saldo inicial
A2: Sistema e tipo | B2: Estoque Inteligente — EE
A3: Intenção / finalidade | B3: Incluir produto, inclusive grade e saldo inicial
A4: Fronteira e classificação | B4: Entrada externa: mantém ALIs ou altera comportamento. Chamadas auxiliares não são novas funções.
A5: Rota / contexto | B5: /produtos; /excluir/produto/{id}
A6: Permissões | B6: Permissão cadastros para manutenção; consultar para leitura quando aplicável. Loja sempre validada.
A7: Evidência atual | B7: ProdutoService.salvar
A8: Dados internos / regra | B8: A01: nome, marca e categoria do modelo. A02: modelo, SKU, código de barras, cor, tamanho, unidade, preço, características e ativo. A03: posição e unidade, na entrada inicial. A04: produto, posição e quantidade inicial. A05: produto, posição, responsável, tipo, variação, saldos anterior/posterior, motivo e data, quando há saldo inicial. A09: loja, responsável, ação, detalhe e data (gerada). Identificações dos registros são geradas pelo banco; leituras/manutenções internas não são TD adicionais da interface.
A10: Item que cruza a fronteira | B10: Fluxo | C10: TD entrada | D10: TD saída exclusiva
A11: nome | B11: Entrada | C11: =IF(AND(A11<>"",B11<>"Saída",COUNTIF($A$11:A11,A11)=1),1,0) -> 1 | D11: =IF(AND(A11<>"",B11="Saída",COUNTIF($A$11:A11,A11)=1),1,0) -> 0
A12: marca | B12: Entrada | C12: =IF(AND(A12<>"",B12<>"Saída",COUNTIF($A$11:A12,A12)=1),1,0) -> 1 | D12: =IF(AND(A12<>"",B12="Saída",COUNTIF($A$11:A12,A12)=1),1,0) -> 0
A13: categoria | B13: Entrada | C13: =IF(AND(A13<>"",B13<>"Saída",COUNTIF($A$11:A13,A13)=1),1,0) -> 1 | D13: =IF(AND(A13<>"",B13="Saída",COUNTIF($A$11:A13,A13)=1),1,0) -> 0
A14: SKU | B14: Entrada | C14: =IF(AND(A14<>"",B14<>"Saída",COUNTIF($A$11:A14,A14)=1),1,0) -> 1 | D14: =IF(AND(A14<>"",B14="Saída",COUNTIF($A$11:A14,A14)=1),1,0) -> 0
A15: código de barras | B15: Entrada | C15: =IF(AND(A15<>"",B15<>"Saída",COUNTIF($A$11:A15,A15)=1),1,0) -> 1 | D15: =IF(AND(A15<>"",B15="Saída",COUNTIF($A$11:A15,A15)=1),1,0) -> 0
A16: cor | B16: Entrada | C16: =IF(AND(A16<>"",B16<>"Saída",COUNTIF($A$11:A16,A16)=1),1,0) -> 1 | D16: =IF(AND(A16<>"",B16="Saída",COUNTIF($A$11:A16,A16)=1),1,0) -> 0
A17: tamanho | B17: Entrada | C17: =IF(AND(A17<>"",B17<>"Saída",COUNTIF($A$11:A17,A17)=1),1,0) -> 1 | D17: =IF(AND(A17<>"",B17="Saída",COUNTIF($A$11:A17,A17)=1),1,0) -> 0
A18: unidade | B18: Entrada | C18: =IF(AND(A18<>"",B18<>"Saída",COUNTIF($A$11:A18,A18)=1),1,0) -> 1 | D18: =IF(AND(A18<>"",B18="Saída",COUNTIF($A$11:A18,A18)=1),1,0) -> 0
A19: preço | B19: Entrada | C19: =IF(AND(A19<>"",B19<>"Saída",COUNTIF($A$11:A19,A19)=1),1,0) -> 1 | D19: =IF(AND(A19<>"",B19="Saída",COUNTIF($A$11:A19,A19)=1),1,0) -> 0
A20: características | B20: Entrada | C20: =IF(AND(A20<>"",B20<>"Saída",COUNTIF($A$11:A20,A20)=1),1,0) -> 1 | D20: =IF(AND(A20<>"",B20="Saída",COUNTIF($A$11:A20,A20)=1),1,0) -> 0
A21: estrutura | B21: Entrada | C21: =IF(AND(A21<>"",B21<>"Saída",COUNTIF($A$11:A21,A21)=1),1,0) -> 1 | D21: =IF(AND(A21<>"",B21="Saída",COUNTIF($A$11:A21,A21)=1),1,0) -> 0
A22: tamanhos da grade | B22: Entrada | C22: =IF(AND(A22<>"",B22<>"Saída",COUNTIF($A$11:A22,A22)=1),1,0) -> 1 | D22: =IF(AND(A22<>"",B22="Saída",COUNTIF($A$11:A22,A22)=1),1,0) -> 0
... A26: mensagem de resultado | B26: Saída | C26: =IF(AND(A26<>"",B26<>"Saída",COUNTIF($A$11:A26,A26)=1),1,0) -> 0 | D26: =IF(AND(A26<>"",B26="Saída",COUNTIF($A$11:A26,A26)=1),1,0) -> 1
C27: =IF(AND(A27<>"",B27<>"Saída",COUNTIF($A$11:A27,A27)=1),1,0) -> 0 | D27: =IF(AND(A27<>"",B27="Saída",COUNTIF($A$11:A27,A27)=1),1,0) -> 0
C28: =IF(AND(A28<>"",B28<>"Saída",COUNTIF($A$11:A28,A28)=1),1,0) -> 0 | D28: =IF(AND(A28<>"",B28="Saída",COUNTIF($A$11:A28,A28)=1),1,0) -> 0
C29: =IF(AND(A29<>"",B29<>"Saída",COUNTIF($A$11:A29,A29)=1),1,0) -> 0 | D29: =IF(AND(A29<>"",B29="Saída",COUNTIF($A$11:A29,A29)=1),1,0) -> 0
C30: =IF(AND(A30<>"",B30<>"Saída",COUNTIF($A$11:A30,A30)=1),1,0) -> 0 | D30: =IF(AND(A30<>"",B30="Saída",COUNTIF($A$11:A30,A30)=1),1,0) -> 0
C31: =IF(AND(A31<>"",B31<>"Saída",COUNTIF($A$11:A31,A31)=1),1,0) -> 0 | D31: =IF(AND(A31<>"",B31="Saída",COUNTIF($A$11:A31,A31)=1),1,0) -> 0
C32: =IF(AND(A32<>"",B32<>"Saída",COUNTIF($A$11:A32,A32)=1),1,0) -> 0 | D32: =IF(AND(A32<>"",B32="Saída",COUNTIF($A$11:A32,A32)=1),1,0) -> 0
C33: =IF(AND(A33<>"",B33<>"Saída",COUNTIF($A$11:A33,A33)=1),1,0) -> 0 | D33: =IF(AND(A33<>"",B33="Saída",COUNTIF($A$11:A33,A33)=1),1,0) -> 0
C34: =IF(AND(A34<>"",B34<>"Saída",COUNTIF($A$11:A34,A34)=1),1,0) -> 0 | D34: =IF(AND(A34<>"",B34="Saída",COUNTIF($A$11:A34,A34)=1),1,0) -> 0
C35: =IF(AND(A35<>"",B35<>"Saída",COUNTIF($A$11:A35,A35)=1),1,0) -> 0 | D35: =IF(AND(A35<>"",B35="Saída",COUNTIF($A$11:A35,A35)=1),1,0) -> 0
C36: =IF(AND(A36<>"",B36<>"Saída",COUNTIF($A$11:A36,A36)=1),1,0) -> 0 | D36: =IF(AND(A36<>"",B36="Saída",COUNTIF($A$11:A36,A36)=1),1,0) -> 0
C37: =IF(AND(A37<>"",B37<>"Saída",COUNTIF($A$11:A37,A37)=1),1,0) -> 0 | D37: =IF(AND(A37<>"",B37="Saída",COUNTIF($A$11:A37,A37)=1),1,0) -> 0
C38: =IF(AND(A38<>"",B38<>"Saída",COUNTIF($A$11:A38,A38)=1),1,0) -> 0 | D38: =IF(AND(A38<>"",B38="Saída",COUNTIF($A$11:A38,A38)=1),1,0) -> 0
... C42: =IF(AND(A42<>"",B42<>"Saída",COUNTIF($A$11:A42,A42)=1),1,0) -> 0 | D42: =IF(AND(A42<>"",B42="Saída",COUNTIF($A$11:A42,A42)=1),1,0) -> 0
A44: Arquivos referenciados (cada grupo uma única vez)
A45: ALI / AIE | B45: Finalidade da referência | C45: AR entrada CE | D45: AR saída CE
A46: A01 | B46: Modelos de produto | C46: 1 | D46: 1
A47: A02 | B47: Produtos | C47: 1 | D47: 1
A48: A03 | B48: Posições | C48: 1 | D48: 1
A49: A04 | B49: Estoque por posição / vínculos | C49: 1 | D49: 1
A50: A05 | B50: Movimentações | C50: 1 | D50: 1
A51: A09 | B51: Auditoria consultável | C51: 1 | D51: 1
A57: Regra AR / RL | B57: União dos ALIs lidos/mantidos. Arquivo lido e mantido conta uma vez; autorização técnica transversal não multiplica AR.
A59: Contagem calculada — entradas editáveis acima
A60: TD total distinto | B60: =SUM(C11:D42) -> 16 | C60: AR distintos | D60: =COUNTA(A46:A56) -> 6
A61: TD entrada CE | B61: =SUM(C11:C42) -> 15 | C61: TD saída sem repetição | D61: =SUM(D11:D42) -> 1
A62: AR entrada CE | B62: =SUM(C46:C56) -> 6 | C62: AR saída CE | D62: =SUM(D46:D56) -> 6
A63: Índice entrada CE | B63: =INDEX(Matrizes!$B$5:$D$7,IF(B62<=1,1,IF(B62<=2,2,3)),IF(B61<=4,1,IF(B61<=15,2,3))) -> 3 | C63: Índice saída CE | D63: =INDEX(Matrizes!$B$5:$D$7,IF(D62<=1,1,IF(D62<=3,2,3)),IF(D61<=5,1,IF(D61<=19,2,3))) -> 2
A64: Índice adotado | B64: =INDEX(Matrizes!$B$5:$D$7,IF(D60<=1,1,IF(D60<=2,2,3)),IF(B60<=4,1,IF(B60<=15,2,3))) -> 3 | C64: Complexidade | D64: =INDEX(Matrizes!$B$10:$D$10,1,B64) -> Complexa
A65: Peso apropriado ao tipo | B65: =INDEX(Matrizes!$B$13:$D$17,MATCH("EE",Matrizes!$A$13:$A$17,0),B64) -> 6 | C65: PF desta função | D65: =B65 -> 6
A67: Justificativa da contagem | B67: TD usa somente itens que atravessam a fronteira. Uma mensagem de resultado e um conjunto de comandos. Dados internos não somam TD.
A69: Fluxo da função — leitura do protótipo real
A70: Entrada / contexto | B70: nome; marca; categoria; SKU; código de barras; cor; tamanho; unidade; preço; características; estrutura; tamanhos da grade; posição inicial; quantidades iniciais
A71: Acionamento | B71: Incluir produto, inclusive grade e saldo inicial. Comando real: /produtos; /excluir/produto/{id}
A72: Resultado / saída | B72: Produto salvo. Uma grade pode criar vários produtos e saldos; tipos de dados contam uma vez.
A73: Evidência visual | B73: Capturas da aplicação nas páginas seguintes. Veja a legenda de cada estado e a origem registrada.
A75: EE01 — captura real 1/2
A76: Formulário real antes da requisição autenticada; registros próprios da loja APF de demonstração.
A77: Origem: http://localhost:8080/produtos | Capturada em: 2026-10-25T22:10:56.689Z | EE01-entrada.png
A131: EE01 — captura real 2/2
A132: Operação realmente enviada e confirmada; dados da loja APF de demonstração.
A133: Origem: http://localhost:8080/produtos | Capturada em: 2026-10-25T22:10:56.854Z | EE01-saida.png

Sheet EE02
A1: EE02 — Alterar produto
A2: Sistema e tipo | B2: Estoque Inteligente — EE
A3: Intenção / finalidade | B3: Alterar produto
A4: Fronteira e classificação | B4: Entrada externa: mantém ALIs ou altera comportamento. Chamadas auxiliares não são novas funções.
A5: Rota / contexto | B5: /produtos; /excluir/produto/{id}
A6: Permissões | B6: Permissão cadastros para manutenção; consultar para leitura quando aplicável. Loja sempre validada.
A7: Evidência atual | B7: ProdutoService.salvar
A8: Dados internos / regra | B8: A01: modelo; A02: unidade anterior; A04: vínculos para validar mudança de unidade; A09: registro da alteração.
A10: Item que cruza a fronteira | B10: Fluxo | C10: TD entrada | D10: TD saída exclusiva
A11: produto | B11: Entrada | C11: =IF(AND(A11<>"",B11<>"Saída",COUNTIF($A$11:A11,A11)=1),1,0) -> 1 | D11: =IF(AND(A11<>"",B11="Saída",COUNTIF($A$11:A11,A11)=1),1,0) -> 0
A12: nome | B12: Entrada | C12: =IF(AND(A12<>"",B12<>"Saída",COUNTIF($A$11:A12,A12)=1),1,0) -> 1 | D12: =IF(AND(A12<>"",B12="Saída",COUNTIF($A$11:A12,A12)=1),1,0) -> 0
A13: marca | B13: Entrada | C13: =IF(AND(A13<>"",B13<>"Saída",COUNTIF($A$11:A13,A13)=1),1,0) -> 1 | D13: =IF(AND(A13<>"",B13="Saída",COUNTIF($A$11:A13,A13)=1),1,0) -> 0
A14: categoria | B14: Entrada | C14: =IF(AND(A14<>"",B14<>"Saída",COUNTIF($A$11:A14,A14)=1),1,0) -> 1 | D14: =IF(AND(A14<>"",B14="Saída",COUNTIF($A$11:A14,A14)=1),1,0) -> 0
A15: SKU | B15: Entrada | C15: =IF(AND(A15<>"",B15<>"Saída",COUNTIF($A$11:A15,A15)=1),1,0) -> 1 | D15: =IF(AND(A15<>"",B15="Saída",COUNTIF($A$11:A15,A15)=1),1,0) -> 0
A16: código de barras | B16: Entrada | C16: =IF(AND(A16<>"",B16<>"Saída",COUNTIF($A$11:A16,A16)=1),1,0) -> 1 | D16: =IF(AND(A16<>"",B16="Saída",COUNTIF($A$11:A16,A16)=1),1,0) -> 0
A17: cor | B17: Entrada | C17: =IF(AND(A17<>"",B17<>"Saída",COUNTIF($A$11:A17,A17)=1),1,0) -> 1 | D17: =IF(AND(A17<>"",B17="Saída",COUNTIF($A$11:A17,A17)=1),1,0) -> 0
A18: tamanho | B18: Entrada | C18: =IF(AND(A18<>"",B18<>"Saída",COUNTIF($A$11:A18,A18)=1),1,0) -> 1 | D18: =IF(AND(A18<>"",B18="Saída",COUNTIF($A$11:A18,A18)=1),1,0) -> 0
A19: unidade | B19: Entrada | C19: =IF(AND(A19<>"",B19<>"Saída",COUNTIF($A$11:A19,A19)=1),1,0) -> 1 | D19: =IF(AND(A19<>"",B19="Saída",COUNTIF($A$11:A19,A19)=1),1,0) -> 0
A20: preço | B20: Entrada | C20: =IF(AND(A20<>"",B20<>"Saída",COUNTIF($A$11:A20,A20)=1),1,0) -> 1 | D20: =IF(AND(A20<>"",B20="Saída",COUNTIF($A$11:A20,A20)=1),1,0) -> 0
A21: características | B21: Entrada | C21: =IF(AND(A21<>"",B21<>"Saída",COUNTIF($A$11:A21,A21)=1),1,0) -> 1 | D21: =IF(AND(A21<>"",B21="Saída",COUNTIF($A$11:A21,A21)=1),1,0) -> 0
A22: acionamento | B22: Controle | C22: =IF(AND(A22<>"",B22<>"Saída",COUNTIF($A$11:A22,A22)=1),1,0) -> 1 | D22: =IF(AND(A22<>"",B22="Saída",COUNTIF($A$11:A22,A22)=1),1,0) -> 0
A23: mensagem de resultado | B23: Saída | C23: =IF(AND(A23<>"",B23<>"Saída",COUNTIF($A$11:A23,A23)=1),1,0) -> 0 | D23: =IF(AND(A23<>"",B23="Saída",COUNTIF($A$11:A23,A23)=1),1,0) -> 1
C24: =IF(AND(A24<>"",B24<>"Saída",COUNTIF($A$11:A24,A24)=1),1,0) -> 0 | D24: =IF(AND(A24<>"",B24="Saída",COUNTIF($A$11:A24,A24)=1),1,0) -> 0
C25: =IF(AND(A25<>"",B25<>"Saída",COUNTIF($A$11:A25,A25)=1),1,0) -> 0 | D25: =IF(AND(A25<>"",B25="Saída",COUNTIF($A$11:A25,A25)=1),1,0) -> 0
C26: =IF(AND(A26<>"",B26<>"Saída",COUNTIF($A$11:A26,A26)=1),1,0) -> 0 | D26: =IF(AND(A26<>"",B26="Saída",COUNTIF($A$11:A26,A26)=1),1,0) -> 0
C27: =IF(AND(A27<>"",B27<>"Saída",COUNTIF($A$11:A27,A27)=1),1,0) -> 0 | D27: =IF(AND(A27<>"",B27="Saída",COUNTIF($A$11:A27,A27)=1),1,0) -> 0
C28: =IF(AND(A28<>"",B28<>"Saída",COUNTIF($A$11:A28,A28)=1),1,0) -> 0 | D28: =IF(AND(A28<>"",B28="Saída",COUNTIF($A$11:A28,A28)=1),1,0) -> 0
C29: =IF(AND(A29<>"",B29<>"Saída",COUNTIF($A$11:A29,A29)=1),1,0) -> 0 | D29: =IF(AND(A29<>"",B29="Saída",COUNTIF($A$11:A29,A29)=1),1,0) -> 0
C30: =IF(AND(A30<>"",B30<>"Saída",COUNTIF($A$11:A30,A30)=1),1,0) -> 0 | D30: =IF(AND(A30<>"",B30="Saída",COUNTIF($A$11:A30,A30)=1),1,0) -> 0
C31: =IF(AND(A31<>"",B31<>"Saída",COUNTIF($A$11:A31,A31)=1),1,0) -> 0 | D31: =IF(AND(A31<>"",B31="Saída",COUNTIF($A$11:A31,A31)=1),1,0) -> 0
C32: =IF(AND(A32<>"",B32<>"Saída",COUNTIF($A$11:A32,A32)=1),1,0) -> 0 | D32: =IF(AND(A32<>"",B32="Saída",COUNTIF($A$11:A32,A32)=1),1,0) -> 0
C33: =IF(AND(A33<>"",B33<>"Saída",COUNTIF($A$11:A33,A33)=1),1,0) -> 0 | D33: =IF(AND(A33<>"",B33="Saída",COUNTIF($A$11:A33,A33)=1),1,0) -> 0
C34: =IF(AND(A34<>"",B34<>"Saída",COUNTIF($A$11:A34,A34)=1),1,0) -> 0 | D34: =IF(AND(A34<>"",B34="Saída",COUNTIF($A$11:A34,A34)=1),1,0) -> 0
C35: =IF(AND(A35<>"",B35<>"Saída",COUNTIF($A$11:A35,A35)=1),1,0) -> 0 | D35: =IF(AND(A35<>"",B35="Saída",COUNTIF($A$11:A35,A35)=1),1,0) -> 0
... C42: =IF(AND(A42<>"",B42<>"Saída",COUNTIF($A$11:A42,A42)=1),1,0) -> 0 | D42: =IF(AND(A42<>"",B42="Saída",COUNTIF($A$11:A42,A42)=1),1,0) -> 0
A44: Arquivos referenciados (cada grupo uma única vez)
A45: ALI / AIE | B45: Finalidade da referência | C45: AR entrada CE | D45: AR saída CE
A46: A01 | B46: Modelos de produto | C46: 1 | D46: 1
A47: A02 | B47: Produtos | C47: 1 | D47: 1
A48: A04 | B48: Estoque por posição / vínculos | C48: 1 | D48: 1
A49: A09 | B49: Auditoria consultável | C49: 1 | D49: 1
A57: Regra AR / RL | B57: União dos ALIs lidos/mantidos. Arquivo lido e mantido conta uma vez; autorização técnica transversal não multiplica AR.
A59: Contagem calculada — entradas editáveis acima
A60: TD total distinto | B60: =SUM(C11:D42) -> 13 | C60: AR distintos | D60: =COUNTA(A46:A56) -> 4
A61: TD entrada CE | B61: =SUM(C11:C42) -> 12 | C61: TD saída sem repetição | D61: =SUM(D11:D42) -> 1
A62: AR entrada CE | B62: =SUM(C46:C56) -> 4 | C62: AR saída CE | D62: =SUM(D46:D56) -> 4
A63: Índice entrada CE | B63: =INDEX(Matrizes!$B$5:$D$7,IF(B62<=1,1,IF(B62<=2,2,3)),IF(B61<=4,1,IF(B61<=15,2,3))) -> 3 | C63: Índice saída CE | D63: =INDEX(Matrizes!$B$5:$D$7,IF(D62<=1,1,IF(D62<=3,2,3)),IF(D61<=5,1,IF(D61<=19,2,3))) -> 2
A64: Índice adotado | B64: =INDEX(Matrizes!$B$5:$D$7,IF(D60<=1,1,IF(D60<=2,2,3)),IF(B60<=4,1,IF(B60<=15,2,3))) -> 3 | C64: Complexidade | D64: =INDEX(Matrizes!$B$10:$D$10,1,B64) -> Complexa
A65: Peso apropriado ao tipo | B65: =INDEX(Matrizes!$B$13:$D$17,MATCH("EE",Matrizes!$A$13:$A$17,0),B64) -> 6 | C65: PF desta função | D65: =B65 -> 6
A67: Justificativa da contagem | B67: TD usa somente itens que atravessam a fronteira. Uma mensagem de resultado e um conjunto de comandos. Dados internos não somam TD.
A69: Fluxo da função — leitura do protótipo real
A70: Entrada / contexto | B70: produto; nome; marca; categoria; SKU; código de barras; cor; tamanho; unidade; preço; características
A71: Acionamento | B71: Alterar produto. Comando real: /produtos; /excluir/produto/{id}
A72: Resultado / saída | B72: Produto salvo; nova associação de modelo e atributos persistidos.
A73: Evidência visual | B73: Capturas da aplicação nas páginas seguintes. Veja a legenda de cada estado e a origem registrada.
A75: EE02 — captura real 1/2
A76: Formulário real antes da requisição autenticada; registros próprios da loja APF de demonstração.
A77: Origem: http://localhost:8080/produtos?id=18&q=&page=0 | Capturada em: 2026-10-25T22:10:57.142Z | EE02-entrada.png
A131: EE02 — captura real 2/2
A132: Operação realmente enviada e confirmada; dados da loja APF de demonstração.
A133: Origem: http://localhost:8080/produtos | Capturada em: 2026-10-25T22:10:57.320Z | EE02-saida.png

Sheet EE03
A1: EE03 — Excluir produto logicamente
A2: Sistema e tipo | B2: Estoque Inteligente — EE
A3: Intenção / finalidade | B3: Excluir produto logicamente
A4: Fronteira e classificação | B4: Entrada externa: mantém ALIs ou altera comportamento. Chamadas auxiliares não são novas funções.
A5: Rota / contexto | B5: /produtos; /excluir/produto/{id}
A6: Permissões | B6: Permissão cadastros para manutenção; consultar para leitura quando aplicável. Loja sempre validada.
A7: Evidência atual | B7: ProdutoService.excluir
A8: Dados internos / regra | B8: A02: ativo; A04: quantidade e vínculos removidos se vazios; A09: registro da exclusão.
A10: Item que cruza a fronteira | B10: Fluxo | C10: TD entrada | D10: TD saída exclusiva
A11: produto | B11: Entrada | C11: =IF(AND(A11<>"",B11<>"Saída",COUNTIF($A$11:A11,A11)=1),1,0) -> 1 | D11: =IF(AND(A11<>"",B11="Saída",COUNTIF($A$11:A11,A11)=1),1,0) -> 0
A12: acionamento | B12: Controle | C12: =IF(AND(A12<>"",B12<>"Saída",COUNTIF($A$11:A12,A12)=1),1,0) -> 1 | D12: =IF(AND(A12<>"",B12="Saída",COUNTIF($A$11:A12,A12)=1),1,0) -> 0
A13: mensagem de resultado | B13: Saída | C13: =IF(AND(A13<>"",B13<>"Saída",COUNTIF($A$11:A13,A13)=1),1,0) -> 0 | D13: =IF(AND(A13<>"",B13="Saída",COUNTIF($A$11:A13,A13)=1),1,0) -> 1
C14: =IF(AND(A14<>"",B14<>"Saída",COUNTIF($A$11:A14,A14)=1),1,0) -> 0 | D14: =IF(AND(A14<>"",B14="Saída",COUNTIF($A$11:A14,A14)=1),1,0) -> 0
C15: =IF(AND(A15<>"",B15<>"Saída",COUNTIF($A$11:A15,A15)=1),1,0) -> 0 | D15: =IF(AND(A15<>"",B15="Saída",COUNTIF($A$11:A15,A15)=1),1,0) -> 0
C16: =IF(AND(A16<>"",B16<>"Saída",COUNTIF($A$11:A16,A16)=1),1,0) -> 0 | D16: =IF(AND(A16<>"",B16="Saída",COUNTIF($A$11:A16,A16)=1),1,0) -> 0
C17: =IF(AND(A17<>"",B17<>"Saída",COUNTIF($A$11:A17,A17)=1),1,0) -> 0 | D17: =IF(AND(A17<>"",B17="Saída",COUNTIF($A$11:A17,A17)=1),1,0) -> 0
C18: =IF(AND(A18<>"",B18<>"Saída",COUNTIF($A$11:A18,A18)=1),1,0) -> 0 | D18: =IF(AND(A18<>"",B18="Saída",COUNTIF($A$11:A18,A18)=1),1,0) -> 0
C19: =IF(AND(A19<>"",B19<>"Saída",COUNTIF($A$11:A19,A19)=1),1,0) -> 0 | D19: =IF(AND(A19<>"",B19="Saída",COUNTIF($A$11:A19,A19)=1),1,0) -> 0
C20: =IF(AND(A20<>"",B20<>"Saída",COUNTIF($A$11:A20,A20)=1),1,0) -> 0 | D20: =IF(AND(A20<>"",B20="Saída",COUNTIF($A$11:A20,A20)=1),1,0) -> 0
C21: =IF(AND(A21<>"",B21<>"Saída",COUNTIF($A$11:A21,A21)=1),1,0) -> 0 | D21: =IF(AND(A21<>"",B21="Saída",COUNTIF($A$11:A21,A21)=1),1,0) -> 0
C22: =IF(AND(A22<>"",B22<>"Saída",COUNTIF($A$11:A22,A22)=1),1,0) -> 0 | D22: =IF(AND(A22<>"",B22="Saída",COUNTIF($A$11:A22,A22)=1),1,0) -> 0
C23: =IF(AND(A23<>"",B23<>"Saída",COUNTIF($A$11:A23,A23)=1),1,0) -> 0 | D23: =IF(AND(A23<>"",B23="Saída",COUNTIF($A$11:A23,A23)=1),1,0) -> 0
C24: =IF(AND(A24<>"",B24<>"Saída",COUNTIF($A$11:A24,A24)=1),1,0) -> 0 | D24: =IF(AND(A24<>"",B24="Saída",COUNTIF($A$11:A24,A24)=1),1,0) -> 0
C25: =IF(AND(A25<>"",B25<>"Saída",COUNTIF($A$11:A25,A25)=1),1,0) -> 0 | D25: =IF(AND(A25<>"",B25="Saída",COUNTIF($A$11:A25,A25)=1),1,0) -> 0
... C42: =IF(AND(A42<>"",B42<>"Saída",COUNTIF($A$11:A42,A42)=1),1,0) -> 0 | D42: =IF(AND(A42<>"",B42="Saída",COUNTIF($A$11:A42,A42)=1),1,0) -> 0
A44: Arquivos referenciados (cada grupo uma única vez)
A45: ALI / AIE | B45: Finalidade da referência | C45: AR entrada CE | D45: AR saída CE
A46: A02 | B46: Produtos | C46: 1 | D46: 1
A47: A04 | B47: Estoque por posição / vínculos | C47: 1 | D47: 1
A48: A09 | B48: Auditoria consultável | C48: 1 | D48: 1
A57: Regra AR / RL | B57: União dos ALIs lidos/mantidos. Arquivo lido e mantido conta uma vez; autorização técnica transversal não multiplica AR.
A59: Contagem calculada — entradas editáveis acima
A60: TD total distinto | B60: =SUM(C11:D42) -> 3 | C60: AR distintos | D60: =COUNTA(A46:A56) -> 3
A61: TD entrada CE | B61: =SUM(C11:C42) -> 2 | C61: TD saída sem repetição | D61: =SUM(D11:D42) -> 1
A62: AR entrada CE | B62: =SUM(C46:C56) -> 3 | C62: AR saída CE | D62: =SUM(D46:D56) -> 3
A63: Índice entrada CE | B63: =INDEX(Matrizes!$B$5:$D$7,IF(B62<=1,1,IF(B62<=2,2,3)),IF(B61<=4,1,IF(B61<=15,2,3))) -> 2 | C63: Índice saída CE | D63: =INDEX(Matrizes!$B$5:$D$7,IF(D62<=1,1,IF(D62<=3,2,3)),IF(D61<=5,1,IF(D61<=19,2,3))) -> 1
A64: Índice adotado | B64: =INDEX(Matrizes!$B$5:$D$7,IF(D60<=1,1,IF(D60<=2,2,3)),IF(B60<=4,1,IF(B60<=15,2,3))) -> 2 | C64: Complexidade | D64: =INDEX(Matrizes!$B$10:$D$10,1,B64) -> Moderada
A65: Peso apropriado ao tipo | B65: =INDEX(Matrizes!$B$13:$D$17,MATCH("EE",Matrizes!$A$13:$A$17,0),B64) -> 4 | C65: PF desta função | D65: =B65 -> 4
A67: Justificativa da contagem | B67: TD usa somente itens que atravessam a fronteira. Uma mensagem de resultado e um conjunto de comandos. Dados internos não somam TD.
A69: Fluxo da função — leitura do protótipo real
A70: Entrada / contexto | B70: produto
A71: Acionamento | B71: Excluir produto logicamente. Comando real: /produtos; /excluir/produto/{id}
A72: Resultado / saída | B72: Produto desativado; vínculos vazios removidos; histórico preservado.
A73: Evidência visual | B73: Capturas da aplicação nas páginas seguintes. Veja a legenda de cada estado e a origem registrada.
A75: EE03 — captura real 1/2
A76: Formulário real antes da requisição autenticada; registros próprios da loja APF de demonstração.
A77: Origem: http://localhost:8080/produtos?id=18&q=&page=0 | Capturada em: 2026-10-25T22:12:59.225Z | EE03-entrada.png
A131: EE03 — captura real 2/2
A132: Operação realmente enviada e confirmada; dados da loja APF de demonstração.
A133: Origem: http://localhost:8080/produtos | Capturada em: 2026-10-25T22:12:59.404Z | EE03-saida.png

Sheet EE04
A1: EE04 — Incluir modelo
A2: Sistema e tipo | B2: Estoque Inteligente — EE
A3: Intenção / finalidade | B3: Incluir modelo
A4: Fronteira e classificação | B4: Entrada externa: mantém ALIs ou altera comportamento. Chamadas auxiliares não são novas funções.
A5: Rota / contexto | B5: /modelos; /excluir/modelo/{id}
A6: Permissões | B6: Permissão cadastros para manutenção; consultar para leitura quando aplicável. Loja sempre validada.
A7: Evidência atual | B7: ModeloProdutoService.salvar
A8: Dados internos / regra | B8: A01: loja, nome, marca e categoria; identificação do modelo gerada no cadastro. A09: loja, responsável, ação modelo.salvar, detalhe com a identificação do modelo e data gerada. Esses dados de auditoria são mantidos internamente e não são campos extras recebidos pela interface.
A10: Item que cruza a fronteira | B10: Fluxo | C10: TD entrada | D10: TD saída exclusiva
A11: nome | B11: Entrada | C11: =IF(AND(A11<>"",B11<>"Saída",COUNTIF($A$11:A11,A11)=1),1,0) -> 1 | D11: =IF(AND(A11<>"",B11="Saída",COUNTIF($A$11:A11,A11)=1),1,0) -> 0
A12: marca | B12: Entrada | C12: =IF(AND(A12<>"",B12<>"Saída",COUNTIF($A$11:A12,A12)=1),1,0) -> 1 | D12: =IF(AND(A12<>"",B12="Saída",COUNTIF($A$11:A12,A12)=1),1,0) -> 0
A13: categoria | B13: Entrada | C13: =IF(AND(A13<>"",B13<>"Saída",COUNTIF($A$11:A13,A13)=1),1,0) -> 1 | D13: =IF(AND(A13<>"",B13="Saída",COUNTIF($A$11:A13,A13)=1),1,0) -> 0
A14: acionamento | B14: Controle | C14: =IF(AND(A14<>"",B14<>"Saída",COUNTIF($A$11:A14,A14)=1),1,0) -> 1 | D14: =IF(AND(A14<>"",B14="Saída",COUNTIF($A$11:A14,A14)=1),1,0) -> 0
A15: mensagem de resultado | B15: Saída | C15: =IF(AND(A15<>"",B15<>"Saída",COUNTIF($A$11:A15,A15)=1),1,0) -> 0 | D15: =IF(AND(A15<>"",B15="Saída",COUNTIF($A$11:A15,A15)=1),1,0) -> 1
C16: =IF(AND(A16<>"",B16<>"Saída",COUNTIF($A$11:A16,A16)=1),1,0) -> 0 | D16: =IF(AND(A16<>"",B16="Saída",COUNTIF($A$11:A16,A16)=1),1,0) -> 0
C17: =IF(AND(A17<>"",B17<>"Saída",COUNTIF($A$11:A17,A17)=1),1,0) -> 0 | D17: =IF(AND(A17<>"",B17="Saída",COUNTIF($A$11:A17,A17)=1),1,0) -> 0
C18: =IF(AND(A18<>"",B18<>"Saída",COUNTIF($A$11:A18,A18)=1),1,0) -> 0 | D18: =IF(AND(A18<>"",B18="Saída",COUNTIF($A$11:A18,A18)=1),1,0) -> 0
C19: =IF(AND(A19<>"",B19<>"Saída",COUNTIF($A$11:A19,A19)=1),1,0) -> 0 | D19: =IF(AND(A19<>"",B19="Saída",COUNTIF($A$11:A19,A19)=1),1,0) -> 0
C20: =IF(AND(A20<>"",B20<>"Saída",COUNTIF($A$11:A20,A20)=1),1,0) -> 0 | D20: =IF(AND(A20<>"",B20="Saída",COUNTIF($A$11:A20,A20)=1),1,0) -> 0
C21: =IF(AND(A21<>"",B21<>"Saída",COUNTIF($A$11:A21,A21)=1),1,0) -> 0 | D21: =IF(AND(A21<>"",B21="Saída",COUNTIF($A$11:A21,A21)=1),1,0) -> 0
C22: =IF(AND(A22<>"",B22<>"Saída",COUNTIF($A$11:A22,A22)=1),1,0) -> 0 | D22: =IF(AND(A22<>"",B22="Saída",COUNTIF($A$11:A22,A22)=1),1,0) -> 0
C23: =IF(AND(A23<>"",B23<>"Saída",COUNTIF($A$11:A23,A23)=1),1,0) -> 0 | D23: =IF(AND(A23<>"",B23="Saída",COUNTIF($A$11:A23,A23)=1),1,0) -> 0
C24: =IF(AND(A24<>"",B24<>"Saída",COUNTIF($A$11:A24,A24)=1),1,0) -> 0 | D24: =IF(AND(A24<>"",B24="Saída",COUNTIF($A$11:A24,A24)=1),1,0) -> 0
C25: =IF(AND(A25<>"",B25<>"Saída",COUNTIF($A$11:A25,A25)=1),1,0) -> 0 | D25: =IF(AND(A25<>"",B25="Saída",COUNTIF($A$11:A25,A25)=1),1,0) -> 0
C26: =IF(AND(A26<>"",B26<>"Saída",COUNTIF($A$11:A26,A26)=1),1,0) -> 0 | D26: =IF(AND(A26<>"",B26="Saída",COUNTIF($A$11:A26,A26)=1),1,0) -> 0
C27: =IF(AND(A27<>"",B27<>"Saída",COUNTIF($A$11:A27,A27)=1),1,0) -> 0 | D27: =IF(AND(A27<>"",B27="Saída",COUNTIF($A$11:A27,A27)=1),1,0) -> 0
... C42: =IF(AND(A42<>"",B42<>"Saída",COUNTIF($A$11:A42,A42)=1),1,0) -> 0 | D42: =IF(AND(A42<>"",B42="Saída",COUNTIF($A$11:A42,A42)=1),1,0) -> 0
A44: Arquivos referenciados (cada grupo uma única vez)
A45: ALI / AIE | B45: Finalidade da referência | C45: AR entrada CE | D45: AR saída CE
A46: A01 | B46: Modelos de produto | C46: 1 | D46: 1
A47: A09 | B47: Auditoria consultável | C47: 1 | D47: 1
A57: Regra AR / RL | B57: União dos ALIs lidos/mantidos. Arquivo lido e mantido conta uma vez; autorização técnica transversal não multiplica AR.
A59: Contagem calculada — entradas editáveis acima
A60: TD total distinto | B60: =SUM(C11:D42) -> 5 | C60: AR distintos | D60: =COUNTA(A46:A56) -> 2
A61: TD entrada CE | B61: =SUM(C11:C42) -> 4 | C61: TD saída sem repetição | D61: =SUM(D11:D42) -> 1
A62: AR entrada CE | B62: =SUM(C46:C56) -> 2 | C62: AR saída CE | D62: =SUM(D46:D56) -> 2
A63: Índice entrada CE | B63: =INDEX(Matrizes!$B$5:$D$7,IF(B62<=1,1,IF(B62<=2,2,3)),IF(B61<=4,1,IF(B61<=15,2,3))) -> 1 | C63: Índice saída CE | D63: =INDEX(Matrizes!$B$5:$D$7,IF(D62<=1,1,IF(D62<=3,2,3)),IF(D61<=5,1,IF(D61<=19,2,3))) -> 1
A64: Índice adotado | B64: =INDEX(Matrizes!$B$5:$D$7,IF(D60<=1,1,IF(D60<=2,2,3)),IF(B60<=4,1,IF(B60<=15,2,3))) -> 2 | C64: Complexidade | D64: =INDEX(Matrizes!$B$10:$D$10,1,B64) -> Moderada
A65: Peso apropriado ao tipo | B65: =INDEX(Matrizes!$B$13:$D$17,MATCH("EE",Matrizes!$A$13:$A$17,0),B64) -> 4 | C65: PF desta função | D65: =B65 -> 4
A67: Justificativa da contagem | B67: TD usa somente itens que atravessam a fronteira. Uma mensagem de resultado e um conjunto de comandos. Dados internos não somam TD.
A69: Fluxo da função — leitura do protótipo real
A70: Entrada / contexto | B70: nome; marca; categoria
A71: Acionamento | B71: Incluir modelo. Comando real: /modelos; /excluir/modelo/{id}
A72: Resultado / saída | B72: Modelo salvo.
A73: Evidência visual | B73: Capturas da aplicação nas páginas seguintes. Veja a legenda de cada estado e a origem registrada.
A75: EE04 — captura real 1/2
A76: Inclusão de modelo temporário de demonstração, antes de enviar.
A77: Origem: http://localhost:8080/modelos | Capturada em: 2026-10-25T22:02:48.817Z | EE04-entrada.png
A131: EE04 — captura real 2/2
A132: Modelo salvo pela aplicação; operação realmente executada.
A133: Origem: http://localhost:8080/modelos | Capturada em: 2026-10-25T22:02:49.041Z | EE04-saida.png

Sheet EE05
A1: EE05 — Alterar modelo
A2: Sistema e tipo | B2: Estoque Inteligente — EE
A3: Intenção / finalidade | B3: Alterar modelo
A4: Fronteira e classificação | B4: Entrada externa: mantém ALIs ou altera comportamento. Chamadas auxiliares não são novas funções.
A5: Rota / contexto | B5: /modelos; /excluir/modelo/{id}
A6: Permissões | B6: Permissão cadastros para manutenção; consultar para leitura quando aplicável. Loja sempre validada.
A7: Evidência atual | B7: ModeloProdutoService.salvar
A8: Dados internos / regra | B8: A01: código e cadastro anterior; A09: registro de alteração.
A10: Item que cruza a fronteira | B10: Fluxo | C10: TD entrada | D10: TD saída exclusiva
A11: modelo | B11: Entrada | C11: =IF(AND(A11<>"",B11<>"Saída",COUNTIF($A$11:A11,A11)=1),1,0) -> 1 | D11: =IF(AND(A11<>"",B11="Saída",COUNTIF($A$11:A11,A11)=1),1,0) -> 0
A12: nome | B12: Entrada | C12: =IF(AND(A12<>"",B12<>"Saída",COUNTIF($A$11:A12,A12)=1),1,0) -> 1 | D12: =IF(AND(A12<>"",B12="Saída",COUNTIF($A$11:A12,A12)=1),1,0) -> 0
A13: marca | B13: Entrada | C13: =IF(AND(A13<>"",B13<>"Saída",COUNTIF($A$11:A13,A13)=1),1,0) -> 1 | D13: =IF(AND(A13<>"",B13="Saída",COUNTIF($A$11:A13,A13)=1),1,0) -> 0
A14: categoria | B14: Entrada | C14: =IF(AND(A14<>"",B14<>"Saída",COUNTIF($A$11:A14,A14)=1),1,0) -> 1 | D14: =IF(AND(A14<>"",B14="Saída",COUNTIF($A$11:A14,A14)=1),1,0) -> 0
A15: acionamento | B15: Controle | C15: =IF(AND(A15<>"",B15<>"Saída",COUNTIF($A$11:A15,A15)=1),1,0) -> 1 | D15: =IF(AND(A15<>"",B15="Saída",COUNTIF($A$11:A15,A15)=1),1,0) -> 0
A16: mensagem de resultado | B16: Saída | C16: =IF(AND(A16<>"",B16<>"Saída",COUNTIF($A$11:A16,A16)=1),1,0) -> 0 | D16: =IF(AND(A16<>"",B16="Saída",COUNTIF($A$11:A16,A16)=1),1,0) -> 1
C17: =IF(AND(A17<>"",B17<>"Saída",COUNTIF($A$11:A17,A17)=1),1,0) -> 0 | D17: =IF(AND(A17<>"",B17="Saída",COUNTIF($A$11:A17,A17)=1),1,0) -> 0
C18: =IF(AND(A18<>"",B18<>"Saída",COUNTIF($A$11:A18,A18)=1),1,0) -> 0 | D18: =IF(AND(A18<>"",B18="Saída",COUNTIF($A$11:A18,A18)=1),1,0) -> 0
C19: =IF(AND(A19<>"",B19<>"Saída",COUNTIF($A$11:A19,A19)=1),1,0) -> 0 | D19: =IF(AND(A19<>"",B19="Saída",COUNTIF($A$11:A19,A19)=1),1,0) -> 0
C20: =IF(AND(A20<>"",B20<>"Saída",COUNTIF($A$11:A20,A20)=1),1,0) -> 0 | D20: =IF(AND(A20<>"",B20="Saída",COUNTIF($A$11:A20,A20)=1),1,0) -> 0
C21: =IF(AND(A21<>"",B21<>"Saída",COUNTIF($A$11:A21,A21)=1),1,0) -> 0 | D21: =IF(AND(A21<>"",B21="Saída",COUNTIF($A$11:A21,A21)=1),1,0) -> 0
C22: =IF(AND(A22<>"",B22<>"Saída",COUNTIF($A$11:A22,A22)=1),1,0) -> 0 | D22: =IF(AND(A22<>"",B22="Saída",COUNTIF($A$11:A22,A22)=1),1,0) -> 0
C23: =IF(AND(A23<>"",B23<>"Saída",COUNTIF($A$11:A23,A23)=1),1,0) -> 0 | D23: =IF(AND(A23<>"",B23="Saída",COUNTIF($A$11:A23,A23)=1),1,0) -> 0
C24: =IF(AND(A24<>"",B24<>"Saída",COUNTIF($A$11:A24,A24)=1),1,0) -> 0 | D24: =IF(AND(A24<>"",B24="Saída",COUNTIF($A$11:A24,A24)=1),1,0) -> 0
C25: =IF(AND(A25<>"",B25<>"Saída",COUNTIF($A$11:A25,A25)=1),1,0) -> 0 | D25: =IF(AND(A25<>"",B25="Saída",COUNTIF($A$11:A25,A25)=1),1,0) -> 0
C26: =IF(AND(A26<>"",B26<>"Saída",COUNTIF($A$11:A26,A26)=1),1,0) -> 0 | D26: =IF(AND(A26<>"",B26="Saída",COUNTIF($A$11:A26,A26)=1),1,0) -> 0
C27: =IF(AND(A27<>"",B27<>"Saída",COUNTIF($A$11:A27,A27)=1),1,0) -> 0 | D27: =IF(AND(A27<>"",B27="Saída",COUNTIF($A$11:A27,A27)=1),1,0) -> 0
C28: =IF(AND(A28<>"",B28<>"Saída",COUNTIF($A$11:A28,A28)=1),1,0) -> 0 | D28: =IF(AND(A28<>"",B28="Saída",COUNTIF($A$11:A28,A28)=1),1,0) -> 0
... C42: =IF(AND(A42<>"",B42<>"Saída",COUNTIF($A$11:A42,A42)=1),1,0) -> 0 | D42: =IF(AND(A42<>"",B42="Saída",COUNTIF($A$11:A42,A42)=1),1,0) -> 0
A44: Arquivos referenciados (cada grupo uma única vez)
A45: ALI / AIE | B45: Finalidade da referência | C45: AR entrada CE | D45: AR saída CE
A46: A01 | B46: Modelos de produto | C46: 1 | D46: 1
A47: A09 | B47: Auditoria consultável | C47: 1 | D47: 1
A57: Regra AR / RL | B57: União dos ALIs lidos/mantidos. Arquivo lido e mantido conta uma vez; autorização técnica transversal não multiplica AR.
A59: Contagem calculada — entradas editáveis acima
A60: TD total distinto | B60: =SUM(C11:D42) -> 6 | C60: AR distintos | D60: =COUNTA(A46:A56) -> 2
A61: TD entrada CE | B61: =SUM(C11:C42) -> 5 | C61: TD saída sem repetição | D61: =SUM(D11:D42) -> 1
A62: AR entrada CE | B62: =SUM(C46:C56) -> 2 | C62: AR saída CE | D62: =SUM(D46:D56) -> 2
A63: Índice entrada CE | B63: =INDEX(Matrizes!$B$5:$D$7,IF(B62<=1,1,IF(B62<=2,2,3)),IF(B61<=4,1,IF(B61<=15,2,3))) -> 2 | C63: Índice saída CE | D63: =INDEX(Matrizes!$B$5:$D$7,IF(D62<=1,1,IF(D62<=3,2,3)),IF(D61<=5,1,IF(D61<=19,2,3))) -> 1
A64: Índice adotado | B64: =INDEX(Matrizes!$B$5:$D$7,IF(D60<=1,1,IF(D60<=2,2,3)),IF(B60<=4,1,IF(B60<=15,2,3))) -> 2 | C64: Complexidade | D64: =INDEX(Matrizes!$B$10:$D$10,1,B64) -> Moderada
A65: Peso apropriado ao tipo | B65: =INDEX(Matrizes!$B$13:$D$17,MATCH("EE",Matrizes!$A$13:$A$17,0),B64) -> 4 | C65: PF desta função | D65: =B65 -> 4
A67: Justificativa da contagem | B67: TD usa somente itens que atravessam a fronteira. Uma mensagem de resultado e um conjunto de comandos. Dados internos não somam TD.
A69: Fluxo da função — leitura do protótipo real
A70: Entrada / contexto | B70: modelo; nome; marca; categoria
A71: Acionamento | B71: Alterar modelo. Comando real: /modelos; /excluir/modelo/{id}
A72: Resultado / saída | B72: Modelo salvo.
A73: Evidência visual | B73: Capturas da aplicação nas páginas seguintes. Veja a legenda de cada estado e a origem registrada.
A75: EE05 — captura real 1/2
A76: Alteração real do modelo temporário.
A77: Origem: http://localhost:8080/modelos?id=16 | Capturada em: 2026-10-25T22:02:49.204Z | EE05-entrada.png
A131: EE05 — captura real 2/2
A132: Alteração enviada e concluída.
A133: Origem: http://localhost:8080/modelos | Capturada em: 2026-10-25T22:02:49.737Z | EE05-saida.png

Sheet EE06
A1: EE06 — Excluir modelo
A2: Sistema e tipo | B2: Estoque Inteligente — EE
A3: Intenção / finalidade | B3: Excluir modelo
A4: Fronteira e classificação | B4: Entrada externa: mantém ALIs ou altera comportamento. Chamadas auxiliares não são novas funções.
A5: Rota / contexto | B5: /modelos; /excluir/modelo/{id}
A6: Permissões | B6: Permissão cadastros para manutenção; consultar para leitura quando aplicável. Loja sempre validada.
A7: Evidência atual | B7: ModeloProdutoService.excluir
A8: Dados internos / regra | B8: A02: referência ao modelo bloqueia exclusão; A01: código; A09: registro da exclusão.
A10: Item que cruza a fronteira | B10: Fluxo | C10: TD entrada | D10: TD saída exclusiva
A11: modelo | B11: Entrada | C11: =IF(AND(A11<>"",B11<>"Saída",COUNTIF($A$11:A11,A11)=1),1,0) -> 1 | D11: =IF(AND(A11<>"",B11="Saída",COUNTIF($A$11:A11,A11)=1),1,0) -> 0
A12: acionamento | B12: Controle | C12: =IF(AND(A12<>"",B12<>"Saída",COUNTIF($A$11:A12,A12)=1),1,0) -> 1 | D12: =IF(AND(A12<>"",B12="Saída",COUNTIF($A$11:A12,A12)=1),1,0) -> 0
A13: mensagem de resultado | B13: Saída | C13: =IF(AND(A13<>"",B13<>"Saída",COUNTIF($A$11:A13,A13)=1),1,0) -> 0 | D13: =IF(AND(A13<>"",B13="Saída",COUNTIF($A$11:A13,A13)=1),1,0) -> 1
C14: =IF(AND(A14<>"",B14<>"Saída",COUNTIF($A$11:A14,A14)=1),1,0) -> 0 | D14: =IF(AND(A14<>"",B14="Saída",COUNTIF($A$11:A14,A14)=1),1,0) -> 0
C15: =IF(AND(A15<>"",B15<>"Saída",COUNTIF($A$11:A15,A15)=1),1,0) -> 0 | D15: =IF(AND(A15<>"",B15="Saída",COUNTIF($A$11:A15,A15)=1),1,0) -> 0
C16: =IF(AND(A16<>"",B16<>"Saída",COUNTIF($A$11:A16,A16)=1),1,0) -> 0 | D16: =IF(AND(A16<>"",B16="Saída",COUNTIF($A$11:A16,A16)=1),1,0) -> 0
C17: =IF(AND(A17<>"",B17<>"Saída",COUNTIF($A$11:A17,A17)=1),1,0) -> 0 | D17: =IF(AND(A17<>"",B17="Saída",COUNTIF($A$11:A17,A17)=1),1,0) -> 0
C18: =IF(AND(A18<>"",B18<>"Saída",COUNTIF($A$11:A18,A18)=1),1,0) -> 0 | D18: =IF(AND(A18<>"",B18="Saída",COUNTIF($A$11:A18,A18)=1),1,0) -> 0
C19: =IF(AND(A19<>"",B19<>"Saída",COUNTIF($A$11:A19,A19)=1),1,0) -> 0 | D19: =IF(AND(A19<>"",B19="Saída",COUNTIF($A$11:A19,A19)=1),1,0) -> 0
C20: =IF(AND(A20<>"",B20<>"Saída",COUNTIF($A$11:A20,A20)=1),1,0) -> 0 | D20: =IF(AND(A20<>"",B20="Saída",COUNTIF($A$11:A20,A20)=1),1,0) -> 0
C21: =IF(AND(A21<>"",B21<>"Saída",COUNTIF($A$11:A21,A21)=1),1,0) -> 0 | D21: =IF(AND(A21<>"",B21="Saída",COUNTIF($A$11:A21,A21)=1),1,0) -> 0
C22: =IF(AND(A22<>"",B22<>"Saída",COUNTIF($A$11:A22,A22)=1),1,0) -> 0 | D22: =IF(AND(A22<>"",B22="Saída",COUNTIF($A$11:A22,A22)=1),1,0) -> 0
C23: =IF(AND(A23<>"",B23<>"Saída",COUNTIF($A$11:A23,A23)=1),1,0) -> 0 | D23: =IF(AND(A23<>"",B23="Saída",COUNTIF($A$11:A23,A23)=1),1,0) -> 0
C24: =IF(AND(A24<>"",B24<>"Saída",COUNTIF($A$11:A24,A24)=1),1,0) -> 0 | D24: =IF(AND(A24<>"",B24="Saída",COUNTIF($A$11:A24,A24)=1),1,0) -> 0
C25: =IF(AND(A25<>"",B25<>"Saída",COUNTIF($A$11:A25,A25)=1),1,0) -> 0 | D25: =IF(AND(A25<>"",B25="Saída",COUNTIF($A$11:A25,A25)=1),1,0) -> 0
... C42: =IF(AND(A42<>"",B42<>"Saída",COUNTIF($A$11:A42,A42)=1),1,0) -> 0 | D42: =IF(AND(A42<>"",B42="Saída",COUNTIF($A$11:A42,A42)=1),1,0) -> 0
A44: Arquivos referenciados (cada grupo uma única vez)
A45: ALI / AIE | B45: Finalidade da referência | C45: AR entrada CE | D45: AR saída CE
A46: A01 | B46: Modelos de produto | C46: 1 | D46: 1
A47: A02 | B47: Produtos | C47: 1 | D47: 1
A48: A09 | B48: Auditoria consultável | C48: 1 | D48: 1
A57: Regra AR / RL | B57: União dos ALIs lidos/mantidos. Arquivo lido e mantido conta uma vez; autorização técnica transversal não multiplica AR.
A59: Contagem calculada — entradas editáveis acima
A60: TD total distinto | B60: =SUM(C11:D42) -> 3 | C60: AR distintos | D60: =COUNTA(A46:A56) -> 3
A61: TD entrada CE | B61: =SUM(C11:C42) -> 2 | C61: TD saída sem repetição | D61: =SUM(D11:D42) -> 1
A62: AR entrada CE | B62: =SUM(C46:C56) -> 3 | C62: AR saída CE | D62: =SUM(D46:D56) -> 3
A63: Índice entrada CE | B63: =INDEX(Matrizes!$B$5:$D$7,IF(B62<=1,1,IF(B62<=2,2,3)),IF(B61<=4,1,IF(B61<=15,2,3))) -> 2 | C63: Índice saída CE | D63: =INDEX(Matrizes!$B$5:$D$7,IF(D62<=1,1,IF(D62<=3,2,3)),IF(D61<=5,1,IF(D61<=19,2,3))) -> 1
A64: Índice adotado | B64: =INDEX(Matrizes!$B$5:$D$7,IF(D60<=1,1,IF(D60<=2,2,3)),IF(B60<=4,1,IF(B60<=15,2,3))) -> 2 | C64: Complexidade | D64: =INDEX(Matrizes!$B$10:$D$10,1,B64) -> Moderada
A65: Peso apropriado ao tipo | B65: =INDEX(Matrizes!$B$13:$D$17,MATCH("EE",Matrizes!$A$13:$A$17,0),B64) -> 4 | C65: PF desta função | D65: =B65 -> 4
A67: Justificativa da contagem | B67: TD usa somente itens que atravessam a fronteira. Uma mensagem de resultado e um conjunto de comandos. Dados internos não somam TD.
A69: Fluxo da função — leitura do protótipo real
A70: Entrada / contexto | B70: modelo
A71: Acionamento | B71: Excluir modelo. Comando real: /modelos; /excluir/modelo/{id}
A72: Resultado / saída | B72: Modelo excluído fisicamente se não estiver vinculado a produtos.
A73: Evidência visual | B73: Capturas da aplicação nas páginas seguintes. Veja a legenda de cada estado e a origem registrada.
A75: EE06 — captura real 1/2
A76: Modelo temporário selecionado para exclusão física; sem produtos vinculados.
A77: Origem: http://localhost:8080/modelos?id=16 | Capturada em: 2026-10-25T22:02:49.885Z | EE06-entrada.png
A131: EE06 — captura real 2/2
A132: Exclusão física realmente executada; registro temporário removido.
A133: Origem: http://localhost:8080/modelos | Capturada em: 2026-10-25T22:02:50.066Z | EE06-saida.png

Sheet EE07
A1: EE07 — Incluir posição
A2: Sistema e tipo | B2: Estoque Inteligente — EE
A3: Intenção / finalidade | B3: Incluir posição
A4: Fronteira e classificação | B4: Entrada externa: mantém ALIs ou altera comportamento. Chamadas auxiliares não são novas funções.
A5: Rota / contexto | B5: /posicoes; /excluir/posicao/{id}
A6: Permissões | B6: Permissão cadastros para manutenção; consultar para leitura quando aplicável. Loja sempre validada.
A7: Evidência atual | B7: PosicaoService.salvar
A8: Dados internos / regra | B8: A03: loja, código, setor, linha, coluna, capacidade, unidade, dispositivo, pino e ativo; identificação gerada no cadastro. A09: loja, responsável, ação posicao.salvar, detalhe com a identificação da posição e data gerada. Auditoria é manutenção interna, sem TD extras na interface.
A10: Item que cruza a fronteira | B10: Fluxo | C10: TD entrada | D10: TD saída exclusiva
A11: código | B11: Entrada | C11: =IF(AND(A11<>"",B11<>"Saída",COUNTIF($A$11:A11,A11)=1),1,0) -> 1 | D11: =IF(AND(A11<>"",B11="Saída",COUNTIF($A$11:A11,A11)=1),1,0) -> 0
A12: setor | B12: Entrada | C12: =IF(AND(A12<>"",B12<>"Saída",COUNTIF($A$11:A12,A12)=1),1,0) -> 1 | D12: =IF(AND(A12<>"",B12="Saída",COUNTIF($A$11:A12,A12)=1),1,0) -> 0
A13: linha | B13: Entrada | C13: =IF(AND(A13<>"",B13<>"Saída",COUNTIF($A$11:A13,A13)=1),1,0) -> 1 | D13: =IF(AND(A13<>"",B13="Saída",COUNTIF($A$11:A13,A13)=1),1,0) -> 0
A14: coluna | B14: Entrada | C14: =IF(AND(A14<>"",B14<>"Saída",COUNTIF($A$11:A14,A14)=1),1,0) -> 1 | D14: =IF(AND(A14<>"",B14="Saída",COUNTIF($A$11:A14,A14)=1),1,0) -> 0
A15: capacidade | B15: Entrada | C15: =IF(AND(A15<>"",B15<>"Saída",COUNTIF($A$11:A15,A15)=1),1,0) -> 1 | D15: =IF(AND(A15<>"",B15="Saída",COUNTIF($A$11:A15,A15)=1),1,0) -> 0
A16: unidade | B16: Entrada | C16: =IF(AND(A16<>"",B16<>"Saída",COUNTIF($A$11:A16,A16)=1),1,0) -> 1 | D16: =IF(AND(A16<>"",B16="Saída",COUNTIF($A$11:A16,A16)=1),1,0) -> 0
A17: dispositivo | B17: Entrada | C17: =IF(AND(A17<>"",B17<>"Saída",COUNTIF($A$11:A17,A17)=1),1,0) -> 1 | D17: =IF(AND(A17<>"",B17="Saída",COUNTIF($A$11:A17,A17)=1),1,0) -> 0
A18: pino | B18: Entrada | C18: =IF(AND(A18<>"",B18<>"Saída",COUNTIF($A$11:A18,A18)=1),1,0) -> 1 | D18: =IF(AND(A18<>"",B18="Saída",COUNTIF($A$11:A18,A18)=1),1,0) -> 0
A19: acionamento | B19: Controle | C19: =IF(AND(A19<>"",B19<>"Saída",COUNTIF($A$11:A19,A19)=1),1,0) -> 1 | D19: =IF(AND(A19<>"",B19="Saída",COUNTIF($A$11:A19,A19)=1),1,0) -> 0
A20: mensagem de resultado | B20: Saída | C20: =IF(AND(A20<>"",B20<>"Saída",COUNTIF($A$11:A20,A20)=1),1,0) -> 0 | D20: =IF(AND(A20<>"",B20="Saída",COUNTIF($A$11:A20,A20)=1),1,0) -> 1
C21: =IF(AND(A21<>"",B21<>"Saída",COUNTIF($A$11:A21,A21)=1),1,0) -> 0 | D21: =IF(AND(A21<>"",B21="Saída",COUNTIF($A$11:A21,A21)=1),1,0) -> 0
C22: =IF(AND(A22<>"",B22<>"Saída",COUNTIF($A$11:A22,A22)=1),1,0) -> 0 | D22: =IF(AND(A22<>"",B22="Saída",COUNTIF($A$11:A22,A22)=1),1,0) -> 0
C23: =IF(AND(A23<>"",B23<>"Saída",COUNTIF($A$11:A23,A23)=1),1,0) -> 0 | D23: =IF(AND(A23<>"",B23="Saída",COUNTIF($A$11:A23,A23)=1),1,0) -> 0
C24: =IF(AND(A24<>"",B24<>"Saída",COUNTIF($A$11:A24,A24)=1),1,0) -> 0 | D24: =IF(AND(A24<>"",B24="Saída",COUNTIF($A$11:A24,A24)=1),1,0) -> 0
C25: =IF(AND(A25<>"",B25<>"Saída",COUNTIF($A$11:A25,A25)=1),1,0) -> 0 | D25: =IF(AND(A25<>"",B25="Saída",COUNTIF($A$11:A25,A25)=1),1,0) -> 0
C26: =IF(AND(A26<>"",B26<>"Saída",COUNTIF($A$11:A26,A26)=1),1,0) -> 0 | D26: =IF(AND(A26<>"",B26="Saída",COUNTIF($A$11:A26,A26)=1),1,0) -> 0
C27: =IF(AND(A27<>"",B27<>"Saída",COUNTIF($A$11:A27,A27)=1),1,0) -> 0 | D27: =IF(AND(A27<>"",B27="Saída",COUNTIF($A$11:A27,A27)=1),1,0) -> 0
C28: =IF(AND(A28<>"",B28<>"Saída",COUNTIF($A$11:A28,A28)=1),1,0) -> 0 | D28: =IF(AND(A28<>"",B28="Saída",COUNTIF($A$11:A28,A28)=1),1,0) -> 0
C29: =IF(AND(A29<>"",B29<>"Saída",COUNTIF($A$11:A29,A29)=1),1,0) -> 0 | D29: =IF(AND(A29<>"",B29="Saída",COUNTIF($A$11:A29,A29)=1),1,0) -> 0
C30: =IF(AND(A30<>"",B30<>"Saída",COUNTIF($A$11:A30,A30)=1),1,0) -> 0 | D30: =IF(AND(A30<>"",B30="Saída",COUNTIF($A$11:A30,A30)=1),1,0) -> 0
C31: =IF(AND(A31<>"",B31<>"Saída",COUNTIF($A$11:A31,A31)=1),1,0) -> 0 | D31: =IF(AND(A31<>"",B31="Saída",COUNTIF($A$11:A31,A31)=1),1,0) -> 0
C32: =IF(AND(A32<>"",B32<>"Saída",COUNTIF($A$11:A32,A32)=1),1,0) -> 0 | D32: =IF(AND(A32<>"",B32="Saída",COUNTIF($A$11:A32,A32)=1),1,0) -> 0
... C42: =IF(AND(A42<>"",B42<>"Saída",COUNTIF($A$11:A42,A42)=1),1,0) -> 0 | D42: =IF(AND(A42<>"",B42="Saída",COUNTIF($A$11:A42,A42)=1),1,0) -> 0
A44: Arquivos referenciados (cada grupo uma única vez)
A45: ALI / AIE | B45: Finalidade da referência | C45: AR entrada CE | D45: AR saída CE
A46: A03 | B46: Posições | C46: 1 | D46: 1
A47: A09 | B47: Auditoria consultável | C47: 1 | D47: 1
A57: Regra AR / RL | B57: União dos ALIs lidos/mantidos. Arquivo lido e mantido conta uma vez; autorização técnica transversal não multiplica AR.
A59: Contagem calculada — entradas editáveis acima
A60: TD total distinto | B60: =SUM(C11:D42) -> 10 | C60: AR distintos | D60: =COUNTA(A46:A56) -> 2
A61: TD entrada CE | B61: =SUM(C11:C42) -> 9 | C61: TD saída sem repetição | D61: =SUM(D11:D42) -> 1
A62: AR entrada CE | B62: =SUM(C46:C56) -> 2 | C62: AR saída CE | D62: =SUM(D46:D56) -> 2
A63: Índice entrada CE | B63: =INDEX(Matrizes!$B$5:$D$7,IF(B62<=1,1,IF(B62<=2,2,3)),IF(B61<=4,1,IF(B61<=15,2,3))) -> 2 | C63: Índice saída CE | D63: =INDEX(Matrizes!$B$5:$D$7,IF(D62<=1,1,IF(D62<=3,2,3)),IF(D61<=5,1,IF(D61<=19,2,3))) -> 1
A64: Índice adotado | B64: =INDEX(Matrizes!$B$5:$D$7,IF(D60<=1,1,IF(D60<=2,2,3)),IF(B60<=4,1,IF(B60<=15,2,3))) -> 2 | C64: Complexidade | D64: =INDEX(Matrizes!$B$10:$D$10,1,B64) -> Moderada
A65: Peso apropriado ao tipo | B65: =INDEX(Matrizes!$B$13:$D$17,MATCH("EE",Matrizes!$A$13:$A$17,0),B64) -> 4 | C65: PF desta função | D65: =B65 -> 4
A67: Justificativa da contagem | B67: TD usa somente itens que atravessam a fronteira. Uma mensagem de resultado e um conjunto de comandos. Dados internos não somam TD.
A69: Fluxo da função — leitura do protótipo real
A70: Entrada / contexto | B70: código; setor; linha; coluna; capacidade; unidade; dispositivo; pino
A71: Acionamento | B71: Incluir posição. Comando real: /posicoes; /excluir/posicao/{id}
A72: Resultado / saída | B72: Posição salva.
A73: Evidência visual | B73: Capturas da aplicação nas páginas seguintes. Veja a legenda de cada estado e a origem registrada.
A75: EE07 — captura real 1/2
A76: Formulário real antes da requisição autenticada; registros próprios da loja APF de demonstração.
A77: Origem: http://localhost:8080/posicoes | Capturada em: 2026-10-25T22:10:54.583Z | EE07-entrada.png
A131: EE07 — captura real 2/2
A132: Operação realmente enviada e confirmada; dados da loja APF de demonstração.
A133: Origem: http://localhost:8080/posicoes | Capturada em: 2026-10-25T22:10:55.207Z | EE07-saida.png

Sheet EE08
A1: EE08 — Alterar posição
A2: Sistema e tipo | B2: Estoque Inteligente — EE
A3: Intenção / finalidade | B3: Alterar posição
A4: Fronteira e classificação | B4: Entrada externa: mantém ALIs ou altera comportamento. Chamadas auxiliares não são novas funções.
A5: Rota / contexto | B5: /posicoes; /excluir/posicao/{id}
A6: Permissões | B6: Permissão cadastros para manutenção; consultar para leitura quando aplicável. Loja sempre validada.
A7: Evidência atual | B7: PosicaoService.salvar
A8: Dados internos / regra | B8: A03: unidade anterior; A04: vínculos existentes; A09: registro da alteração.
A10: Item que cruza a fronteira | B10: Fluxo | C10: TD entrada | D10: TD saída exclusiva
A11: posição | B11: Entrada | C11: =IF(AND(A11<>"",B11<>"Saída",COUNTIF($A$11:A11,A11)=1),1,0) -> 1 | D11: =IF(AND(A11<>"",B11="Saída",COUNTIF($A$11:A11,A11)=1),1,0) -> 0
A12: código | B12: Entrada | C12: =IF(AND(A12<>"",B12<>"Saída",COUNTIF($A$11:A12,A12)=1),1,0) -> 1 | D12: =IF(AND(A12<>"",B12="Saída",COUNTIF($A$11:A12,A12)=1),1,0) -> 0
A13: setor | B13: Entrada | C13: =IF(AND(A13<>"",B13<>"Saída",COUNTIF($A$11:A13,A13)=1),1,0) -> 1 | D13: =IF(AND(A13<>"",B13="Saída",COUNTIF($A$11:A13,A13)=1),1,0) -> 0
A14: linha | B14: Entrada | C14: =IF(AND(A14<>"",B14<>"Saída",COUNTIF($A$11:A14,A14)=1),1,0) -> 1 | D14: =IF(AND(A14<>"",B14="Saída",COUNTIF($A$11:A14,A14)=1),1,0) -> 0
A15: coluna | B15: Entrada | C15: =IF(AND(A15<>"",B15<>"Saída",COUNTIF($A$11:A15,A15)=1),1,0) -> 1 | D15: =IF(AND(A15<>"",B15="Saída",COUNTIF($A$11:A15,A15)=1),1,0) -> 0
A16: capacidade | B16: Entrada | C16: =IF(AND(A16<>"",B16<>"Saída",COUNTIF($A$11:A16,A16)=1),1,0) -> 1 | D16: =IF(AND(A16<>"",B16="Saída",COUNTIF($A$11:A16,A16)=1),1,0) -> 0
A17: unidade | B17: Entrada | C17: =IF(AND(A17<>"",B17<>"Saída",COUNTIF($A$11:A17,A17)=1),1,0) -> 1 | D17: =IF(AND(A17<>"",B17="Saída",COUNTIF($A$11:A17,A17)=1),1,0) -> 0
A18: dispositivo | B18: Entrada | C18: =IF(AND(A18<>"",B18<>"Saída",COUNTIF($A$11:A18,A18)=1),1,0) -> 1 | D18: =IF(AND(A18<>"",B18="Saída",COUNTIF($A$11:A18,A18)=1),1,0) -> 0
A19: pino | B19: Entrada | C19: =IF(AND(A19<>"",B19<>"Saída",COUNTIF($A$11:A19,A19)=1),1,0) -> 1 | D19: =IF(AND(A19<>"",B19="Saída",COUNTIF($A$11:A19,A19)=1),1,0) -> 0
A20: acionamento | B20: Controle | C20: =IF(AND(A20<>"",B20<>"Saída",COUNTIF($A$11:A20,A20)=1),1,0) -> 1 | D20: =IF(AND(A20<>"",B20="Saída",COUNTIF($A$11:A20,A20)=1),1,0) -> 0
A21: mensagem de resultado | B21: Saída | C21: =IF(AND(A21<>"",B21<>"Saída",COUNTIF($A$11:A21,A21)=1),1,0) -> 0 | D21: =IF(AND(A21<>"",B21="Saída",COUNTIF($A$11:A21,A21)=1),1,0) -> 1
C22: =IF(AND(A22<>"",B22<>"Saída",COUNTIF($A$11:A22,A22)=1),1,0) -> 0 | D22: =IF(AND(A22<>"",B22="Saída",COUNTIF($A$11:A22,A22)=1),1,0) -> 0
C23: =IF(AND(A23<>"",B23<>"Saída",COUNTIF($A$11:A23,A23)=1),1,0) -> 0 | D23: =IF(AND(A23<>"",B23="Saída",COUNTIF($A$11:A23,A23)=1),1,0) -> 0
C24: =IF(AND(A24<>"",B24<>"Saída",COUNTIF($A$11:A24,A24)=1),1,0) -> 0 | D24: =IF(AND(A24<>"",B24="Saída",COUNTIF($A$11:A24,A24)=1),1,0) -> 0
C25: =IF(AND(A25<>"",B25<>"Saída",COUNTIF($A$11:A25,A25)=1),1,0) -> 0 | D25: =IF(AND(A25<>"",B25="Saída",COUNTIF($A$11:A25,A25)=1),1,0) -> 0
C26: =IF(AND(A26<>"",B26<>"Saída",COUNTIF($A$11:A26,A26)=1),1,0) -> 0 | D26: =IF(AND(A26<>"",B26="Saída",COUNTIF($A$11:A26,A26)=1),1,0) -> 0
C27: =IF(AND(A27<>"",B27<>"Saída",COUNTIF($A$11:A27,A27)=1),1,0) -> 0 | D27: =IF(AND(A27<>"",B27="Saída",COUNTIF($A$11:A27,A27)=1),1,0) -> 0
C28: =IF(AND(A28<>"",B28<>"Saída",COUNTIF($A$11:A28,A28)=1),1,0) -> 0 | D28: =IF(AND(A28<>"",B28="Saída",COUNTIF($A$11:A28,A28)=1),1,0) -> 0
C29: =IF(AND(A29<>"",B29<>"Saída",COUNTIF($A$11:A29,A29)=1),1,0) -> 0 | D29: =IF(AND(A29<>"",B29="Saída",COUNTIF($A$11:A29,A29)=1),1,0) -> 0
C30: =IF(AND(A30<>"",B30<>"Saída",COUNTIF($A$11:A30,A30)=1),1,0) -> 0 | D30: =IF(AND(A30<>"",B30="Saída",COUNTIF($A$11:A30,A30)=1),1,0) -> 0
C31: =IF(AND(A31<>"",B31<>"Saída",COUNTIF($A$11:A31,A31)=1),1,0) -> 0 | D31: =IF(AND(A31<>"",B31="Saída",COUNTIF($A$11:A31,A31)=1),1,0) -> 0
C32: =IF(AND(A32<>"",B32<>"Saída",COUNTIF($A$11:A32,A32)=1),1,0) -> 0 | D32: =IF(AND(A32<>"",B32="Saída",COUNTIF($A$11:A32,A32)=1),1,0) -> 0
C33: =IF(AND(A33<>"",B33<>"Saída",COUNTIF($A$11:A33,A33)=1),1,0) -> 0 | D33: =IF(AND(A33<>"",B33="Saída",COUNTIF($A$11:A33,A33)=1),1,0) -> 0
... C42: =IF(AND(A42<>"",B42<>"Saída",COUNTIF($A$11:A42,A42)=1),1,0) -> 0 | D42: =IF(AND(A42<>"",B42="Saída",COUNTIF($A$11:A42,A42)=1),1,0) -> 0
A44: Arquivos referenciados (cada grupo uma única vez)
A45: ALI / AIE | B45: Finalidade da referência | C45: AR entrada CE | D45: AR saída CE
A46: A03 | B46: Posições | C46: 1 | D46: 1
A47: A04 | B47: Estoque por posição / vínculos | C47: 1 | D47: 1
A48: A09 | B48: Auditoria consultável | C48: 1 | D48: 1
A57: Regra AR / RL | B57: União dos ALIs lidos/mantidos. Arquivo lido e mantido conta uma vez; autorização técnica transversal não multiplica AR.
A59: Contagem calculada — entradas editáveis acima
A60: TD total distinto | B60: =SUM(C11:D42) -> 11 | C60: AR distintos | D60: =COUNTA(A46:A56) -> 3
A61: TD entrada CE | B61: =SUM(C11:C42) -> 10 | C61: TD saída sem repetição | D61: =SUM(D11:D42) -> 1
A62: AR entrada CE | B62: =SUM(C46:C56) -> 3 | C62: AR saída CE | D62: =SUM(D46:D56) -> 3
A63: Índice entrada CE | B63: =INDEX(Matrizes!$B$5:$D$7,IF(B62<=1,1,IF(B62<=2,2,3)),IF(B61<=4,1,IF(B61<=15,2,3))) -> 3 | C63: Índice saída CE | D63: =INDEX(Matrizes!$B$5:$D$7,IF(D62<=1,1,IF(D62<=3,2,3)),IF(D61<=5,1,IF(D61<=19,2,3))) -> 1
A64: Índice adotado | B64: =INDEX(Matrizes!$B$5:$D$7,IF(D60<=1,1,IF(D60<=2,2,3)),IF(B60<=4,1,IF(B60<=15,2,3))) -> 3 | C64: Complexidade | D64: =INDEX(Matrizes!$B$10:$D$10,1,B64) -> Complexa
A65: Peso apropriado ao tipo | B65: =INDEX(Matrizes!$B$13:$D$17,MATCH("EE",Matrizes!$A$13:$A$17,0),B64) -> 6 | C65: PF desta função | D65: =B65 -> 6
A67: Justificativa da contagem | B67: TD usa somente itens que atravessam a fronteira. Uma mensagem de resultado e um conjunto de comandos. Dados internos não somam TD.
A69: Fluxo da função — leitura do protótipo real
A70: Entrada / contexto | B70: posição; código; setor; linha; coluna; capacidade; unidade; dispositivo; pino
A71: Acionamento | B71: Alterar posição. Comando real: /posicoes; /excluir/posicao/{id}
A72: Resultado / saída | B72: Posição salva; troca de unidade exige ausência de vínculos.
A73: Evidência visual | B73: Capturas da aplicação nas páginas seguintes. Veja a legenda de cada estado e a origem registrada.
A75: EE08 — captura real 1/2
A76: Formulário real antes da requisição autenticada; registros próprios da loja APF de demonstração.
A77: Origem: http://localhost:8080/posicoes?id=27 | Capturada em: 2026-10-25T22:10:56.137Z | EE08-entrada.png
A131: EE08 — captura real 2/2
A132: Operação realmente enviada e confirmada; dados da loja APF de demonstração.
A133: Origem: http://localhost:8080/posicoes | Capturada em: 2026-10-25T22:10:56.342Z | EE08-saida.png

Sheet EE09
A1: EE09 — Excluir posição logicamente
A2: Sistema e tipo | B2: Estoque Inteligente — EE
A3: Intenção / finalidade | B3: Excluir posição logicamente
A4: Fronteira e classificação | B4: Entrada externa: mantém ALIs ou altera comportamento. Chamadas auxiliares não são novas funções.
A5: Rota / contexto | B5: /posicoes; /excluir/posicao/{id}
A6: Permissões | B6: Permissão cadastros para manutenção; consultar para leitura quando aplicável. Loja sempre validada.
A7: Evidência atual | B7: PosicaoService.excluir
A8: Dados internos / regra | B8: A03: ativo; A04: quantidade e vínculos vazios; A09: registro da exclusão.
A10: Item que cruza a fronteira | B10: Fluxo | C10: TD entrada | D10: TD saída exclusiva
A11: posição | B11: Entrada | C11: =IF(AND(A11<>"",B11<>"Saída",COUNTIF($A$11:A11,A11)=1),1,0) -> 1 | D11: =IF(AND(A11<>"",B11="Saída",COUNTIF($A$11:A11,A11)=1),1,0) -> 0
A12: acionamento | B12: Controle | C12: =IF(AND(A12<>"",B12<>"Saída",COUNTIF($A$11:A12,A12)=1),1,0) -> 1 | D12: =IF(AND(A12<>"",B12="Saída",COUNTIF($A$11:A12,A12)=1),1,0) -> 0
A13: mensagem de resultado | B13: Saída | C13: =IF(AND(A13<>"",B13<>"Saída",COUNTIF($A$11:A13,A13)=1),1,0) -> 0 | D13: =IF(AND(A13<>"",B13="Saída",COUNTIF($A$11:A13,A13)=1),1,0) -> 1
C14: =IF(AND(A14<>"",B14<>"Saída",COUNTIF($A$11:A14,A14)=1),1,0) -> 0 | D14: =IF(AND(A14<>"",B14="Saída",COUNTIF($A$11:A14,A14)=1),1,0) -> 0
C15: =IF(AND(A15<>"",B15<>"Saída",COUNTIF($A$11:A15,A15)=1),1,0) -> 0 | D15: =IF(AND(A15<>"",B15="Saída",COUNTIF($A$11:A15,A15)=1),1,0) -> 0
C16: =IF(AND(A16<>"",B16<>"Saída",COUNTIF($A$11:A16,A16)=1),1,0) -> 0 | D16: =IF(AND(A16<>"",B16="Saída",COUNTIF($A$11:A16,A16)=1),1,0) -> 0
C17: =IF(AND(A17<>"",B17<>"Saída",COUNTIF($A$11:A17,A17)=1),1,0) -> 0 | D17: =IF(AND(A17<>"",B17="Saída",COUNTIF($A$11:A17,A17)=1),1,0) -> 0
C18: =IF(AND(A18<>"",B18<>"Saída",COUNTIF($A$11:A18,A18)=1),1,0) -> 0 | D18: =IF(AND(A18<>"",B18="Saída",COUNTIF($A$11:A18,A18)=1),1,0) -> 0
C19: =IF(AND(A19<>"",B19<>"Saída",COUNTIF($A$11:A19,A19)=1),1,0) -> 0 | D19: =IF(AND(A19<>"",B19="Saída",COUNTIF($A$11:A19,A19)=1),1,0) -> 0
C20: =IF(AND(A20<>"",B20<>"Saída",COUNTIF($A$11:A20,A20)=1),1,0) -> 0 | D20: =IF(AND(A20<>"",B20="Saída",COUNTIF($A$11:A20,A20)=1),1,0) -> 0
C21: =IF(AND(A21<>"",B21<>"Saída",COUNTIF($A$11:A21,A21)=1),1,0) -> 0 | D21: =IF(AND(A21<>"",B21="Saída",COUNTIF($A$11:A21,A21)=1),1,0) -> 0
C22: =IF(AND(A22<>"",B22<>"Saída",COUNTIF($A$11:A22,A22)=1),1,0) -> 0 | D22: =IF(AND(A22<>"",B22="Saída",COUNTIF($A$11:A22,A22)=1),1,0) -> 0
C23: =IF(AND(A23<>"",B23<>"Saída",COUNTIF($A$11:A23,A23)=1),1,0) -> 0 | D23: =IF(AND(A23<>"",B23="Saída",COUNTIF($A$11:A23,A23)=1),1,0) -> 0
C24: =IF(AND(A24<>"",B24<>"Saída",COUNTIF($A$11:A24,A24)=1),1,0) -> 0 | D24: =IF(AND(A24<>"",B24="Saída",COUNTIF($A$11:A24,A24)=1),1,0) -> 0
C25: =IF(AND(A25<>"",B25<>"Saída",COUNTIF($A$11:A25,A25)=1),1,0) -> 0 | D25: =IF(AND(A25<>"",B25="Saída",COUNTIF($A$11:A25,A25)=1),1,0) -> 0
... C42: =IF(AND(A42<>"",B42<>"Saída",COUNTIF($A$11:A42,A42)=1),1,0) -> 0 | D42: =IF(AND(A42<>"",B42="Saída",COUNTIF($A$11:A42,A42)=1),1,0) -> 0
A44: Arquivos referenciados (cada grupo uma única vez)
A45: ALI / AIE | B45: Finalidade da referência | C45: AR entrada CE | D45: AR saída CE
A46: A03 | B46: Posições | C46: 1 | D46: 1
A47: A04 | B47: Estoque por posição / vínculos | C47: 1 | D47: 1
A48: A09 | B48: Auditoria consultável | C48: 1 | D48: 1
A57: Regra AR / RL | B57: União dos ALIs lidos/mantidos. Arquivo lido e mantido conta uma vez; autorização técnica transversal não multiplica AR.
A59: Contagem calculada — entradas editáveis acima
A60: TD total distinto | B60: =SUM(C11:D42) -> 3 | C60: AR distintos | D60: =COUNTA(A46:A56) -> 3
A61: TD entrada CE | B61: =SUM(C11:C42) -> 2 | C61: TD saída sem repetição | D61: =SUM(D11:D42) -> 1
A62: AR entrada CE | B62: =SUM(C46:C56) -> 3 | C62: AR saída CE | D62: =SUM(D46:D56) -> 3
A63: Índice entrada CE | B63: =INDEX(Matrizes!$B$5:$D$7,IF(B62<=1,1,IF(B62<=2,2,3)),IF(B61<=4,1,IF(B61<=15,2,3))) -> 2 | C63: Índice saída CE | D63: =INDEX(Matrizes!$B$5:$D$7,IF(D62<=1,1,IF(D62<=3,2,3)),IF(D61<=5,1,IF(D61<=19,2,3))) -> 1
A64: Índice adotado | B64: =INDEX(Matrizes!$B$5:$D$7,IF(D60<=1,1,IF(D60<=2,2,3)),IF(B60<=4,1,IF(B60<=15,2,3))) -> 2 | C64: Complexidade | D64: =INDEX(Matrizes!$B$10:$D$10,1,B64) -> Moderada
A65: Peso apropriado ao tipo | B65: =INDEX(Matrizes!$B$13:$D$17,MATCH("EE",Matrizes!$A$13:$A$17,0),B64) -> 4 | C65: PF desta função | D65: =B65 -> 4
A67: Justificativa da contagem | B67: TD usa somente itens que atravessam a fronteira. Uma mensagem de resultado e um conjunto de comandos. Dados internos não somam TD.
A69: Fluxo da função — leitura do protótipo real
A70: Entrada / contexto | B70: posição
A71: Acionamento | B71: Excluir posição logicamente. Comando real: /posicoes; /excluir/posicao/{id}
A72: Resultado / saída | B72: Posição desativada; histórico preservado; exige saldo zero.
A73: Evidência visual | B73: Capturas da aplicação nas páginas seguintes. Veja a legenda de cada estado e a origem registrada.
A75: EE09 — captura real 1/2
A76: Formulário real antes da requisição autenticada; registros próprios da loja APF de demonstração.
A77: Origem: http://localhost:8080/posicoes?id=27 | Capturada em: 2026-10-25T22:12:59.520Z | EE09-entrada.png
A131: EE09 — captura real 2/2
A132: Operação realmente enviada e confirmada; dados da loja APF de demonstração.
A133: Origem: http://localhost:8080/posicoes | Capturada em: 2026-10-25T22:12:59.666Z | EE09-saida.png

Sheet EE10
A1: EE10 — Incluir vínculo
A2: Sistema e tipo | B2: Estoque Inteligente — EE
A3: Intenção / finalidade | B3: Incluir vínculo
A4: Fronteira e classificação | B4: Entrada externa: mantém ALIs ou altera comportamento. Chamadas auxiliares não são novas funções.
A5: Rota / contexto | B5: /vinculos (create/update/delete)
A6: Permissões | B6: Permissão cadastros para manutenção; consultar para leitura quando aplicável. Loja sempre validada.
A7: Evidência atual | B7: VinculoService.salvar
A8: Dados internos / regra | B8: A02: identificação do produto, unidade e ativo. A03: identificação da posição, unidade e ativo. A04: loja, produto, posição e quantidade inicial zero. A09: loja, responsável, ação vinculo.criar, detalhe produto:posição e data gerada. O usuário informa somente produto/posição; quantidade não é entrada desta EE.
A10: Item que cruza a fronteira | B10: Fluxo | C10: TD entrada | D10: TD saída exclusiva
A11: produto | B11: Entrada | C11: =IF(AND(A11<>"",B11<>"Saída",COUNTIF($A$11:A11,A11)=1),1,0) -> 1 | D11: =IF(AND(A11<>"",B11="Saída",COUNTIF($A$11:A11,A11)=1),1,0) -> 0
A12: posição | B12: Entrada | C12: =IF(AND(A12<>"",B12<>"Saída",COUNTIF($A$11:A12,A12)=1),1,0) -> 1 | D12: =IF(AND(A12<>"",B12="Saída",COUNTIF($A$11:A12,A12)=1),1,0) -> 0
A13: acionamento | B13: Controle | C13: =IF(AND(A13<>"",B13<>"Saída",COUNTIF($A$11:A13,A13)=1),1,0) -> 1 | D13: =IF(AND(A13<>"",B13="Saída",COUNTIF($A$11:A13,A13)=1),1,0) -> 0
A14: mensagem de resultado | B14: Saída | C14: =IF(AND(A14<>"",B14<>"Saída",COUNTIF($A$11:A14,A14)=1),1,0) -> 0 | D14: =IF(AND(A14<>"",B14="Saída",COUNTIF($A$11:A14,A14)=1),1,0) -> 1
C15: =IF(AND(A15<>"",B15<>"Saída",COUNTIF($A$11:A15,A15)=1),1,0) -> 0 | D15: =IF(AND(A15<>"",B15="Saída",COUNTIF($A$11:A15,A15)=1),1,0) -> 0
C16: =IF(AND(A16<>"",B16<>"Saída",COUNTIF($A$11:A16,A16)=1),1,0) -> 0 | D16: =IF(AND(A16<>"",B16="Saída",COUNTIF($A$11:A16,A16)=1),1,0) -> 0
C17: =IF(AND(A17<>"",B17<>"Saída",COUNTIF($A$11:A17,A17)=1),1,0) -> 0 | D17: =IF(AND(A17<>"",B17="Saída",COUNTIF($A$11:A17,A17)=1),1,0) -> 0
C18: =IF(AND(A18<>"",B18<>"Saída",COUNTIF($A$11:A18,A18)=1),1,0) -> 0 | D18: =IF(AND(A18<>"",B18="Saída",COUNTIF($A$11:A18,A18)=1),1,0) -> 0
C19: =IF(AND(A19<>"",B19<>"Saída",COUNTIF($A$11:A19,A19)=1),1,0) -> 0 | D19: =IF(AND(A19<>"",B19="Saída",COUNTIF($A$11:A19,A19)=1),1,0) -> 0
C20: =IF(AND(A20<>"",B20<>"Saída",COUNTIF($A$11:A20,A20)=1),1,0) -> 0 | D20: =IF(AND(A20<>"",B20="Saída",COUNTIF($A$11:A20,A20)=1),1,0) -> 0
C21: =IF(AND(A21<>"",B21<>"Saída",COUNTIF($A$11:A21,A21)=1),1,0) -> 0 | D21: =IF(AND(A21<>"",B21="Saída",COUNTIF($A$11:A21,A21)=1),1,0) -> 0
C22: =IF(AND(A22<>"",B22<>"Saída",COUNTIF($A$11:A22,A22)=1),1,0) -> 0 | D22: =IF(AND(A22<>"",B22="Saída",COUNTIF($A$11:A22,A22)=1),1,0) -> 0
C23: =IF(AND(A23<>"",B23<>"Saída",COUNTIF($A$11:A23,A23)=1),1,0) -> 0 | D23: =IF(AND(A23<>"",B23="Saída",COUNTIF($A$11:A23,A23)=1),1,0) -> 0
C24: =IF(AND(A24<>"",B24<>"Saída",COUNTIF($A$11:A24,A24)=1),1,0) -> 0 | D24: =IF(AND(A24<>"",B24="Saída",COUNTIF($A$11:A24,A24)=1),1,0) -> 0
C25: =IF(AND(A25<>"",B25<>"Saída",COUNTIF($A$11:A25,A25)=1),1,0) -> 0 | D25: =IF(AND(A25<>"",B25="Saída",COUNTIF($A$11:A25,A25)=1),1,0) -> 0
C26: =IF(AND(A26<>"",B26<>"Saída",COUNTIF($A$11:A26,A26)=1),1,0) -> 0 | D26: =IF(AND(A26<>"",B26="Saída",COUNTIF($A$11:A26,A26)=1),1,0) -> 0
... C42: =IF(AND(A42<>"",B42<>"Saída",COUNTIF($A$11:A42,A42)=1),1,0) -> 0 | D42: =IF(AND(A42<>"",B42="Saída",COUNTIF($A$11:A42,A42)=1),1,0) -> 0
A44: Arquivos referenciados (cada grupo uma única vez)
A45: ALI / AIE | B45: Finalidade da referência | C45: AR entrada CE | D45: AR saída CE
A46: A02 | B46: Produtos | C46: 1 | D46: 1
A47: A03 | B47: Posições | C47: 1 | D47: 1
A48: A04 | B48: Estoque por posição / vínculos | C48: 1 | D48: 1
A49: A09 | B49: Auditoria consultável | C49: 1 | D49: 1
A57: Regra AR / RL | B57: União dos ALIs lidos/mantidos. Arquivo lido e mantido conta uma vez; autorização técnica transversal não multiplica AR.
A59: Contagem calculada — entradas editáveis acima
A60: TD total distinto | B60: =SUM(C11:D42) -> 4 | C60: AR distintos | D60: =COUNTA(A46:A56) -> 4
A61: TD entrada CE | B61: =SUM(C11:C42) -> 3 | C61: TD saída sem repetição | D61: =SUM(D11:D42) -> 1
A62: AR entrada CE | B62: =SUM(C46:C56) -> 4 | C62: AR saída CE | D62: =SUM(D46:D56) -> 4
